Workbook

Sheet 收支紀錄
A1: 時間戳記 | B1: 類別 | C1: 金額(NTD) | D1: 日期(其他請填yyyymmdd, ex:20240808) | E1: 收入主分類 | F1: 工作選項 | G1: 其他業外選項 | H1: 支出主分類 | I1: 食品酒水選項 | J1: 日常生活選項 | K1: 房屋支出選項 | L1: 行車交通選項 | M1: 休閒娛樂選項 | N1: 稅金保險選項 | O1: 醫療費用選項 | P1: 進修學習選項 | Q1: 人情往來 | R1: 其他投資選項 | S1: 備註 | T1: 是否紀錄於總表?
A2: 45487.513 | B2: 支出 | C2: 82 | D2: 45487 | H2: 行車交通 | L2: 火車費
A3: 45487.513 | B3: 支出 | C3: 148 | D3: 45487 | H3: 行車交通 | L3: 加油
A4: 45487.514 | B4: 支出 | C4: 100 | D4: 45487 | H4: 休閒娛樂 | M4: 運動健身
A5: 45487.514 | B5: 支出 | C5: 60 | D5: 45487 | H5: 日常生活 | J5: 日常用品
A6: 45487.514 | B6: 支出 | C6: 77 | D6: 45487 | H6: 行車交通 | L6: 火車費
A7: 45487.514 | B7: 支出 | C7: 380 | D7: 45487 | H7: 食品酒水 | I7: 早餐
A8: 45487.515 | B8: 支出 | C8: 510 | D8: 45487 | H8: 食品酒水 | I8: 晚餐
A9: 45487.515 | B9: 支出 | C9: 359 | D9: 45487 | H9: 日常生活 | J9: 日常用品
A10: 45487.515 | B10: 支出 | C10: 233 | D10: 45487 | H10: 日常生活 | J10: 日常用品
A11: 45487.515 | B11: 支出 | C11: 20 | D11: 45487 | H11: 行車交通 | L11: 停車
A12: 45487.515 | B12: 支出 | C12: 78 | D12: 45487 | H12: 食品酒水 | I12: 早餐
A13: 45487.515 | B13: 支出 | C13: 515 | D13: 45487 | H13: 休閒娛樂 | M13: 公司福利金
A14: 45487.516 | B14: 支出 | C14: 1303 | D14: 45487 | H14: 食品酒水 | I14: 前月公司餐費扣款
A15: 45487.516 | B15: 支出 | C15: 180 | D15: 45487 | H15: 休閒娛樂 | M15: 運動健身
A16: 45487.516 | B16: 支出 | C16: 520 | D16: 45487 | H16: 食品酒水 | I16: 晚餐
A17: 45487.516 | B17: 支出 | C17: 211 | D17: 45487 | H17: 食品酒水 | I17: 食材
A18: 45487.516 | B18: 支出 | C18: 50 | D18: 45487 | H18: 食品酒水 | I18: 宵夜
A19: 45487.517 | B19: 支出 | C19: 100 | D19: 45487 | H19: 休閒娛樂 | M19: 運動健身
A20: 45487.517 | B20: 支出 | C20: 930 | D20: 45487 | H20: 行車交通 | L20: 高鐵
A21: 45487.517 | B21: 支出 | C21: 205 | D21: 45487 | H21: 食品酒水 | I21: 晚餐
A22: 45487.517 | B22: 支出 | C22: 99 | D22: 45487 | H22: 食品酒水 | I22: 宵夜
A23: 45487.517 | B23: 支出 | C23: 379 | D23: 45487 | H23: 食品酒水 | I23: 晚餐
A24: 45487.518 | B24: 支出 | C24: 45 | D24: 45487 | H24: 行車交通 | L24: 停車
A25: 45487.518 | B25: 支出 | C25: 798 | D25: 45487 | H25: 休閒娛樂 | M25: youtube Premium
A26: 45487.518 | B26: 支出 | C26: 391 | D26: 45487 | H26: 食品酒水 | I26: 晚餐
A27: 45487.518 | B27: 支出 | C27: 50 | D27: 45487 | H27: 行車交通 | L27: 停車
A28: 45487.518 | B28: 支出 | C28: 250 | D28: 45487 | H28: 食品酒水 | I28: 宵夜
A29: 45487.519 | B29: 支出 | C29: 460 | D29: 45487 | H29: 行車交通 | L29: 火車費
A30: 45487.91 | B30: 支出 | C30: 1118 | D30: 45487 | H30: 食品酒水 | I30: 食材
A31: 45488.35 | B31: 支出 | C31: 82 | D31: 45488 | H31: 行車交通 | L31: 火車費
A32: 45490.002 | B32: 收入 | C32: 930 | D32: 45489 | E32: 其他業外 | G32: 股票配息 | S32: 00751B | T32: 是
A33: 45491.968 | B33: 支出 | C33: 100 | D33: 45490 | H33: 休閒娛樂 | M33: 運動健身
A34: 45491.969 | B34: 支出 | C34: 23 | D34: 45490 | H34: 食品酒水 | I34: 飲料酒水
A35: 45493.357 | B35: 支出 | C35: 145 | D35: 45493 | H35: 食品酒水 | I35: 早餐
A36: 45493.406 | B36: 支出 | C36: 48 | D36: 45493 | H36: 食品酒水 | I36: 食材
A37: 45494.34 | B37: 支出 | C37: 58 | D37: 45494 | H37: 食品酒水 | I37: 早餐
A38: 45494.886 | B38: 支出 | C38: 200 | D38: 45494 | H38: 食品酒水 | I38: 午餐
A39: 45494.887 | B39: 支出 | C39: 140 | D39: 45494 | H39: 休閒娛樂 | M39: 運動健身
A40: 45494.887 | B40: 支出 | C40: 400 | D40: 45494 | H40: 食品酒水 | I40: 食材
A41: 45497.327 | B41: 支出 | C41: 50 | D41: 45497 | H41: 食品酒水 | I41: 早餐
A42: 45497.438 | B42: 支出 | C42: 723 | D42: 45497 | H42: 行車交通 | L42: 加油
A43: 45499.939 | B43: 支出 | C43: 600 | D43: 45499 | H43: 休閒娛樂 | M43: 剪髮
A44: 45500.347 | B44: 支出 | C44: 20 | D44: 45500 | H44: 行車交通 | L44: 捷運費
A45: 45500.829 | B45: 支出 | C45: 320 | D45: 45500 | H45: 食品酒水 | I45: 晚餐
A46: 45500.891 | B46: 支出 | C46: 424 | D46: 45500 | H46: 行車交通 | L46: 加油
A47: 45500.891 | B47: 支出 | C47: 284 | D47: 45500 | H47: 日常生活 | J47: 日常用品
A48: 45501.368 | B48: 支出 | C48: 157 | D48: 45501 | H48: 食品酒水 | I48: 早餐
A49: 45501.936 | B49: 支出 | C49: 6600 | D49: 45501 | H49: 人情往來 | Q49: 送禮請客 | S49: 中瑋萬豪婚禮2人 | T49: 是
A50: 45501.937 | B50: 支出 | C50: 20 | D50: 45501 | H50: 休閒娛樂 | M50: 旅遊度假
A51: 45501.937 | B51: 支出 | C51: 218 | D51: 45501 | H51: 食品酒水 | I51: 晚餐
A52: 45503.015 | B52: 支出 | C52: 728 | D52: 45503 | H52: 日常生活 | J52: 電話費
A53: 45503.906 | B53: 支出 | C53: 384 | D53: 45503 | H53: 房屋支出 | K53: 電費 | S53: 竹南電費 | T53: 是
A54: 45504.826 | B54: 支出 | C54: 126 | D54: 45504 | H54: 行車交通 | L54: 加油
A55: 45504.887 | B55: 支出 | C55: 160 | D55: 45504 | H55: 休閒娛樂 | M55: 休閒玩樂 | S55: HamiVedio
A56: 45505.932 | B56: 支出 | C56: 1500 | D56: 45502 | H56: 日常生活 | J56: 日常用品
A57: 45507.282 | B57: 支出 | C57: 794 | D57: 45506 | H57: 行車交通 | L57: 加油
A58: 45507.283 | B58: 支出 | C58: 40 | D58: 45507 | H58: 行車交通 | L58: 捷運費
A59: 45507.283 | B59: 支出 | C59: 765 | D59: 45507 | H59: 行車交通 | L59: 高鐵
A60: 45508.654 | B60: 支出 | C60: 30 | D60: 45508 | H60: 行車交通 | L60: 捷運費
A61: 45508.654 | B61: 支出 | C61: 765 | D61: 45508 | H61: 行車交通 | L61: 高鐵
A62: 45508.654 | B62: 支出 | C62: 40 | D62: 45508 | H62: 行車交通 | L62: 捷運費
A63: 45509.011 | B63: 支出 | C63: 30 | D63: 45507 | H63: 行車交通 | L63: 捷運費
A64: 45509.012 | B64: 支出 | C64: 800 | D64: 45507 | H64: 食品酒水 | I64: 午餐 | S64: 孫東寶88節餐5人
A65: 45510.008 | B65: 支出 | C65: 375 | D65: 45493 | H65: 食品酒水 | I65: 晚餐
A66: 45510.974 | B66: 支出 | C66: 2701 | D66: 45504 | H66: 稅金保險 | N66: 勞健保
A67: 45510.975 | B67: 支出 | C67: 515 | D67: 45509 | H67: 休閒娛樂 | M67: 公司福利金
A68: 45510.975 | B68: 支出 | C68: 1603 | D68: 45509 | H68: 食品酒水 | I68: 前月公司餐費扣款
A69: 45510.976 | B69: 支出 | C69: 3087 | D69: 45504 | H69: 投資及其他 | R69: 公司認股
A70: 45510.977 | B70: 收入 | C70: 102900 | D70: 45504 | E70: 工作 | F70: 底薪
A71: 45510.978 | B71: 收入 | C71: 17150 | D71: 45504 | E71: 工作 | F71: 加班/津貼 | S71: 特休折現 | T71: 是
A72: 45510.979 | B72: 收入 | C72: 5000 | D72: 45504 | E72: 工作 | F72: 加班/津貼 | S72: 體檢補助 | T72: 是
A73: 45510.981 | B73: 收入 | C73: 1185 | D73: 45497 | E73: 其他業外 | G73: 股票配息 | S73: 元大金 | T73: 是
A74: 45510.982 | B74: 收入 | C74: 1990 | D74: 45502 | E74: 其他業外 | G74: 股票配息 | S74: 國泰金 | T74: 是
A75: 45510.982 | B75: 收入 | C75: 990 | D75: 45503 | E75: 其他業外 | G75: 股票配息 | S75: 台泥 | T75: 是
A76: 45510.983 | B76: 收入 | C76: 1491 | D76: 45504 | E76: 其他業外 | G76: 股票配息 | S76: 開發金 | T76: 是
A77: 45510.997 | B77: 收入 | C77: 2370 | D77: 45488 | S77: 國泰美債20年 | T77: 是
A78: 45510.999 | B78: 收入 | C78: 1490 | D78: 45502 | E78: 其他業外 | G78: 股票配息 | S78: 正隆 | T78: 是
A79: 45510.999 | B79: 收入 | C79: 1390 | D79: 45485 | E79: 其他業外 | G79: 股票配息 | S79: 中再保 | T79: 是
A80: 45511.005 | B80: 收入 | C80: 100000 | D80: 45504 | E80: 工作 | F80: 年終/績效 | S80: 七月獎金 | T80: 是
A81: 45511.006 | B81: 支出 | C81: 7110 | D81: 45504 | H81: 稅金保險 | N81: 稅金 | S81: 獎金稅 | T81: 是
A82: 45511.008 | B82: 支出 | C82: 800 | D82: 45502 | H82: 行車交通 | L82: Etag
A83: 45519.383 | B83: 收入 | C83: 1000 | D83: 45519 | E83: 工作 | F83: 加班/津貼 | S83: 生日禮金 | T83: 是
A84: 45521.413 | B84: 收入 | C84: 172 | D84: 45523 | E84: 其他業外 | G84: 其他 | S84: 禾聯碩出借 | T84: 是
A85: 45523.56 | B85: 支出 | C85: 1679 | D85: 45523 | H85: 房屋支出 | K85: 電費
A86: 45526.009 | B86: 支出 | C86: 214 | D86: 45511 | H86: 食品酒水 | I86: 晚餐
A87: 45526.01 | B87: 支出 | C87: 1888 | D87: 45511 | H87: 休閒娛樂 | M87: 奢侈敗家 | S87: 麟洋紀念酒 | T87: 是
A88: 45526.012 | B88: 支出 | C88: 40 | D88: 45517 | H88: 行車交通 | L88: 捷運費
A89: 45526.012 | B89: 支出 | C89: 1040 | D89: 45517 | H89: 行車交通 | L89: 高鐵
A90: 45526.012 | B90: 支出 | C90: 655 | D90: 45517 | H90: 食品酒水 | I90: 晚餐
A91: 45526.012 | B91: 支出 | C91: 70 | D91: 45517 | H91: 日常生活 | J91: 洗衣
A92: 45526.013 | B92: 支出 | C92: 25 | D92: 45517 | H92: 行車交通 | L92: 捷運費
A93: 45526.013 | B93: 支出 | C93: 100 | D93: 45518 | H93: 休閒娛樂 | M93: 運動健身
A94: 45526.014 | B94: 支出 | C94: 149 | D94: 45519 | H94: 食品酒水 | I94: 餐飲票券 | S94: PChome 7-11禮券$200-$50P幣 | T94: 否
A95: 45526.014 | B95: 支出 | C95: 479 | D95: 45521 | H95: 食品酒水 | I95: 午餐
A96: 45526.014 | B96: 支出 | C96: 912 | D96: 45522 | H96: 行車交通 | L96: 加油
A97: 45526.015 | B97: 支出 | C97: 100 | D97: 45525 | H97: 休閒娛樂 | M97: 運動健身 | T97: 否
A98: 45526.015 | B98: 支出 | C98: 465 | D98: 45529 | H98: 行車交通 | L98: 火車費 | S98: 台鐵:高雄-台中 | T98: 否
A99: 45526.022 | B99: 支出 | C99: 40000 | D99: 45512 | H99: 休閒娛樂 | M99: 旅遊度假 | S99: 韓國旅遊兩人(大概值) | T99: 是
A100: 45526.025 | B100: 支出 | C100: 118 | D100: 45606 | H100: 休閒娛樂 | M100: 運動健身 | S100: 舒跑盃報名費$100+ibon手續費$18 | T100: 否
...

Sheet Calculation
B1: 工作 | F1: 其他業外
A2: 收入 | B2: 底薪 | C2: 加班/津貼 | D2: 年終/績效 | E2: 備註 | F2: 股票配息 | G2: 發票/彩券/中獎 | H2: 保險理賠 | I2: 租金 | J2: 房屋補貼 | K2: 其他 | L2: 備註
A3: 45474 | B3: =SUMIFS(INDIRECT("C"&$C$70&":C"), INDIRECT("B"&$C$70&":B"), ">="&$A3, INDIRECT("B"&$C$70&":B"), "<"&$A4, INDIRECT("F"&$C$70&":F"), B$2) -> 102900 | C3: =SUMIFS(INDIRECT("C"&$C$70&":C"), INDIRECT("B"&$C$70&":B"), ">="&$A3, INDIRECT("B"&$C$70&":B"), "<"&$A4, INDIRECT("F"&$C$70&":F"), C$2) -> 22150 | D3: =SUMIFS(INDIRECT("C"&$C$70&":C"), INDIRECT("B"&$C$70&":B"), ">="&$A3, INDIRECT("B"&$C$70&":B"), "<"&$A4, INDIRECT("F"&$C$70&":F"), D$2) -> 100000 | E3: =IFERROR(__xludf.DUMMYFUNCTION("TEXTJOIN("", "", TRUE, FILTER(INDIRECT(""U""&$C$70&"":U""), INDIRECT(""E""&$C$70&"":E"") = $B$1, INDIRECT(""B""&$C$70&"":B"") >= $A3, INDIRECT(""B""&$C$70&"":B"") <$A4))"),"$17150特休折現, $5000體檢補助, $100000七月獎金") -> $17150特休折現, $5000體檢補助, $100000七月獎金 | F3: =SUMIFS(INDIRECT("C"&$C$70&":C"), INDIRECT("B"&$C$70&":B"), ">="&$A3, INDIRECT("B"&$C$70&":B"), "<"&$A4, INDIRECT("G"&$C$70&":G"), F$2) -> 9466 | G3: =SUMIFS(INDIRECT("C"&$C$70&":C"), INDIRECT("B"&$C$70&":B"), ">="&$A3, INDIRECT("B"&$C$70&":B"), "<"&$A4, INDIRECT("G"&$C$70&":G"), G$2) -> 0 | H3: =SUMIFS(INDIRECT("C"&$C$70&":C"), INDIRECT("B"&$C$70&":B"), ">="&$A3, INDIRECT("B"&$C$70&":B"), "<"&$A4, INDIRECT("G"&$C$70&":G"), H$2) -> 0 | I3: =SUMIFS(INDIRECT("C"&$C$70&":C"), INDIRECT("B"&$C$70&":B"), ">="&$A3, INDIRECT("B"&$C$70&":B"), "<"&$A4, INDIRECT("G"&$C$70&":G"), I$2) -> 0 | J3: =SUMIFS(INDIRECT("C"&$C$70&":C"), INDIRECT("B"&$C$70&":B"), ">="&$A3, INDIRECT("B"&$C$70&":B"), "<"&$A4, INDIRECT("G"&$C$70&":G"), J$2) -> 0 | K3: =SUMIFS(INDIRECT("C"&$C$70&":C"), INDIRECT("B"&$C$70&":B"), ">="&$A3, INDIRECT("B"&$C$70&":B"), "<"&$A4, INDIRECT("G"&$C$70&":G"), K$2) -> 0 | L3: =IFERROR(__xludf.DUMMYFUNCTION("TEXTJOIN("", "", TRUE, FILTER(INDIRECT(""U""&$C$70&"":U""), INDIRECT(""E""&$C$70&"":E"") = $F$1, INDIRECT(""B""&$C$70&"":B"") >= $A3, INDIRECT(""B""&$C$70&"":B"") <$A4))"),"$930 00751B, $1185元大金, $1990國泰金, $990台泥, $1491開發金, $1490正隆, $1390中再保") -> $930 00751B, $1185元大金, $1990國泰金, $990台泥, $1491開發金, $1490正隆, $1390中再保
A4: 45505 | B4: =SUMIFS(INDIRECT("C"&$C$70&":C"), INDIRECT("B"&$C$70&":B"), ">="&$A4, INDIRECT("B"&$C$70&":B"), "<"&$A5, INDIRECT("F"&$C$70&":F"), B$2) -> 102900 | C4: =SUMIFS(INDIRECT("C"&$C$70&":C"), INDIRECT("B"&$C$70&":B"), ">="&$A4, INDIRECT("B"&$C$70&":B"), "<"&$A5, INDIRECT("F"&$C$70&":F"), C$2) -> 1000 | D4: =SUMIFS(INDIRECT("C"&$C$70&":C"), INDIRECT("B"&$C$70&":B"), ">="&$A4, INDIRECT("B"&$C$70&":B"), "<"&$A5, INDIRECT("F"&$C$70&":F"), D$2) -> 0 | E4: =IFERROR(__xludf.DUMMYFUNCTION("TEXTJOIN("", "", TRUE, FILTER(INDIRECT(""U""&$C$70&"":U""), INDIRECT(""E""&$C$70&"":E"") = $B$1, INDIRECT(""B""&$C$70&"":B"") >= $A4, INDIRECT(""B""&$C$70&"":B"") <$A5))"),"$1000生日禮金") -> $1000生日禮金 | F4: =SUMIFS(INDIRECT("C"&$C$70&":C"), INDIRECT("B"&$C$70&":B"), ">="&$A4, INDIRECT("B"&$C$70&":B"), "<"&$A5, INDIRECT("G"&$C$70&":G"), F$2) -> 13981 | G4: =SUMIFS(INDIRECT("C"&$C$70&":C"), INDIRECT("B"&$C$70&":B"), ">="&$A4, INDIRECT("B"&$C$70&":B"), "<"&$A5, INDIRECT("G"&$C$70&":G"), G$2) -> 200 | H4: =SUMIFS(INDIRECT("C"&$C$70&":C"), INDIRECT("B"&$C$70&":B"), ">="&$A4, INDIRECT("B"&$C$70&":B"), "<"&$A5, INDIRECT("G"&$C$70&":G"), H$2) -> 0 | I4: =SUMIFS(INDIRECT("C"&$C$70&":C"), INDIRECT("B"&$C$70&":B"), ">="&$A4, INDIRECT("B"&$C$70&":B"), "<"&$A5, INDIRECT("G"&$C$70&":G"), I$2) -> 0 | J4: =SUMIFS(INDIRECT("C"&$C$70&":C"), INDIRECT("B"&$C$70&":B"), ">="&$A4, INDIRECT("B"&$C$70&":B"), "<"&$A5, INDIRECT("G"&$C$70&":G"), J$2) -> 0 | K4: =SUMIFS(INDIRECT("C"&$C$70&":C"), INDIRECT("B"&$C$70&":B"), ">="&$A4, INDIRECT("B"&$C$70&":B"), "<"&$A5, INDIRECT("G"&$C$70&":G"), K$2) -> 172 | L4: =IFERROR(__xludf.DUMMYFUNCTION("TEXTJOIN("", "", TRUE, FILTER(INDIRECT(""U""&$C$70&"":U""), INDIRECT(""E""&$C$70&"":E"") = $F$1, INDIRECT(""B""&$C$70&"":B"") >= $A4, INDIRECT(""B""&$C$70&"":B"") <$A5))"),"$172禾聯碩出借, $1190皇鼎, $200發票, $850山隆, $2090亞泥, $390聯邦銀, $693中鋼, $973台中銀行, $1846第一金, $1642玉山金, $1845台新金, $2462華南金") -> $172禾聯碩出借, $1190皇鼎, $200發票, $850山隆, $2090亞泥, $390聯邦銀, $693中鋼, $973台中銀行, $1846第一金, $1642玉山金, $1845台新金, $2462華南金
A5: 45536 | B5: =SUMIFS(INDIRECT("C"&$C$70&":C"), INDIRECT("B"&$C$70&":B"), ">="&$A5, INDIRECT("B"&$C$70&":B"), "<"&$A6, INDIRECT("F"&$C$70&":F"), B$2) -> 102900 | C5: =SUMIFS(INDIRECT("C"&$C$70&":C"), INDIRECT("B"&$C$70&":B"), ">="&$A5, INDIRECT("B"&$C$70&":B"), "<"&$A6, INDIRECT("F"&$C$70&":F"), C$2) -> 1000 | D5: =SUMIFS(INDIRECT("C"&$C$70&":C"), INDIRECT("B"&$C$70&":B"), ">="&$A5, INDIRECT("B"&$C$70&":B"), "<"&$A6, INDIRECT("F"&$C$70&":F"), D$2) -> 0 | E5: =IFERROR(__xludf.DUMMYFUNCTION("TEXTJOIN("", "", TRUE, FILTER(INDIRECT(""U""&$C$70&"":U""), INDIRECT(""E""&$C$70&"":E"") = $B$1, INDIRECT(""B""&$C$70&"":B"") >= $A5, INDIRECT(""B""&$C$70&"":B"") <$A6))"),"$1000中秋獎金") -> $1000中秋獎金 | F5: =SUMIFS(INDIRECT("C"&$C$70&":C"), INDIRECT("B"&$C$70&":B"), ">="&$A5, INDIRECT("B"&$C$70&":B"), "<"&$A6, INDIRECT("G"&$C$70&":G"), F$2) -> 16544 | G5: =SUMIFS(INDIRECT("C"&$C$70&":C"), INDIRECT("B"&$C$70&":B"), ">="&$A5, INDIRECT("B"&$C$70&":B"), "<"&$A6, INDIRECT("G"&$C$70&":G"), G$2) -> 0 | H5: =SUMIFS(INDIRECT("C"&$C$70&":C"), INDIRECT("B"&$C$70&":B"), ">="&$A5, INDIRECT("B"&$C$70&":B"), "<"&$A6, INDIRECT("G"&$C$70&":G"), H$2) -> 0 | I5: =SUMIFS(INDIRECT("C"&$C$70&":C"), INDIRECT("B"&$C$70&":B"), ">="&$A5, INDIRECT("B"&$C$70&":B"), "<"&$A6, INDIRECT("G"&$C$70&":G"), I$2) -> 0 | J5: =SUMIFS(INDIRECT("C"&$C$70&":C"), INDIRECT("B"&$C$70&":B"), ">="&$A5, INDIRECT("B"&$C$70&":B"), "<"&$A6, INDIRECT("G"&$C$70&":G"), J$2) -> 0 | K5: =SUMIFS(INDIRECT("C"&$C$70&":C"), INDIRECT("B"&$C$70&":B"), ">="&$A5, INDIRECT("B"&$C$70&":B"), "<"&$A6, INDIRECT("G"&$C$70&":G"), K$2) -> 0 | L5: =IFERROR(__xludf.DUMMYFUNCTION("TEXTJOIN("", "", TRUE, FILTER(INDIRECT(""U""&$C$70&"":U""), INDIRECT(""E""&$C$70&"":E"") = $F$1, INDIRECT(""B""&$C$70&"":B"") >= $A5, INDIRECT(""B""&$C$70&"":B"") <$A6))"),"$3440元大美債, $2291台企銀, $1653兆豐金, $2590合庫金, $890高雄銀, $1690彰銀, $3990禾聯碩") -> $3440元大美債, $2291台企銀, $1653兆豐金, $2590合庫金, $890高雄銀, $1690彰銀, $3990禾聯碩
A6: 45566 | B6: =SUMIFS(INDIRECT("C"&$C$70&":C"), INDIRECT("B"&$C$70&":B"), ">="&$A6, INDIRECT("B"&$C$70&":B"), "<"&$A7, INDIRECT("F"&$C$70&":F"), B$2) -> 0 | C6: =SUMIFS(INDIRECT("C"&$C$70&":C"), INDIRECT("B"&$C$70&":B"), ">="&$A6, INDIRECT("B"&$C$70&":B"), "<"&$A7, INDIRECT("F"&$C$70&":F"), C$2) -> 0 | D6: =SUMIFS(INDIRECT("C"&$C$70&":C"), INDIRECT("B"&$C$70&":B"), ">="&$A6, INDIRECT("B"&$C$70&":B"), "<"&$A7, INDIRECT("F"&$C$70&":F"), D$2) -> 75500 | E6: =IFERROR(__xludf.DUMMYFUNCTION("TEXTJOIN("", "", TRUE, FILTER(INDIRECT(""U""&$C$70&"":U""), INDIRECT(""E""&$C$70&"":E"") = $B$1, INDIRECT(""B""&$C$70&"":B"") >= $A6, INDIRECT(""B""&$C$70&"":B"") <$A7))"),"") | F6: =SUMIFS(INDIRECT("C"&$C$70&":C"), INDIRECT("B"&$C$70&":B"), ">="&$A6, INDIRECT("B"&$C$70&":B"), "<"&$A7, INDIRECT("G"&$C$70&":G"), F$2) -> 6970 | G6: =SUMIFS(INDIRECT("C"&$C$70&":C"), INDIRECT("B"&$C$70&":B"), ">="&$A6, INDIRECT("B"&$C$70&":B"), "<"&$A7, INDIRECT("G"&$C$70&":G"), G$2) -> 0 | H6: =SUMIFS(INDIRECT("C"&$C$70&":C"), INDIRECT("B"&$C$70&":B"), ">="&$A6, INDIRECT("B"&$C$70&":B"), "<"&$A7, INDIRECT("G"&$C$70&":G"), H$2) -> 0 | I6: =SUMIFS(INDIRECT("C"&$C$70&":C"), INDIRECT("B"&$C$70&":B"), ">="&$A6, INDIRECT("B"&$C$70&":B"), "<"&$A7, INDIRECT("G"&$C$70&":G"), I$2) -> 0 | J6: =SUMIFS(INDIRECT("C"&$C$70&":C"), INDIRECT("B"&$C$70&":B"), ">="&$A6, INDIRECT("B"&$C$70&":B"), "<"&$A7, INDIRECT("G"&$C$70&":G"), J$2) -> 5000 | K6: =SUMIFS(INDIRECT("C"&$C$70&":C"), INDIRECT("B"&$C$70&":B"), ">="&$A6, INDIRECT("B"&$C$70&":B"), "<"&$A7, INDIRECT("G"&$C$70&":G"), K$2) -> 0 | L6: =IFERROR(__xludf.DUMMYFUNCTION("TEXTJOIN("", "", TRUE, FILTER(INDIRECT(""U""&$C$70&"":U""), INDIRECT(""E""&$C$70&"":E"") = $F$1, INDIRECT(""B""&$C$70&"":B"") >= $A6, INDIRECT(""B""&$C$70&"":B"") <$A7))"),"$5000文心1, $2290元大A級, $4190國泰美債, $490興富發") -> $5000文心1, $2290元大A級, $4190國泰美債, $490興富發
A7: 45597 | B7: =SUMIFS(INDIRECT("C"&$C$70&":C"), INDIRECT("B"&$C$70&":B"), ">="&$A7, INDIRECT("B"&$C$70&":B"), "<"&$A8, INDIRECT("F"&$C$70&":F"), B$2) -> 102900 | C7: =SUMIFS(INDIRECT("C"&$C$70&":C"), INDIRECT("B"&$C$70&":B"), ">="&$A7, INDIRECT("B"&$C$70&":B"), "<"&$A8, INDIRECT("F"&$C$70&":F"), C$2) -> 20000 | D7: =SUMIFS(INDIRECT("C"&$C$70&":C"), INDIRECT("B"&$C$70&":B"), ">="&$A7, INDIRECT("B"&$C$70&":B"), "<"&$A8, INDIRECT("F"&$C$70&":F"), D$2) -> 0 | E7: =IFERROR(__xludf.DUMMYFUNCTION("TEXTJOIN("", "", TRUE, FILTER(INDIRECT(""U""&$C$70&"":U""), INDIRECT(""E""&$C$70&"":E"") = $B$1, INDIRECT(""B""&$C$70&"":B"") >= $A7, INDIRECT(""B""&$C$70&"":B"") <$A8))"),"$20000旅遊補助") -> $20000旅遊補助 | F7: =SUMIFS(INDIRECT("C"&$C$70&":C"), INDIRECT("B"&$C$70&":B"), ">="&$A7, INDIRECT("B"&$C$70&":B"), "<"&$A8, INDIRECT("G"&$C$70&":G"), F$2) -> 4748 | G7: =SUMIFS(INDIRECT("C"&$C$70&":C"), INDIRECT("B"&$C$70&":B"), ">="&$A7, INDIRECT("B"&$C$70&":B"), "<"&$A8, INDIRECT("G"&$C$70&":G"), G$2) -> 0 | H7: =SUMIFS(INDIRECT("C"&$C$70&":C"), INDIRECT("B"&$C$70&":B"), ">="&$A7, INDIRECT("B"&$C$70&":B"), "<"&$A8, INDIRECT("G"&$C$70&":G"), H$2) -> 0 | I7: =SUMIFS(INDIRECT("C"&$C$70&":C"), INDIRECT("B"&$C$70&":B"), ">="&$A7, INDIRECT("B"&$C$70&":B"), "<"&$A8, INDIRECT("G"&$C$70&":G"), I$2) -> 0 | J7: =SUMIFS(INDIRECT("C"&$C$70&":C"), INDIRECT("B"&$C$70&":B"), ">="&$A7, INDIRECT("B"&$C$70&":B"), "<"&$A8, INDIRECT("G"&$C$70&":G"), J$2) -> 5000 | K7: =SUMIFS(INDIRECT("C"&$C$70&":C"), INDIRECT("B"&$C$70&":B"), ">="&$A7, INDIRECT("B"&$C$70&":B"), "<"&$A8, INDIRECT("G"&$C$70&":G"), K$2) -> 0 | L7: =IFERROR(__xludf.DUMMYFUNCTION("TEXTJOIN("", "", TRUE, FILTER(INDIRECT(""U""&$C$70&"":U""), INDIRECT(""E""&$C$70&"":E"") = $F$1, INDIRECT(""B""&$C$70&"":B"") >= $A7, INDIRECT(""B""&$C$70&"":B"") <$A8))"),"$5000文心1, $3953台灣中小, $795中信優息") -> $5000文心1, $3953台灣中小, $795中信優息
A8: 45627 | B8: =SUMIFS(INDIRECT("C"&$C$70&":C"), INDIRECT("B"&$C$70&":B"), ">="&$A8, INDIRECT("B"&$C$70&":B"), "<"&$A9, INDIRECT("F"&$C$70&":F"), B$2) -> 102900 | C8: =SUMIFS(INDIRECT("C"&$C$70&":C"), INDIRECT("B"&$C$70&":B"), ">="&$A8, INDIRECT("B"&$C$70&":B"), "<"&$A9, INDIRECT("F"&$C$70&":F"), C$2) -> 0 | D8: =SUMIFS(INDIRECT("C"&$C$70&":C"), INDIRECT("B"&$C$70&":B"), ">="&$A8, INDIRECT("B"&$C$70&":B"), "<"&$A9, INDIRECT("F"&$C$70&":F"), D$2) -> 0 | E8: =IFERROR(__xludf.DUMMYFUNCTION("TEXTJOIN("", "", TRUE, FILTER(INDIRECT(""U""&$C$70&"":U""), INDIRECT(""E""&$C$70&"":E"") = $B$1, INDIRECT(""B""&$C$70&"":B"") >= $A8, INDIRECT(""B""&$C$70&"":B"") <$A9))"),"") | F8: =SUMIFS(INDIRECT("C"&$C$70&":C"), INDIRECT("B"&$C$70&":B"), ">="&$A8, INDIRECT("B"&$C$70&":B"), "<"&$A9, INDIRECT("G"&$C$70&":G"), F$2) -> 7350 | G8: =SUMIFS(INDIRECT("C"&$C$70&":C"), INDIRECT("B"&$C$70&":B"), ">="&$A8, INDIRECT("B"&$C$70&":B"), "<"&$A9, INDIRECT("G"&$C$70&":G"), G$2) -> 4000 | H8: =SUMIFS(INDIRECT("C"&$C$70&":C"), INDIRECT("B"&$C$70&":B"), ">="&$A8, INDIRECT("B"&$C$70&":B"), "<"&$A9, INDIRECT("G"&$C$70&":G"), H$2) -> 0 | I8: =SUMIFS(INDIRECT("C"&$C$70&":C"), INDIRECT("B"&$C$70&":B"), ">="&$A8, INDIRECT("B"&$C$70&":B"), "<"&$A9, INDIRECT("G"&$C$70&":G"), I$2) -> 0 | J8: =SUMIFS(INDIRECT("C"&$C$70&":C"), INDIRECT("B"&$C$70&":B"), ">="&$A8, INDIRECT("B"&$C$70&":B"), "<"&$A9, INDIRECT("G"&$C$70&":G"), J$2) -> 5000 | K8: =SUMIFS(INDIRECT("C"&$C$70&":C"), INDIRECT("B"&$C$70&":B"), ">="&$A8, INDIRECT("B"&$C$70&":B"), "<"&$A9, INDIRECT("G"&$C$70&":G"), K$2) -> 0 | L8: =IFERROR(__xludf.DUMMYFUNCTION("TEXTJOIN("", "", TRUE, FILTER(INDIRECT(""U""&$C$70&"":U""), INDIRECT(""E""&$C$70&"":E"") = $F$1, INDIRECT(""B""&$C$70&"":B"") >= $A8, INDIRECT(""B""&$C$70&"":B"") <$A9))"),"$4000發票中獎, $440富邦台50, $5090美債20, $1820中信優息") -> $4000發票中獎, $440富邦台50, $5090美債20, $1820中信優息
A9: 45658 | B9: =SUMIFS(INDIRECT("C"&$C$70&":C"), INDIRECT("B"&$C$70&":B"), ">="&$A9, INDIRECT("B"&$C$70&":B"), "<"&$A10, INDIRECT("F"&$C$70&":F"), B$2) -> 102900 | C9: =SUMIFS(INDIRECT("C"&$C$70&":C"), INDIRECT("B"&$C$70&":B"), ">="&$A9, INDIRECT("B"&$C$70&":B"), "<"&$A10, INDIRECT("F"&$C$70&":F"), C$2) -> 447 | D9: =SUMIFS(INDIRECT("C"&$C$70&":C"), INDIRECT("B"&$C$70&":B"), ">="&$A9, INDIRECT("B"&$C$70&":B"), "<"&$A10, INDIRECT("F"&$C$70&":F"), D$2) -> 536987 | E9: =IFERROR(__xludf.DUMMYFUNCTION("TEXTJOIN("", "", TRUE, FILTER(INDIRECT(""U""&$C$70&"":U""), INDIRECT(""E""&$C$70&"":E"") = $B$1, INDIRECT(""B""&$C$70&"":B"") >= $A9, INDIRECT(""B""&$C$70&"":B"") <$A10))"),"$536987註1, $447調休") -> $536987註1, $447調休 | F9: =SUMIFS(INDIRECT("C"&$C$70&":C"), INDIRECT("B"&$C$70&":B"), ">="&$A9, INDIRECT("B"&$C$70&":B"), "<"&$A10, INDIRECT("G"&$C$70&":G"), F$2) -> 8710 | G9: =SUMIFS(INDIRECT("C"&$C$70&":C"), INDIRECT("B"&$C$70&":B"), ">="&$A9, INDIRECT("B"&$C$70&":B"), "<"&$A10, INDIRECT("G"&$C$70&":G"), G$2) -> 3659 | H9: =SUMIFS(INDIRECT("C"&$C$70&":C"), INDIRECT("B"&$C$70&":B"), ">="&$A9, INDIRECT("B"&$C$70&":B"), "<"&$A10, INDIRECT("G"&$C$70&":G"), H$2) -> 0 | I9: =SUMIFS(INDIRECT("C"&$C$70&":C"), INDIRECT("B"&$C$70&":B"), ">="&$A9, INDIRECT("B"&$C$70&":B"), "<"&$A10, INDIRECT("G"&$C$70&":G"), I$2) -> 0 | J9: =SUMIFS(INDIRECT("C"&$C$70&":C"), INDIRECT("B"&$C$70&":B"), ">="&$A9, INDIRECT("B"&$C$70&":B"), "<"&$A10, INDIRECT("G"&$C$70&":G"), J$2) -> 5000 | K9: =SUMIFS(INDIRECT("C"&$C$70&":C"), INDIRECT("B"&$C$70&":B"), ">="&$A9, INDIRECT("B"&$C$70&":B"), "<"&$A10, INDIRECT("G"&$C$70&":G"), K$2) -> 0 | L9: =IFERROR(__xludf.DUMMYFUNCTION("TEXTJOIN("", "", TRUE, FILTER(INDIRECT(""U""&$C$70&"":U""), INDIRECT(""E""&$C$70&"":E"") = $F$1, INDIRECT(""B""&$C$70&"":B"") >= $A9, INDIRECT(""B""&$C$70&"":B"") <$A10))"),"$3659紅包自己抽寶, $6890元大A級, $1820中信優息") -> $3659紅包自己抽寶, $6890元大A級, $1820中信優息
A10: 45689 | B10: =SUMIFS(INDIRECT("C"&$C$70&":C"), INDIRECT("B"&$C$70&":B"), ">="&$A10, INDIRECT("B"&$C$70&":B"), "<"&$A11, INDIRECT("F"&$C$70&":F"), B$2) -> 101185 | C10: =SUMIFS(INDIRECT("C"&$C$70&":C"), INDIRECT("B"&$C$70&":B"), ">="&$A10, INDIRECT("B"&$C$70&":B"), "<"&$A11, INDIRECT("F"&$C$70&":F"), C$2) -> 0 | D10: =SUMIFS(INDIRECT("C"&$C$70&":C"), INDIRECT("B"&$C$70&":B"), ">="&$A10, INDIRECT("B"&$C$70&":B"), "<"&$A11, INDIRECT("F"&$C$70&":F"), D$2) -> 0 | E10: =IFERROR(__xludf.DUMMYFUNCTION("TEXTJOIN("", "", TRUE, FILTER(INDIRECT(""U""&$C$70&"":U""), INDIRECT(""E""&$C$70&"":E"") = $B$1, INDIRECT(""B""&$C$70&"":B"") >= $A10, INDIRECT(""B""&$C$70&"":B"") <$A11))"),"$101185含請假扣款") -> $101185含請假扣款 | F10: =SUMIFS(INDIRECT("C"&$C$70&":C"), INDIRECT("B"&$C$70&":B"), ">="&$A10, INDIRECT("B"&$C$70&":B"), "<"&$A11, INDIRECT("G"&$C$70&":G"), F$2) -> 1680 | G10: =SUMIFS(INDIRECT("C"&$C$70&":C"), INDIRECT("B"&$C$70&":B"), ">="&$A10, INDIRECT("B"&$C$70&":B"), "<"&$A11, INDIRECT("G"&$C$70&":G"), G$2) -> 0 | H10: =SUMIFS(INDIRECT("C"&$C$70&":C"), INDIRECT("B"&$C$70&":B"), ">="&$A10, INDIRECT("B"&$C$70&":B"), "<"&$A11, INDIRECT("G"&$C$70&":G"), H$2) -> 0 | I10: =SUMIFS(INDIRECT("C"&$C$70&":C"), INDIRECT("B"&$C$70&":B"), ">="&$A10, INDIRECT("B"&$C$70&":B"), "<"&$A11, INDIRECT("G"&$C$70&":G"), I$2) -> 0 | J10: =SUMIFS(INDIRECT("C"&$C$70&":C"), INDIRECT("B"&$C$70&":B"), ">="&$A10, INDIRECT("B"&$C$70&":B"), "<"&$A11, INDIRECT("G"&$C$70&":G"), J$2) -> 5000 | K10: =SUMIFS(INDIRECT("C"&$C$70&":C"), INDIRECT("B"&$C$70&":B"), ">="&$A10, INDIRECT("B"&$C$70&":B"), "<"&$A11, INDIRECT("G"&$C$70&":G"), K$2) -> 500 | L10: =IFERROR(__xludf.DUMMYFUNCTION("TEXTJOIN("", "", TRUE, FILTER(INDIRECT(""U""&$C$70&"":U""), INDIRECT(""E""&$C$70&"":E"") = $F$1, INDIRECT(""B""&$C$70&"":B"") >= $A10, INDIRECT(""B""&$C$70&"":B"") <$A11))"),"$500除濕機退稅, $1680中信優息") -> $500除濕機退稅, $1680中信優息
A11: 45717 | B11: =SUMIFS(INDIRECT("C"&$C$70&":C"), INDIRECT("B"&$C$70&":B"), ">="&$A11, INDIRECT("B"&$C$70&":B"), "<"&$A12, INDIRECT("F"&$C$70&":F"), B$2) -> 101078 | C11: =SUMIFS(INDIRECT("C"&$C$70&":C"), INDIRECT("B"&$C$70&":B"), ">="&$A11, INDIRECT("B"&$C$70&":B"), "<"&$A12, INDIRECT("F"&$C$70&":F"), C$2) -> 7563 | D11: =SUMIFS(INDIRECT("C"&$C$70&":C"), INDIRECT("B"&$C$70&":B"), ">="&$A11, INDIRECT("B"&$C$70&":B"), "<"&$A12, INDIRECT("F"&$C$70&":F"), D$2) -> 0 | E11: =IFERROR(__xludf.DUMMYFUNCTION("TEXTJOIN("", "", TRUE, FILTER(INDIRECT(""U""&$C$70&"":U""), INDIRECT(""E""&$C$70&"":E"") = $B$1, INDIRECT(""B""&$C$70&"":B"") >= $A11, INDIRECT(""B""&$C$70&"":B"") <$A12))"),"$101078 $1822請假扣款, $7443加班, $120加班誤餐費") -> $101078 $1822請假扣款, $7443加班, $120加班誤餐費 | F11: =SUMIFS(INDIRECT("C"&$C$70&":C"), INDIRECT("B"&$C$70&":B"), ">="&$A11, INDIRECT("B"&$C$70&":B"), "<"&$A12, INDIRECT("G"&$C$70&":G"), F$2) -> 6930 | G11: =SUMIFS(INDIRECT("C"&$C$70&":C"), INDIRECT("B"&$C$70&":B"), ">="&$A11, INDIRECT("B"&$C$70&":B"), "<"&$A12, INDIRECT("G"&$C$70&":G"), G$2) -> 0 | H11: =SUMIFS(INDIRECT("C"&$C$70&":C"), INDIRECT("B"&$C$70&":B"), ">="&$A11, INDIRECT("B"&$C$70&":B"), "<"&$A12, INDIRECT("G"&$C$70&":G"), H$2) -> 0 | I11: =SUMIFS(INDIRECT("C"&$C$70&":C"), INDIRECT("B"&$C$70&":B"), ">="&$A11, INDIRECT("B"&$C$70&":B"), "<"&$A12, INDIRECT("G"&$C$70&":G"), I$2) -> 0 | J11: =SUMIFS(INDIRECT("C"&$C$70&":C"), INDIRECT("B"&$C$70&":B"), ">="&$A11, INDIRECT("B"&$C$70&":B"), "<"&$A12, INDIRECT("G"&$C$70&":G"), J$2) -> 5000 | K11: =SUMIFS(INDIRECT("C"&$C$70&":C"), INDIRECT("B"&$C$70&":B"), ">="&$A11, INDIRECT("B"&$C$70&":B"), "<"&$A12, INDIRECT("G"&$C$70&":G"), K$2) -> 0 | L11: =IFERROR(__xludf.DUMMYFUNCTION("TEXTJOIN("", "", TRUE, FILTER(INDIRECT(""U""&$C$70&"":U""), INDIRECT(""E""&$C$70&"":E"") = $F$1, INDIRECT(""B""&$C$70&"":B"") >= $A11, INDIRECT(""B""&$C$70&"":B"") <$A12))"),"$2430中信優息, $4500元大美債") -> $2430中信優息, $4500元大美債
A12: 45748 | B12: =SUMIFS(INDIRECT("C"&$C$70&":C"), INDIRECT("B"&$C$70&":B"), ">="&$A12, INDIRECT("B"&$C$70&":B"), "<"&$A13, INDIRECT("F"&$C$70&":F"), B$2) -> 102364 | C12: =SUMIFS(INDIRECT("C"&$C$70&":C"), INDIRECT("B"&$C$70&":B"), ">="&$A12, INDIRECT("B"&$C$70&":B"), "<"&$A13, INDIRECT("F"&$C$70&":F"), C$2) -> 1000 | D12: =SUMIFS(INDIRECT("C"&$C$70&":C"), INDIRECT("B"&$C$70&":B"), ">="&$A12, INDIRECT("B"&$C$70&":B"), "<"&$A13, INDIRECT("F"&$C$70&":F"), D$2) -> 75500 | E12: =IFERROR(__xludf.DUMMYFUNCTION("TEXTJOIN("", "", TRUE, FILTER(INDIRECT(""U""&$C$70&"":U""), INDIRECT(""E""&$C$70&"":E"") = $B$1, INDIRECT(""B""&$C$70&"":B"") >= $A12, INDIRECT(""B""&$C$70&"":B"") <$A13))"),"$102364 $536請假扣款, $1000勞動節, $75500績效") -> $102364 $536請假扣款, $1000勞動節, $75500績效 | F12: =SUMIFS(INDIRECT("C"&$C$70&":C"), INDIRECT("B"&$C$70&":B"), ">="&$A12, INDIRECT("B"&$C$70&":B"), "<"&$A13, INDIRECT("G"&$C$70&":G"), F$2) -> 9782 | G12: =SUMIFS(INDIRECT("C"&$C$70&":C"), INDIRECT("B"&$C$70&":B"), ">="&$A12, INDIRECT("B"&$C$70&":B"), "<"&$A13, INDIRECT("G"&$C$70&":G"), G$2) -> 0 | H12: =SUMIFS(INDIRECT("C"&$C$70&":C"), INDIRECT("B"&$C$70&":B"), ">="&$A12, INDIRECT("B"&$C$70&":B"), "<"&$A13, INDIRECT("G"&$C$70&":G"), H$2) -> 0 | I12: =SUMIFS(INDIRECT("C"&$C$70&":C"), INDIRECT("B"&$C$70&":B"), ">="&$A12, INDIRECT("B"&$C$70&":B"), "<"&$A13, INDIRECT("G"&$C$70&":G"), I$2) -> 0 | J12: =SUMIFS(INDIRECT("C"&$C$70&":C"), INDIRECT("B"&$C$70&":B"), ">="&$A12, INDIRECT("B"&$C$70&":B"), "<"&$A13, INDIRECT("G"&$C$70&":G"), J$2) -> 6000 | K12: =SUMIFS(INDIRECT("C"&$C$70&":C"), INDIRECT("B"&$C$70&":B"), ">="&$A12, INDIRECT("B"&$C$70&":B"), "<"&$A13, INDIRECT("G"&$C$70&":G"), K$2) -> 0 | L12: =IFERROR(__xludf.DUMMYFUNCTION("TEXTJOIN("", "", TRUE, FILTER(INDIRECT(""U""&$C$70&"":U""), INDIRECT(""E""&$C$70&"":E"") = $F$1, INDIRECT(""B""&$C$70&"":B"") >= $A12, INDIRECT(""B""&$C$70&"":B"") <$A13))"),"$2592中信優息, $7190元大A級") -> $2592中信優息, $7190元大A級
A13: 45778 | B13: =SUMIFS(INDIRECT("C"&$C$70&":C"), INDIRECT("B"&$C$70&":B"), ">="&$A13, INDIRECT("B"&$C$70&":B"), "<"&$A14, INDIRECT("F"&$C$70&":F"), B$2) -> 100649 | C13: =SUMIFS(INDIRECT("C"&$C$70&":C"), INDIRECT("B"&$C$70&":B"), ">="&$A13, INDIRECT("B"&$C$70&":B"), "<"&$A14, INDIRECT("F"&$C$70&":F"), C$2) -> 1000 | D13: =SUMIFS(INDIRECT("C"&$C$70&":C"), INDIRECT("B"&$C$70&":B"), ">="&$A13, INDIRECT("B"&$C$70&":B"), "<"&$A14, INDIRECT("F"&$C$70&":F"), D$2) -> 0 | E13: =IFERROR(__xludf.DUMMYFUNCTION("TEXTJOIN("", "", TRUE, FILTER(INDIRECT(""U""&$C$70&"":U""), INDIRECT(""E""&$C$70&"":E"") = $B$1, INDIRECT(""B""&$C$70&"":B"") >= $A13, INDIRECT(""B""&$C$70&"":B"") <$A14))"),"$100649 $2251請假扣款, $1000端午節") -> $100649 $2251請假扣款, $1000端午節 | F13: =SUMIFS(INDIRECT("C"&$C$70&":C"), INDIRECT("B"&$C$70&":B"), ">="&$A13, INDIRECT("B"&$C$70&":B"), "<"&$A14, INDIRECT("G"&$C$70&":G"), F$2) -> 2874 | G13: =SUMIFS(INDIRECT("C"&$C$70&":C"), INDIRECT("B"&$C$70&":B"), ">="&$A13, INDIRECT("B"&$C$70&":B"), "<"&$A14, INDIRECT("G"&$C$70&":G"), G$2) -> 0 | H13: =SUMIFS(INDIRECT("C"&$C$70&":C"), INDIRECT("B"&$C$70&":B"), ">="&$A13, INDIRECT("B"&$C$70&":B"), "<"&$A14, INDIRECT("G"&$C$70&":G"), H$2) -> 0 | I13: =SUMIFS(INDIRECT("C"&$C$70&":C"), INDIRECT("B"&$C$70&":B"), ">="&$A13, INDIRECT("B"&$C$70&":B"), "<"&$A14, INDIRECT("G"&$C$70&":G"), I$2) -> 0 | J13: =SUMIFS(INDIRECT("C"&$C$70&":C"), INDIRECT("B"&$C$70&":B"), ">="&$A13, INDIRECT("B"&$C$70&":B"), "<"&$A14, INDIRECT("G"&$C$70&":G"), J$2) -> 6000 | K13: =SUMIFS(INDIRECT("C"&$C$70&":C"), INDIRECT("B"&$C$70&":B"), ">="&$A13, INDIRECT("B"&$C$70&":B"), "<"&$A14, INDIRECT("G"&$C$70&":G"), K$2) -> 0 | L13: =IFERROR(__xludf.DUMMYFUNCTION("TEXTJOIN("", "", TRUE, FILTER(INDIRECT(""U""&$C$70&"":U""), INDIRECT(""E""&$C$70&"":E"") = $F$1, INDIRECT(""B""&$C$70&"":B"") >= $A13, INDIRECT(""B""&$C$70&"":B"") <$A14))"),"$282台灣中小, $2592中信優息") -> $282台灣中小, $2592中信優息
A14: 45809 | B14: =SUMIFS(INDIRECT("C"&$C$70&":C"), INDIRECT("B"&$C$70&":B"), ">="&$A14, INDIRECT("B"&$C$70&":B"), "<"&$A15, INDIRECT("F"&$C$70&":F"), B$2) -> 107300 | C14: =SUMIFS(INDIRECT("C"&$C$70&":C"), INDIRECT("B"&$C$70&":B"), ">="&$A14, INDIRECT("B"&$C$70&":B"), "<"&$A15, INDIRECT("F"&$C$70&":F"), C$2) -> 0 | D14: =SUMIFS(INDIRECT("C"&$C$70&":C"), INDIRECT("B"&$C$70&":B"), ">="&$A14, INDIRECT("B"&$C$70&":B"), "<"&$A15, INDIRECT("F"&$C$70&":F"), D$2) -> 0 | E14: =IFERROR(__xludf.DUMMYFUNCTION("TEXTJOIN("", "", TRUE, FILTER(INDIRECT(""U""&$C$70&"":U""), INDIRECT(""E""&$C$70&"":E"") = $B$1, INDIRECT(""B""&$C$70&"":B"") >= $A14, INDIRECT(""B""&$C$70&"":B"") <$A15))"),"") | F14: =SUMIFS(INDIRECT("C"&$C$70&":C"), INDIRECT("B"&$C$70&":B"), ">="&$A14, INDIRECT("B"&$C$70&":B"), "<"&$A15, INDIRECT("G"&$C$70&":G"), F$2) -> 7856 | G14: =SUMIFS(INDIRECT("C"&$C$70&":C"), INDIRECT("B"&$C$70&":B"), ">="&$A14, INDIRECT("B"&$C$70&":B"), "<"&$A15, INDIRECT("G"&$C$70&":G"), G$2) -> 0 | H14: =SUMIFS(INDIRECT("C"&$C$70&":C"), INDIRECT("B"&$C$70&":B"), ">="&$A14, INDIRECT("B"&$C$70&":B"), "<"&$A15, INDIRECT("G"&$C$70&":G"), H$2) -> 0 | I14: =SUMIFS(INDIRECT("C"&$C$70&":C"), INDIRECT("B"&$C$70&":B"), ">="&$A14, INDIRECT("B"&$C$70&":B"), "<"&$A15, INDIRECT("G"&$C$70&":G"), I$2) -> 0 | J14: =SUMIFS(INDIRECT("C"&$C$70&":C"), INDIRECT("B"&$C$70&":B"), ">="&$A14, INDIRECT("B"&$C$70&":B"), "<"&$A15, INDIRECT("G"&$C$70&":G"), J$2) -> 6000 | K14: =SUMIFS(INDIRECT("C"&$C$70&":C"), INDIRECT("B"&$C$70&":B"), ">="&$A14, INDIRECT("B"&$C$70&":B"), "<"&$A15, INDIRECT("G"&$C$70&":G"), K$2) -> 0 | L14: =IFERROR(__xludf.DUMMYFUNCTION("TEXTJOIN("", "", TRUE, FILTER(INDIRECT(""U""&$C$70&"":U""), INDIRECT(""E""&$C$70&"":E"") = $F$1, INDIRECT(""B""&$C$70&"":B"") >= $A14, INDIRECT(""B""&$C$70&"":B"") <$A15))"),"$2736中信優息, $5120元大美債") -> $2736中信優息, $5120元大美債
A15: 45839 | B15: =SUMIFS(INDIRECT("C"&$C$70&":C"), INDIRECT("B"&$C$70&":B"), ">="&$A15, INDIRECT("B"&$C$70&":B"), "<"&$A16, INDIRECT("F"&$C$70&":F"), B$2) -> 107300 | C15: =SUMIFS(INDIRECT("C"&$C$70&":C"), INDIRECT("B"&$C$70&":B"), ">="&$A15, INDIRECT("B"&$C$70&":B"), "<"&$A16, INDIRECT("F"&$C$70&":F"), C$2) -> 0 | D15: =SUMIFS(INDIRECT("C"&$C$70&":C"), INDIRECT("B"&$C$70&":B"), ">="&$A15, INDIRECT("B"&$C$70&":B"), "<"&$A16, INDIRECT("F"&$C$70&":F"), D$2) -> 101000 | E15: =IFERROR(__xludf.DUMMYFUNCTION("TEXTJOIN("", "", TRUE, FILTER(INDIRECT(""U""&$C$70&"":U""), INDIRECT(""E""&$C$70&"":E"") = $B$1, INDIRECT(""B""&$C$70&"":B"") >= $A15, INDIRECT(""B""&$C$70&"":B"") <$A16))"),"") | F15: =SUMIFS(INDIRECT("C"&$C$70&":C"), INDIRECT("B"&$C$70&":B"), ">="&$A15, INDIRECT("B"&$C$70&":B"), "<"&$A16, INDIRECT("G"&$C$70&":G"), F$2) -> 21532 | G15: =SUMIFS(INDIRECT("C"&$C$70&":C"), INDIRECT("B"&$C$70&":B"), ">="&$A15, INDIRECT("B"&$C$70&":B"), "<"&$A16, INDIRECT("G"&$C$70&":G"), G$2) -> 0 | H15: =SUMIFS(INDIRECT("C"&$C$70&":C"), INDIRECT("B"&$C$70&":B"), ">="&$A15, INDIRECT("B"&$C$70&":B"), "<"&$A16, INDIRECT("G"&$C$70&":G"), H$2) -> 0 | I15: =SUMIFS(INDIRECT("C"&$C$70&":C"), INDIRECT("B"&$C$70&":B"), ">="&$A15, INDIRECT("B"&$C$70&":B"), "<"&$A16, INDIRECT("G"&$C$70&":G"), I$2) -> 0 | J15: =SUMIFS(INDIRECT("C"&$C$70&":C"), INDIRECT("B"&$C$70&":B"), ">="&$A15, INDIRECT("B"&$C$70&":B"), "<"&$A16, INDIRECT("G"&$C$70&":G"), J$2) -> 6000 | K15: =SUMIFS(INDIRECT("C"&$C$70&":C"), INDIRECT("B"&$C$70&":B"), ">="&$A15, INDIRECT("B"&$C$70&":B"), "<"&$A16, INDIRECT("G"&$C$70&":G"), K$2) -> 0 | L15: =IFERROR(__xludf.DUMMYFUNCTION("TEXTJOIN("", "", TRUE, FILTER(INDIRECT(""U""&$C$70&"":U""), INDIRECT(""E""&$C$70&"":E"") = $F$1, INDIRECT(""B""&$C$70&"":B"") >= $A15, INDIRECT(""B""&$C$70&"":B"") <$A16))"),"$6960元大A級, $2622中信優息, $3790中再保, $1540元大金, $4040遠百, $890正隆, $1690凱基金") -> $6960元大A級, $2622中信優息, $3790中再保, $1540元大金, $4040遠百, $890正隆, $1690凱基金
A16: 45870 | B16: =SUMIFS(INDIRECT("C"&$C$70&":C"), INDIRECT("B"&$C$70&":B"), ">="&$A16, INDIRECT("B"&$C$70&":B"), "<"&$A17, INDIRECT("F"&$C$70&":F"), B$2) -> 106741 | C16: =SUMIFS(INDIRECT("C"&$C$70&":C"), INDIRECT("B"&$C$70&":B"), ">="&$A16, INDIRECT("B"&$C$70&":B"), "<"&$A17, INDIRECT("F"&$C$70&":F"), C$2) -> 28459 | D16: =SUMIFS(INDIRECT("C"&$C$70&":C"), INDIRECT("B"&$C$70&":B"), ">="&$A16, INDIRECT("B"&$C$70&":B"), "<"&$A17, INDIRECT("F"&$C$70&":F"), D$2) -> 0 | E16: =IFERROR(__xludf.DUMMYFUNCTION("TEXTJOIN("", "", TRUE, FILTER(INDIRECT(""U""&$C$70&"":U""), INDIRECT(""E""&$C$70&"":E"") = $B$1, INDIRECT(""B""&$C$70&"":B"") >= $A16, INDIRECT(""B""&$C$70&"":B"") <$A17))"),"$106741 559病假, $2459特休, $5000體檢費, $1000生日禮金, $20000旅遊補助") -> $106741 559病假, $2459特休, $5000體檢費, $1000生日禮金, $20000旅遊補助 | F16: =SUMIFS(INDIRECT("C"&$C$70&":C"), INDIRECT("B"&$C$70&":B"), ">="&$A16, INDIRECT("B"&$C$70&":B"), "<"&$A17, INDIRECT("G"&$C$70&":G"), F$2) -> 17441 | G16: =SUMIFS(INDIRECT("C"&$C$70&":C"), INDIRECT("B"&$C$70&":B"), ">="&$A16, INDIRECT("B"&$C$70&":B"), "<"&$A17, INDIRECT("G"&$C$70&":G"), G$2) -> 0 | H16: =SUMIFS(INDIRECT("C"&$C$70&":C"), INDIRECT("B"&$C$70&":B"), ">="&$A16, INDIRECT("B"&$C$70&":B"), "<"&$A17, INDIRECT("G"&$C$70&":G"), H$2) -> 0 | I16: =SUMIFS(INDIRECT("C"&$C$70&":C"), INDIRECT("B"&$C$70&":B"), ">="&$A16, INDIRECT("B"&$C$70&":B"), "<"&$A17, INDIRECT("G"&$C$70&":G"), I$2) -> 0 | J16: =SUMIFS(INDIRECT("C"&$C$70&":C"), INDIRECT("B"&$C$70&":B"), ">="&$A16, INDIRECT("B"&$C$70&":B"), "<"&$A17, INDIRECT("G"&$C$70&":G"), J$2) -> 6000 | K16: =SUMIFS(INDIRECT("C"&$C$70&":C"), INDIRECT("B"&$C$70&":B"), ">="&$A16, INDIRECT("B"&$C$70&":B"), "<"&$A17, INDIRECT("G"&$C$70&":G"), K$2) -> 0 | L16: =IFERROR(__xludf.DUMMYFUNCTION("TEXTJOIN("", "", TRUE, FILTER(INDIRECT(""U""&$C$70&"":U""), INDIRECT(""E""&$C$70&"":E"") = $F$1, INDIRECT(""B""&$C$70&"":B"") >= $A16, INDIRECT(""B""&$C$70&"":B"") <$A17))"),"$1674玉山金, $2508中信優息, $890山隆, $2290中信金, $8990海悅, $1089聯邦銀") -> $1674玉山金, $2508中信優息, $890山隆, $2290中信金, $8990海悅, $1089聯邦銀
A17: 45901 | B17: =SUMIFS(INDIRECT("C"&$C$70&":C"), INDIRECT("B"&$C$70&":B"), ">="&$A17, INDIRECT("B"&$C$70&":B"), "<"&$A18, INDIRECT("F"&$C$70&":F"), B$2) -> 107076 | C17: =SUMIFS(INDIRECT("C"&$C$70&":C"), INDIRECT("B"&$C$70&":B"), ">="&$A17, INDIRECT("B"&$C$70&":B"), "<"&$A18, INDIRECT("F"&$C$70&":F"), C$2) -> 0 | D17: =SUMIFS(INDIRECT("C"&$C$70&":C"), INDIRECT("B"&$C$70&":B"), ">="&$A17, INDIRECT("B"&$C$70&":B"), "<"&$A18, INDIRECT("F"&$C$70&":F"), D$2) -> 0 | E17: =IFERROR(__xludf.DUMMYFUNCTION("TEXTJOIN("", "", TRUE, FILTER(INDIRECT(""U""&$C$70&"":U""), INDIRECT(""E""&$C$70&"":E"") = $B$1, INDIRECT(""B""&$C$70&"":B"") >= $A17, INDIRECT(""B""&$C$70&"":B"") <$A18))"),"$107076 $224病假") -> $107076 $224病假 | F17: =SUMIFS(INDIRECT("C"&$C$70&":C"), INDIRECT("B"&$C$70&":B"), ">="&$A17, INDIRECT("B"&$C$70&":B"), "<"&$A18, INDIRECT("G"&$C$70&":G"), F$2) -> 20460 | G17: =SUMIFS(INDIRECT("C"&$C$70&":C"), INDIRECT("B"&$C$70&":B"), ">="&$A17, INDIRECT("B"&$C$70&":B"), "<"&$A18, INDIRECT("G"&$C$70&":G"), G$2) -> 0 | H17: =SUMIFS(INDIRECT("C"&$C$70&":C"), INDIRECT("B"&$C$70&":B"), ">="&$A17, INDIRECT("B"&$C$70&":B"), "<"&$A18, INDIRECT("G"&$C$70&":G"), H$2) -> 0 | I17: =SUMIFS(INDIRECT("C"&$C$70&":C"), INDIRECT("B"&$C$70&":B"), ">="&$A17, INDIRECT("B"&$C$70&":B"), "<"&$A18, INDIRECT("G"&$C$70&":G"), I$2) -> 0 | J17: =SUMIFS(INDIRECT("C"&$C$70&":C"), INDIRECT("B"&$C$70&":B"), ">="&$A17, INDIRECT("B"&$C$70&":B"), "<"&$A18, INDIRECT("G"&$C$70&":G"), J$2) -> 6000 | K17: =SUMIFS(INDIRECT("C"&$C$70&":C"), INDIRECT("B"&$C$70&":B"), ">="&$A17, INDIRECT("B"&$C$70&":B"), "<"&$A18, INDIRECT("G"&$C$70&":G"), K$2) -> 0 | L17: =IFERROR(__xludf.DUMMYFUNCTION("TEXTJOIN("", "", TRUE, FILTER(INDIRECT(""U""&$C$70&"":U""), INDIRECT(""E""&$C$70&"":E"") = $F$1, INDIRECT(""B""&$C$70&"":B"") >= $A17, INDIRECT(""B""&$C$70&"":B"") <$A18))"),"$990彰銀, $4470美債20年, $1590兆豐金, $3590台新新光, $2160中信優息, $770台中銀, $900永豐金, $5990遠東銀") -> $990彰銀, $4470美債20年, $1590兆豐金, $3590台新新光, $2160中信優息, $770台中銀, $900永豐金, $5990遠東銀
A18: 45931 | B18: =SUMIFS(INDIRECT("C"&$C$70&":C"), INDIRECT("B"&$C$70&":B"), ">="&$A18, INDIRECT("B"&$C$70&":B"), "<"&$A19, INDIRECT("F"&$C$70&":F"), B$2) -> 105065 | C18: =SUMIFS(INDIRECT("C"&$C$70&":C"), INDIRECT("B"&$C$70&":B"), ">="&$A18, INDIRECT("B"&$C$70&":B"), "<"&$A19, INDIRECT("F"&$C$70&":F"), C$2) -> 1000 | D18: =SUMIFS(INDIRECT("C"&$C$70&":C"), INDIRECT("B"&$C$70&":B"), ">="&$A18, INDIRECT("B"&$C$70&":B"), "<"&$A19, INDIRECT("F"&$C$70&":F"), D$2) -> 76000 | E18: =IFERROR(__xludf.DUMMYFUNCTION("TEXTJOIN("", "", TRUE, FILTER(INDIRECT(""U""&$C$70&"":U""), INDIRECT(""E""&$C$70&"":E"") = $B$1, INDIRECT(""B""&$C$70&"":B"") >= $A18, INDIRECT(""B""&$C$70&"":B"") <$A19))"),"$105065 $2235病假, $1000中秋節, $76000績效") -> $105065 $2235病假, $1000中秋節, $76000績效 | F18: =SUMIFS(INDIRECT("C"&$C$70&":C"), INDIRECT("B"&$C$70&":B"), ">="&$A18, INDIRECT("B"&$C$70&":B"), "<"&$A19, INDIRECT("G"&$C$70&":G"), F$2) -> 11670 | G18: =SUMIFS(INDIRECT("C"&$C$70&":C"), INDIRECT("B"&$C$70&":B"), ">="&$A18, INDIRECT("B"&$C$70&":B"), "<"&$A19, INDIRECT("G"&$C$70&":G"), G$2) -> 0 | H18: =SUMIFS(INDIRECT("C"&$C$70&":C"), INDIRECT("B"&$C$70&":B"), ">="&$A18, INDIRECT("B"&$C$70&":B"), "<"&$A19, INDIRECT("G"&$C$70&":G"), H$2) -> 0 | I18: =SUMIFS(INDIRECT("C"&$C$70&":C"), INDIRECT("B"&$C$70&":B"), ">="&$A18, INDIRECT("B"&$C$70&":B"), "<"&$A19, INDIRECT("G"&$C$70&":G"), I$2) -> 0 | J18: =SUMIFS(INDIRECT("C"&$C$70&":C"), INDIRECT("B"&$C$70&":B"), ">="&$A18, INDIRECT("B"&$C$70&":B"), "<"&$A19, INDIRECT("G"&$C$70&":G"), J$2) -> 6000 | K18: =SUMIFS(INDIRECT("C"&$C$70&":C"), INDIRECT("B"&$C$70&":B"), ">="&$A18, INDIRECT("B"&$C$70&":B"), "<"&$A19, INDIRECT("G"&$C$70&":G"), K$2) -> 0 | L18: =IFERROR(__xludf.DUMMYFUNCTION("TEXTJOIN("", "", TRUE, FILTER(INDIRECT(""U""&$C$70&"":U""), INDIRECT(""E""&$C$70&"":E"") = $F$1, INDIRECT(""B""&$C$70&"":B"") >= $A18, INDIRECT(""B""&$C$70&"":B"") <$A19))"),"$6960元大A級, $2520中信優息, $2190興富發") -> $6960元大A級, $2520中信優息, $2190興富發
A19: 45962 | B19: =SUMIFS(INDIRECT("C"&$C$70&":C"), INDIRECT("B"&$C$70&":B"), ">="&$A19, INDIRECT("B"&$C$70&":B"), "<"&$A20, INDIRECT("F"&$C$70&":F"), B$2) -> 107300 | C19: =SUMIFS(INDIRECT("C"&$C$70&":C"), INDIRECT("B"&$C$70&":B"), ">="&$A19, INDIRECT("B"&$C$70&":B"), "<"&$A20, INDIRECT("F"&$C$70&":F"), C$2) -> 0 | D19: =SUMIFS(INDIRECT("C"&$C$70&":C"), INDIRECT("B"&$C$70&":B"), ">="&$A19, INDIRECT("B"&$C$70&":B"), "<"&$A20, INDIRECT("F"&$C$70&":F"), D$2) -> 0 | E19: =IFERROR(__xludf.DUMMYFUNCTION("TEXTJOIN("", "", TRUE, FILTER(INDIRECT(""U""&$C$70&"":U""), INDIRECT(""E""&$C$70&"":E"") = $B$1, INDIRECT(""B""&$C$70&"":B"") >= $A19, INDIRECT(""B""&$C$70&"":B"") <$A20))"),"") | F19: =SUMIFS(INDIRECT("C"&$C$70&":C"), INDIRECT("B"&$C$70&":B"), ">="&$A19, INDIRECT("B"&$C$70&":B"), "<"&$A20, INDIRECT("G"&$C$70&":G"), F$2) -> 2520 | G19: =SUMIFS(INDIRECT("C"&$C$70&":C"), INDIRECT("B"&$C$70&":B"), ">="&$A19, INDIRECT("B"&$C$70&":B"), "<"&$A20, INDIRECT("G"&$C$70&":G"), G$2) -> 0 | H19: =SUMIFS(INDIRECT("C"&$C$70&":C"), INDIRECT("B"&$C$70&":B"), ">="&$A19, INDIRECT("B"&$C$70&":B"), "<"&$A20, INDIRECT("G"&$C$70&":G"), H$2) -> 0 | I19: =SUMIFS(INDIRECT("C"&$C$70&":C"), INDIRECT("B"&$C$70&":B"), ">="&$A19, INDIRECT("B"&$C$70&":B"), "<"&$A20, INDIRECT("G"&$C$70&":G"), I$2) -> 0 | J19: =SUMIFS(INDIRECT("C"&$C$70&":C"), INDIRECT("B"&$C$70&":B"), ">="&$A19, INDIRECT("B"&$C$70&":B"), "<"&$A20, INDIRECT("G"&$C$70&":G"), J$2) -> 6000 | K19: =SUMIFS(INDIRECT("C"&$C$70&":C"), INDIRECT("B"&$C$70&":B"), ">="&$A19, INDIRECT("B"&$C$70&":B"), "<"&$A20, INDIRECT("G"&$C$70&":G"), K$2) -> 0 | L19: =IFERROR(__xludf.DUMMYFUNCTION("TEXTJOIN("", "", TRUE, FILTER(INDIRECT(""U""&$C$70&"":U""), INDIRECT(""E""&$C$70&"":E"") = $F$1, INDIRECT(""B""&$C$70&"":B"") >= $A19, INDIRECT(""B""&$C$70&"":B"") <$A20))"),"$2520中信優息") -> $2520中信優息
A20: 45992 | B20: =SUMIFS(INDIRECT("C"&$C$70&":C"), INDIRECT("B"&$C$70&":B"), ">="&$A20, INDIRECT("B"&$C$70&":B"), "<"&$A21, INDIRECT("F"&$C$70&":F"), B$2) -> 107300 | C20: =SUMIFS(INDIRECT("C"&$C$70&":C"), INDIRECT("B"&$C$70&":B"), ">="&$A20, INDIRECT("B"&$C$70&":B"), "<"&$A21, INDIRECT("F"&$C$70&":F"), C$2) -> 25000 | D20: =SUMIFS(INDIRECT("C"&$C$70&":C"), INDIRECT("B"&$C$70&":B"), ">="&$A20, INDIRECT("B"&$C$70&":B"), "<"&$A21, INDIRECT("F"&$C$70&":F"), D$2) -> 0 | E20: =IFERROR(__xludf.DUMMYFUNCTION("TEXTJOIN("", "", TRUE, FILTER(INDIRECT(""U""&$C$70&"":U""), INDIRECT(""E""&$C$70&"":E"") = $B$1, INDIRECT(""B""&$C$70&"":B"") >= $A20, INDIRECT(""B""&$C$70&"":B"") <$A21))"),"$25000家庭日") -> $25000家庭日 | F20: =SUMIFS(INDIRECT("C"&$C$70&":C"), INDIRECT("B"&$C$70&":B"), ">="&$A20, INDIRECT("B"&$C$70&":B"), "<"&$A21, INDIRECT("G"&$C$70&":G"), F$2) -> 6990 | G20: =SUMIFS(INDIRECT("C"&$C$70&":C"), INDIRECT("B"&$C$70&":B"), ">="&$A20, INDIRECT("B"&$C$70&":B"), "<"&$A21, INDIRECT("G"&$C$70&":G"), G$2) -> 0 | H20: =SUMIFS(INDIRECT("C"&$C$70&":C"), INDIRECT("B"&$C$70&":B"), ">="&$A20, INDIRECT("B"&$C$70&":B"), "<"&$A21, INDIRECT("G"&$C$70&":G"), H$2) -> 0 | I20: =SUMIFS(INDIRECT("C"&$C$70&":C"), INDIRECT("B"&$C$70&":B"), ">="&$A20, INDIRECT("B"&$C$70&":B"), "<"&$A21, INDIRECT("G"&$C$70&":G"), I$2) -> 0 | J20: =SUMIFS(INDIRECT("C"&$C$70&":C"), INDIRECT("B"&$C$70&":B"), ">="&$A20, INDIRECT("B"&$C$70&":B"), "<"&$A21, INDIRECT("G"&$C$70&":G"), J$2) -> 6000 | K20: =SUMIFS(INDIRECT("C"&$C$70&":C"), INDIRECT("B"&$C$70&":B"), ">="&$A20, INDIRECT("B"&$C$70&":B"), "<"&$A21, INDIRECT("G"&$C$70&":G"), K$2) -> 0 | L20: =IFERROR(__xludf.DUMMYFUNCTION("TEXTJOIN("", "", TRUE, FILTER(INDIRECT(""U""&$C$70&"":U""), INDIRECT(""E""&$C$70&"":E"") = $F$1, INDIRECT(""B""&$C$70&"":B"") >= $A20, INDIRECT(""B""&$C$70&"":B"") <$A21))"),"$4470美債20年, $2520中信優息") -> $4470美債20年, $2520中信優息
A21: 46023 | B21: =SUMIFS(INDIRECT("C"&$C$70&":C"), INDIRECT("B"&$C$70&":B"), ">="&$A21, INDIRECT("B"&$C$70&":B"), "<"&$A22, INDIRECT("F"&$C$70&":F"), B$2) -> 107300 | C21: =SUMIFS(INDIRECT("C"&$C$70&":C"), INDIRECT("B"&$C$70&":B"), ">="&$A21, INDIRECT("B"&$C$70&":B"), "<"&$A22, INDIRECT("F"&$C$70&":F"), C$2) -> 0 | D21: =SUMIFS(INDIRECT("C"&$C$70&":C"), INDIRECT("B"&$C$70&":B"), ">="&$A21, INDIRECT("B"&$C$70&":B"), "<"&$A22, INDIRECT("F"&$C$70&":F"), D$2) -> 0 | E21: =IFERROR(__xludf.DUMMYFUNCTION("TEXTJOIN("", "", TRUE, FILTER(INDIRECT(""U""&$C$70&"":U""), INDIRECT(""E""&$C$70&"":E"") = $B$1, INDIRECT(""B""&$C$70&"":B"") >= $A21, INDIRECT(""B""&$C$70&"":B"") <$A22))"),"") | F21: =SUMIFS(INDIRECT("C"&$C$70&":C"), INDIRECT("B"&$C$70&":B"), ">="&$A21, INDIRECT("B"&$C$70&":B"), "<"&$A22, INDIRECT("G"&$C$70&":G"), F$2) -> 924 | G21: =SUMIFS(INDIRECT("C"&$C$70&":C"), INDIRECT("B"&$C$70&":B"), ">="&$A21, INDIRECT("B"&$C$70&":B"), "<"&$A22, INDIRECT("G"&$C$70&":G"), G$2) -> 0 | H21: =SUMIFS(INDIRECT("C"&$C$70&":C"), INDIRECT("B"&$C$70&":B"), ">="&$A21, INDIRECT("B"&$C$70&":B"), "<"&$A22, INDIRECT("G"&$C$70&":G"), H$2) -> 0 | I21: =SUMIFS(INDIRECT("C"&$C$70&":C"), INDIRECT("B"&$C$70&":B"), ">="&$A21, INDIRECT("B"&$C$70&":B"), "<"&$A22, INDIRECT("G"&$C$70&":G"), I$2) -> 0 | J21: =SUMIFS(INDIRECT("C"&$C$70&":C"), INDIRECT("B"&$C$70&":B"), ">="&$A21, INDIRECT("B"&$C$70&":B"), "<"&$A22, INDIRECT("G"&$C$70&":G"), J$2) -> 6000 | K21: =SUMIFS(INDIRECT("C"&$C$70&":C"), INDIRECT("B"&$C$70&":B"), ">="&$A21, INDIRECT("B"&$C$70&":B"), "<"&$A22, INDIRECT("G"&$C$70&":G"), K$2) -> 934600 | L21: =IFERROR(__xludf.DUMMYFUNCTION("TEXTJOIN("", "", TRUE, FILTER(INDIRECT(""U""&$C$70&"":U""), INDIRECT(""E""&$C$70&"":E"") = $F$1, INDIRECT(""B""&$C$70&"":B"") >= $A21, INDIRECT(""B""&$C$70&"":B"") <$A22))"),"$934600台銀人壽解約, $924中信優息") -> $934600台銀人壽解約, $924中信優息
A22: 46054 | B22: =SUMIFS(INDIRECT("C"&$C$70&":C"), INDIRECT("B"&$C$70&":B"), ">="&$A22, INDIRECT("B"&$C$70&":B"), "<"&$A23, INDIRECT("F"&$C$70&":F"), B$2) -> 106853 | C22: =SUMIFS(INDIRECT("C"&$C$70&":C"), INDIRECT("B"&$C$70&":B"), ">="&$A22, INDIRECT("B"&$C$70&":B"), "<"&$A23, INDIRECT("F"&$C$70&":F"), C$2) -> 0 | D22: =SUMIFS(INDIRECT("C"&$C$70&":C"), INDIRECT("B"&$C$70&":B"), ">="&$A22, INDIRECT("B"&$C$70&":B"), "<"&$A23, INDIRECT("F"&$C$70&":F"), D$2) -> 496487 | E22: =IFERROR(__xludf.DUMMYFUNCTION("TEXTJOIN("", "", TRUE, FILTER(INDIRECT(""U""&$C$70&"":U""), INDIRECT(""E""&$C$70&"":E"") = $B$1, INDIRECT(""B""&$C$70&"":B"") >= $A22, INDIRECT(""B""&$C$70&"":B"") <$A23))"),"$106853$447病假, $496487註1") -> $106853$447病假, $496487註1 | F22: =SUMIFS(INDIRECT("C"&$C$70&":C"), INDIRECT("B"&$C$70&":B"), ">="&$A22, INDIRECT("B"&$C$70&":B"), "<"&$A23, INDIRECT("G"&$C$70&":G"), F$2) -> 2200 | G22: =SUMIFS(INDIRECT("C"&$C$70&":C"), INDIRECT("B"&$C$70&":B"), ">="&$A22, INDIRECT("B"&$C$70&":B"), "<"&$A23, INDIRECT("G"&$C$70&":G"), G$2) -> 0 | H22: =SUMIFS(INDIRECT("C"&$C$70&":C"), INDIRECT("B"&$C$70&":B"), ">="&$A22, INDIRECT("B"&$C$70&":B"), "<"&$A23, INDIRECT("G"&$C$70&":G"), H$2) -> 0 | I22: =SUMIFS(INDIRECT("C"&$C$70&":C"), INDIRECT("B"&$C$70&":B"), ">="&$A22, INDIRECT("B"&$C$70&":B"), "<"&$A23, INDIRECT("G"&$C$70&":G"), I$2) -> 0 | J22: =SUMIFS(INDIRECT("C"&$C$70&":C"), INDIRECT("B"&$C$70&":B"), ">="&$A22, INDIRECT("B"&$C$70&":B"), "<"&$A23, INDIRECT("G"&$C$70&":G"), J$2) -> 6000 | K22: =SUMIFS(INDIRECT("C"&$C$70&":C"), INDIRECT("B"&$C$70&":B"), ">="&$A22, INDIRECT("B"&$C$70&":B"), "<"&$A23, INDIRECT("G"&$C$70&":G"), K$2) -> 0 | L22: =IFERROR(__xludf.DUMMYFUNCTION("TEXTJOIN("", "", TRUE, FILTER(INDIRECT(""U""&$C$70&"":U""), INDIRECT(""E""&$C$70&"":E"") = $F$1, INDIRECT(""B""&$C$70&"":B"") >= $A22, INDIRECT(""B""&$C$70&"":B"") <$A23))"),"$2200元大50") -> $2200元大50
A23: 46082 | B23: =SUMIFS(INDIRECT("C"&$C$70&":C"), INDIRECT("B"&$C$70&":B"), ">="&$A23, INDIRECT("B"&$C$70&":B"), "<"&$A24, INDIRECT("F"&$C$70&":F"), B$2) -> 107300 | C23: =SUMIFS(INDIRECT("C"&$C$70&":C"), INDIRECT("B"&$C$70&":B"), ">="&$A23, INDIRECT("B"&$C$70&":B"), "<"&$A24, INDIRECT("F"&$C$70&":F"), C$2) -> 0 | D23: =SUMIFS(INDIRECT("C"&$C$70&":C"), INDIRECT("B"&$C$70&":B"), ">="&$A23, INDIRECT("B"&$C$70&":B"), "<"&$A24, INDIRECT("F"&$C$70&":F"), D$2) -> 0 | E23: =IFERROR(__xludf.DUMMYFUNCTION("TEXTJOIN("", "", TRUE, FILTER(INDIRECT(""U""&$C$70&"":U""), INDIRECT(""E""&$C$70&"":E"") = $B$1, INDIRECT(""B""&$C$70&"":B"") >= $A23, INDIRECT(""B""&$C$70&"":B"") <$A24))"),"") | F23: =SUMIFS(INDIRECT("C"&$C$70&":C"), INDIRECT("B"&$C$70&":B"), ">="&$A23, INDIRECT("B"&$C$70&":B"), "<"&$A24, INDIRECT("G"&$C$70&":G"), F$2) -> 0 | G23: =SUMIFS(INDIRECT("C"&$C$70&":C"), INDIRECT("B"&$C$70&":B"), ">="&$A23, INDIRECT("B"&$C$70&":B"), "<"&$A24, INDIRECT("G"&$C$70&":G"), G$2) -> 0 | H23: =SUMIFS(INDIRECT("C"&$C$70&":C"), INDIRECT("B"&$C$70&":B"), ">="&$A23, INDIRECT("B"&$C$70&":B"), "<"&$A24, INDIRECT("G"&$C$70&":G"), H$2) -> 0 | I23: =SUMIFS(INDIRECT("C"&$C$70&":C"), INDIRECT("B"&$C$70&":B"), ">="&$A23, INDIRECT("B"&$C$70&":B"), "<"&$A24, INDIRECT("G"&$C$70&":G"), I$2) -> 0 | J23: =SUMIFS(INDIRECT("C"&$C$70&":C"), INDIRECT("B"&$C$70&":B"), ">="&$A23, INDIRECT("B"&$C$70&":B"), "<"&$A24, INDIRECT("G"&$C$70&":G"), J$2) -> 6000 | K23: =SUMIFS(INDIRECT("C"&$C$70&":C"), INDIRECT("B"&$C$70&":B"), ">="&$A23, INDIRECT("B"&$C$70&":B"), "<"&$A24, INDIRECT("G"&$C$70&":G"), K$2) -> 0 | L23: =IFERROR(__xludf.DUMMYFUNCTION("TEXTJOIN("", "", TRUE, FILTER(INDIRECT(""U""&$C$70&"":U""), INDIRECT(""E""&$C$70&"":E"") = $F$1, INDIRECT(""B""&$C$70&"":B"") >= $A23, INDIRECT(""B""&$C$70&"":B"") <$A24))"),"")
A24: 46113 | B24: =SUMIFS(INDIRECT("C"&$C$70&":C"), INDIRECT("B"&$C$70&":B"), ">="&$A24, INDIRECT("B"&$C$70&":B"), "<"&$A25, INDIRECT("F"&$C$70&":F"), B$2) -> 107300 | C24: =SUMIFS(INDIRECT("C"&$C$70&":C"), INDIRECT("B"&$C$70&":B"), ">="&$A24, INDIRECT("B"&$C$70&":B"), "<"&$A25, INDIRECT("F"&$C$70&":F"), C$2) -> 11927 | D24: =SUMIFS(INDIRECT("C"&$C$70&":C"), INDIRECT("B"&$C$70&":B"), ">="&$A24, INDIRECT("B"&$C$70&":B"), "<"&$A25, INDIRECT("F"&$C$70&":F"), D$2) -> 0 | E24: =IFERROR(__xludf.DUMMYFUNCTION("TEXTJOIN("", "", TRUE, FILTER(INDIRECT(""U""&$C$70&"":U""), INDIRECT(""E""&$C$70&"":E"") = $B$1, INDIRECT(""B""&$C$70&"":B"") >= $A24, INDIRECT(""B""&$C$70&"":B"") <$A25))"),"$5000其他加項(?)") -> $5000其他加項(?) | F24: =SUMIFS(INDIRECT("C"&$C$70&":C"), INDIRECT("B"&$C$70&":B"), ">="&$A24, INDIRECT("B"&$C$70&":B"), "<"&$A25, INDIRECT("G"&$C$70&":G"), F$2) -> 0 | G24: =SUMIFS(INDIRECT("C"&$C$70&":C"), INDIRECT("B"&$C$70&":B"), ">="&$A24, INDIRECT("B"&$C$70&":B"), "<"&$A25, INDIRECT("G"&$C$70&":G"), G$2) -> 0 | H24: =SUMIFS(INDIRECT("C"&$C$70&":C"), INDIRECT("B"&$C$70&":B"), ">="&$A24, INDIRECT("B"&$C$70&":B"), "<"&$A25, INDIRECT("G"&$C$70&":G"), H$2) -> 0 | I24: =SUMIFS(INDIRECT("C"&$C$70&":C"), INDIRECT("B"&$C$70&":B"), ">="&$A24, INDIRECT("B"&$C$70&":B"), "<"&$A25, INDIRECT("G"&$C$70&":G"), I$2) -> 0 | J24: =SUMIFS(INDIRECT("C"&$C$70&":C"), INDIRECT("B"&$C$70&":B"), ">="&$A24, INDIRECT("B"&$C$70&":B"), "<"&$A25, INDIRECT("G"&$C$70&":G"), J$2) -> 6000 | K24: =SUMIFS(INDIRECT("C"&$C$70&":C"), INDIRECT("B"&$C$70&":B"), ">="&$A24, INDIRECT("B"&$C$70&":B"), "<"&$A25, INDIRECT("G"&$C$70&":G"), K$2) -> 0 | L24: =IFERROR(__xludf.DUMMYFUNCTION("TEXTJOIN("", "", TRUE, FILTER(INDIRECT(""U""&$C$70&"":U""), INDIRECT(""E""&$C$70&"":E"") = $F$1, INDIRECT(""B""&$C$70&"":B"") >= $A24, INDIRECT(""B""&$C$70&"":B"") <$A25))"),"")
A25: 46143 | B25: =SUMIFS(INDIRECT("C"&$C$70&":C"), INDIRECT("B"&$C$70&":B"), ">="&$A25, INDIRECT("B"&$C$70&":B"), "<"&$A26, INDIRECT("F"&$C$70&":F"), B$2) -> 105512 | C25: =SUMIFS(INDIRECT("C"&$C$70&":C"), INDIRECT("B"&$C$70&":B"), ">="&$A25, INDIRECT("B"&$C$70&":B"), "<"&$A26, INDIRECT("F"&$C$70&":F"), C$2) -> 109991 | D25: =SUMIFS(INDIRECT("C"&$C$70&":C"), INDIRECT("B"&$C$70&":B"), ">="&$A25, INDIRECT("B"&$C$70&":B"), "<"&$A26, INDIRECT("F"&$C$70&":F"), D$2) -> 0 | E25: =IFERROR(__xludf.DUMMYFUNCTION("TEXTJOIN("", "", TRUE, FILTER(INDIRECT(""U""&$C$70&"":U""), INDIRECT(""E""&$C$70&"":E"") = $B$1, INDIRECT(""B""&$C$70&"":B"") >= $A25, INDIRECT(""B""&$C$70&"":B"") <$A26))"),"$105512 $1788請假, $107300家庭日獎金") -> $105512 $1788請假, $107300家庭日獎金 | F25: =SUMIFS(INDIRECT("C"&$C$70&":C"), INDIRECT("B"&$C$70&":B"), ">="&$A25, INDIRECT("B"&$C$70&":B"), "<"&$A26, INDIRECT("G"&$C$70&":G"), F$2) -> 0 | G25: =SUMIFS(INDIRECT("C"&$C$70&":C"), INDIRECT("B"&$C$70&":B"), ">="&$A25, INDIRECT("B"&$C$70&":B"), "<"&$A26, INDIRECT("G"&$C$70&":G"), G$2) -> 0 | H25: =SUMIFS(INDIRECT("C"&$C$70&":C"), INDIRECT("B"&$C$70&":B"), ">="&$A25, INDIRECT("B"&$C$70&":B"), "<"&$A26, INDIRECT("G"&$C$70&":G"), H$2) -> 0 | I25: =SUMIFS(INDIRECT("C"&$C$70&":C"), INDIRECT("B"&$C$70&":B"), ">="&$A25, INDIRECT("B"&$C$70&":B"), "<"&$A26, INDIRECT("G"&$C$70&":G"), I$2) -> 0 | J25: =SUMIFS(INDIRECT("C"&$C$70&":C"), INDIRECT("B"&$C$70&":B"), ">="&$A25, INDIRECT("B"&$C$70&":B"), "<"&$A26, INDIRECT("G"&$C$70&":G"), J$2) -> 6000 | K25: =SUMIFS(INDIRECT("C"&$C$70&":C"), INDIRECT("B"&$C$70&":B"), ">="&$A25, INDIRECT("B"&$C$70&":B"), "<"&$A26, INDIRECT("G"&$C$70&":G"), K$2) -> 0 | L25: =IFERROR(__xludf.DUMMYFUNCTION("TEXTJOIN("", "", TRUE, FILTER(INDIRECT(""U""&$C$70&"":U""), INDIRECT(""E""&$C$70&"":E"") = $F$1, INDIRECT(""B""&$C$70&"":B"") >= $A25, INDIRECT(""B""&$C$70&"":B"") <$A26))"),"")
A26: 46174 | B26: =SUMIFS(INDIRECT("C"&$C$70&":C"), INDIRECT("B"&$C$70&":B"), ">="&$A26, INDIRECT("B"&$C$70&":B"), "<"&$A27, INDIRECT("F"&$C$70&":F"), B$2) -> 110300 | C26: =SUMIFS(INDIRECT("C"&$C$70&":C"), INDIRECT("B"&$C$70&":B"), ">="&$A26, INDIRECT("B"&$C$70&":B"), "<"&$A27, INDIRECT("F"&$C$70&":F"), C$2) -> 0 | D26: =SUMIFS(INDIRECT("C"&$C$70&":C"), INDIRECT("B"&$C$70&":B"), ">="&$A26, INDIRECT("B"&$C$70&":B"), "<"&$A27, INDIRECT("F"&$C$70&":F"), D$2) -> 0 | E26: =IFERROR(__xludf.DUMMYFUNCTION("TEXTJOIN("", "", TRUE, FILTER(INDIRECT(""U""&$C$70&"":U""), INDIRECT(""E""&$C$70&"":E"") = $B$1, INDIRECT(""B""&$C$70&"":B"") >= $A26, INDIRECT(""B""&$C$70&"":B"") <$A27))"),"") | F26: =SUMIFS(INDIRECT("C"&$C$70&":C"), INDIRECT("B"&$C$70&":B"), ">="&$A26, INDIRECT("B"&$C$70&":B"), "<"&$A27, INDIRECT("G"&$C$70&":G"), F$2) -> 2800 | G26: =SUMIFS(INDIRECT("C"&$C$70&":C"), INDIRECT("B"&$C$70&":B"), ">="&$A26, INDIRECT("B"&$C$70&":B"), "<"&$A27, INDIRECT("G"&$C$70&":G"), G$2) -> 0 | H26: =SUMIFS(INDIRECT("C"&$C$70&":C"), INDIRECT("B"&$C$70&":B"), ">="&$A26, INDIRECT("B"&$C$70&":B"), "<"&$A27, INDIRECT("G"&$C$70&":G"), H$2) -> 0 | I26: =SUMIFS(INDIRECT("C"&$C$70&":C"), INDIRECT("B"&$C$70&":B"), ">="&$A26, INDIRECT("B"&$C$70&":B"), "<"&$A27, INDIRECT("G"&$C$70&":G"), I$2) -> 0 | J26: =SUMIFS(INDIRECT("C"&$C$70&":C"), INDIRECT("B"&$C$70&":B"), ">="&$A26, INDIRECT("B"&$C$70&":B"), "<"&$A27, INDIRECT("G"&$C$70&":G"), J$2) -> 6000 | K26: =SUMIFS(INDIRECT("C"&$C$70&":C"), INDIRECT("B"&$C$70&":B"), ">="&$A26, INDIRECT("B"&$C$70&":B"), "<"&$A27, INDIRECT("G"&$C$70&":G"), K$2) -> 0 | L26: =IFERROR(__xludf.DUMMYFUNCTION("TEXTJOIN("", "", TRUE, FILTER(INDIRECT(""U""&$C$70&"":U""), INDIRECT(""E""&$C$70&"":E"") = $F$1, INDIRECT(""B""&$C$70&"":B"") >= $A26, INDIRECT(""B""&$C$70&"":B"") <$A27))"),"$2800華通") -> $2800華通
A27: 46204 | B27: =SUMIFS(INDIRECT("C"&$C$70&":C"), INDIRECT("B"&$C$70&":B"), ">="&$A27, INDIRECT("B"&$C$70&":B"), "<"&$A28, INDIRECT("F"&$C$70&":F"), B$2) -> 110300 | C27: =SUMIFS(INDIRECT("C"&$C$70&":C"), INDIRECT("B"&$C$70&":B"), ">="&$A27, INDIRECT("B"&$C$70&":B"), "<"&$A28, INDIRECT("F"&$C$70&":F"), C$2) -> 0 | D27: =SUMIFS(INDIRECT("C"&$C$70&":C"), INDIRECT("B"&$C$70&":B"), ">="&$A27, INDIRECT("B"&$C$70&":B"), "<"&$A28, INDIRECT("F"&$C$70&":F"), D$2) -> 0 | E27: =IFERROR(__xludf.DUMMYFUNCTION("TEXTJOIN("", "", TRUE, FILTER(INDIRECT(""U""&$C$70&"":U""), INDIRECT(""E""&$C$70&"":E"") = $B$1, INDIRECT(""B""&$C$70&"":B"") >= $A27, INDIRECT(""B""&$C$70&"":B"") <$A28))"),"") | F27: =SUMIFS(INDIRECT("C"&$C$70&":C"), INDIRECT("B"&$C$70&":B"), ">="&$A27, INDIRECT("B"&$C$70&":B"), "<"&$A28, INDIRECT("G"&$C$70&":G"), F$2) -> 0 | G27: =SUMIFS(INDIRECT("C"&$C$70&":C"), INDIRECT("B"&$C$70&":B"), ">="&$A27, INDIRECT("B"&$C$70&":B"), "<"&$A28, INDIRECT("G"&$C$70&":G"), G$2) -> 0 | H27: =SUMIFS(INDIRECT("C"&$C$70&":C"), INDIRECT("B"&$C$70&":B"), ">="&$A27, INDIRECT("B"&$C$70&":B"), "<"&$A28, INDIRECT("G"&$C$70&":G"), H$2) -> 0 | I27: =SUMIFS(INDIRECT("C"&$C$70&":C"), INDIRECT("B"&$C$70&":B"), ">="&$A27, INDIRECT("B"&$C$70&":B"), "<"&$A28, INDIRECT("G"&$C$70&":G"), I$2) -> 0 | J27: =SUMIFS(INDIRECT("C"&$C$70&":C"), INDIRECT("B"&$C$70&":B"), ">="&$A27, INDIRECT("B"&$C$70&":B"), "<"&$A28, INDIRECT("G"&$C$70&":G"), J$2) -> 6000 | K27: =SUMIFS(INDIRECT("C"&$C$70&":C"), INDIRECT("B"&$C$70&":B"), ">="&$A27, INDIRECT("B"&$C$70&":B"), "<"&$A28, INDIRECT("G"&$C$70&":G"), K$2) -> 0 | L27: =IFERROR(__xludf.DUMMYFUNCTION("TEXTJOIN("", "", TRUE, FILTER(INDIRECT(""U""&$C$70&"":U""), INDIRECT(""E""&$C$70&"":E"") = $F$1, INDIRECT(""B""&$C$70&"":B"") >= $A27, INDIRECT(""B""&$C$70&"":B"") <$A28))"),"")
A28: 46235 | B28: =SUMIFS(INDIRECT("C"&$C$70&":C"), INDIRECT("B"&$C$70&":B"), ">="&$A28, INDIRECT("B"&$C$70&":B"), "<"&$A29, INDIRECT("F"&$C$70&":F"), B$2) -> 0 | C28: =SUMIFS(INDIRECT("C"&$C$70&":C"), INDIRECT("B"&$C$70&":B"), ">="&$A28, INDIRECT("B"&$C$70&":B"), "<"&$A29, INDIRECT("F"&$C$70&":F"), C$2) -> 0 | D28: =SUMIFS(INDIRECT("C"&$C$70&":C"), INDIRECT("B"&$C$70&":B"), ">="&$A28, INDIRECT("B"&$C$70&":B"), "<"&$A29, INDIRECT("F"&$C$70&":F"), D$2) -> 0 | E28: =IFERROR(__xludf.DUMMYFUNCTION("TEXTJOIN("", "", TRUE, FILTER(INDIRECT(""U""&$C$70&"":U""), INDIRECT(""E""&$C$70&"":E"") = $B$1, INDIRECT(""B""&$C$70&"":B"") >= $A28, INDIRECT(""B""&$C$70&"":B"") <$A29))"),"#N/A") -> #N/A | F28: =SUMIFS(INDIRECT("C"&$C$70&":C"), INDIRECT("B"&$C$70&":B"), ">="&$A28, INDIRECT("B"&$C$70&":B"), "<"&$A29, INDIRECT("G"&$C$70&":G"), F$2) -> 0 | G28: =SUMIFS(INDIRECT("C"&$C$70&":C"), INDIRECT("B"&$C$70&":B"), ">="&$A28, INDIRECT("B"&$C$70&":B"), "<"&$A29, INDIRECT("G"&$C$70&":G"), G$2) -> 0 | H28: =SUMIFS(INDIRECT("C"&$C$70&":C"), INDIRECT("B"&$C$70&":B"), ">="&$A28, INDIRECT("B"&$C$70&":B"), "<"&$A29, INDIRECT("G"&$C$70&":G"), H$2) -> 0 | I28: =SUMIFS(INDIRECT("C"&$C$70&":C"), INDIRECT("B"&$C$70&":B"), ">="&$A28, INDIRECT("B"&$C$70&":B"), "<"&$A29, INDIRECT("G"&$C$70&":G"), I$2) -> 0 | J28: =SUMIFS(INDIRECT("C"&$C$70&":C"), INDIRECT("B"&$C$70&":B"), ">="&$A28, INDIRECT("B"&$C$70&":B"), "<"&$A29, INDIRECT("G"&$C$70&":G"), J$2) -> 0 | K28: =SUMIFS(INDIRECT("C"&$C$70&":C"), INDIRECT("B"&$C$70&":B"), ">="&$A28, INDIRECT("B"&$C$70&":B"), "<"&$A29, INDIRECT("G"&$C$70&":G"), K$2) -> 0 | L28: =IFERROR(__xludf.DUMMYFUNCTION("TEXTJOIN("", "", TRUE, FILTER(INDIRECT(""U""&$C$70&"":U""), INDIRECT(""E""&$C$70&"":E"") = $F$1, INDIRECT(""B""&$C$70&"":B"") >= $A28, INDIRECT(""B""&$C$70&"":B"") <$A29))"),"#N/A") -> #N/A
A29: 46266 | B29: =SUMIFS(INDIRECT("C"&$C$70&":C"), INDIRECT("B"&$C$70&":B"), ">="&$A29, INDIRECT("B"&$C$70&":B"), "<"&$A30, INDIRECT("F"&$C$70&":F"), B$2) -> 0 | C29: =SUMIFS(INDIRECT("C"&$C$70&":C"), INDIRECT("B"&$C$70&":B"), ">="&$A29, INDIRECT("B"&$C$70&":B"), "<"&$A30, INDIRECT("F"&$C$70&":F"), C$2) -> 0 | D29: =SUMIFS(INDIRECT("C"&$C$70&":C"), INDIRECT("B"&$C$70&":B"), ">="&$A29, INDIRECT("B"&$C$70&":B"), "<"&$A30, INDIRECT("F"&$C$70&":F"), D$2) -> 0 | E29: =IFERROR(__xludf.DUMMYFUNCTION("TEXTJOIN("", "", TRUE, FILTER(INDIRECT(""U""&$C$70&"":U""), INDIRECT(""E""&$C$70&"":E"") = $B$1, INDIRECT(""B""&$C$70&"":B"") >= $A29, INDIRECT(""B""&$C$70&"":B"") <$A30))"),"#N/A") -> #N/A | F29: =SUMIFS(INDIRECT("C"&$C$70&":C"), INDIRECT("B"&$C$70&":B"), ">="&$A29, INDIRECT("B"&$C$70&":B"), "<"&$A30, INDIRECT("G"&$C$70&":G"), F$2) -> 0 | G29: =SUMIFS(INDIRECT("C"&$C$70&":C"), INDIRECT("B"&$C$70&":B"), ">="&$A29, INDIRECT("B"&$C$70&":B"), "<"&$A30, INDIRECT("G"&$C$70&":G"), G$2) -> 0 | H29: =SUMIFS(INDIRECT("C"&$C$70&":C"), INDIRECT("B"&$C$70&":B"), ">="&$A29, INDIRECT("B"&$C$70&":B"), "<"&$A30, INDIRECT("G"&$C$70&":G"), H$2) -> 0 | I29: =SUMIFS(INDIRECT("C"&$C$70&":C"), INDIRECT("B"&$C$70&":B"), ">="&$A29, INDIRECT("B"&$C$70&":B"), "<"&$A30, INDIRECT("G"&$C$70&":G"), I$2) -> 0 | J29: =SUMIFS(INDIRECT("C"&$C$70&":C"), INDIRECT("B"&$C$70&":B"), ">="&$A29, INDIRECT("B"&$C$70&":B"), "<"&$A30, INDIRECT("G"&$C$70&":G"), J$2) -> 0 | K29: =SUMIFS(INDIRECT("C"&$C$70&":C"), INDIRECT("B"&$C$70&":B"), ">="&$A29, INDIRECT("B"&$C$70&":B"), "<"&$A30, INDIRECT("G"&$C$70&":G"), K$2) -> 0 | L29: =IFERROR(__xludf.DUMMYFUNCTION("TEXTJOIN("", "", TRUE, FILTER(INDIRECT(""U""&$C$70&"":U""), INDIRECT(""E""&$C$70&"":E"") = $F$1, INDIRECT(""B""&$C$70&"":B"") >= $A29, INDIRECT(""B""&$C$70&"":B"") <$A30))"),"#N/A") -> #N/A
A30: 46296 | B30: =SUMIFS(INDIRECT("C"&$C$70&":C"), INDIRECT("B"&$C$70&":B"), ">="&$A30, INDIRECT("B"&$C$70&":B"), "<"&$A31, INDIRECT("F"&$C$70&":F"), B$2) -> 0 | C30: =SUMIFS(INDIRECT("C"&$C$70&":C"), INDIRECT("B"&$C$70&":B"), ">="&$A30, INDIRECT("B"&$C$70&":B"), "<"&$A31, INDIRECT("F"&$C$70&":F"), C$2) -> 0 | D30: =SUMIFS(INDIRECT("C"&$C$70&":C"), INDIRECT("B"&$C$70&":B"), ">="&$A30, INDIRECT("B"&$C$70&":B"), "<"&$A31, INDIRECT("F"&$C$70&":F"), D$2) -> 0 | E30: =IFERROR(__xludf.DUMMYFUNCTION("TEXTJOIN("", "", TRUE, FILTER(INDIRECT(""U""&$C$70&"":U""), INDIRECT(""E""&$C$70&"":E"") = $B$1, INDIRECT(""B""&$C$70&"":B"") >= $A30, INDIRECT(""B""&$C$70&"":B"") <$A31))"),"#N/A") -> #N/A | F30: =SUMIFS(INDIRECT("C"&$C$70&":C"), INDIRECT("B"&$C$70&":B"), ">="&$A30, INDIRECT("B"&$C$70&":B"), "<"&$A31, INDIRECT("G"&$C$70&":G"), F$2) -> 0 | G30: =SUMIFS(INDIRECT("C"&$C$70&":C"), INDIRECT("B"&$C$70&":B"), ">="&$A30, INDIRECT("B"&$C$70&":B"), "<"&$A31, INDIRECT("G"&$C$70&":G"), G$2) -> 0 | H30: =SUMIFS(INDIRECT("C"&$C$70&":C"), INDIRECT("B"&$C$70&":B"), ">="&$A30, INDIRECT("B"&$C$70&":B"), "<"&$A31, INDIRECT("G"&$C$70&":G"), H$2) -> 0 | I30: =SUMIFS(INDIRECT("C"&$C$70&":C"), INDIRECT("B"&$C$70&":B"), ">="&$A30, INDIRECT("B"&$C$70&":B"), "<"&$A31, INDIRECT("G"&$C$70&":G"), I$2) -> 0 | J30: =SUMIFS(INDIRECT("C"&$C$70&":C"), INDIRECT("B"&$C$70&":B"), ">="&$A30, INDIRECT("B"&$C$70&":B"), "<"&$A31, INDIRECT("G"&$C$70&":G"), J$2) -> 0 | K30: =SUMIFS(INDIRECT("C"&$C$70&":C"), INDIRECT("B"&$C$70&":B"), ">="&$A30, INDIRECT("B"&$C$70&":B"), "<"&$A31, INDIRECT("G"&$C$70&":G"), K$2) -> 0 | L30: =IFERROR(__xludf.DUMMYFUNCTION("TEXTJOIN("", "", TRUE, FILTER(INDIRECT(""U""&$C$70&"":U""), INDIRECT(""E""&$C$70&"":E"") = $F$1, INDIRECT(""B""&$C$70&"":B"") >= $A30, INDIRECT(""B""&$C$70&"":B"") <$A31))"),"#N/A") -> #N/A
A31: 46327 | B31: =SUMIFS(INDIRECT("C"&$C$70&":C"), INDIRECT("B"&$C$70&":B"), ">="&$A31, INDIRECT("B"&$C$70&":B"), "<"&$A32, INDIRECT("F"&$C$70&":F"), B$2) -> 0 | C31: =SUMIFS(INDIRECT("C"&$C$70&":C"), INDIRECT("B"&$C$70&":B"), ">="&$A31, INDIRECT("B"&$C$70&":B"), "<"&$A32, INDIRECT("F"&$C$70&":F"), C$2) -> 0 | D31: =SUMIFS(INDIRECT("C"&$C$70&":C"), INDIRECT("B"&$C$70&":B"), ">="&$A31, INDIRECT("B"&$C$70&":B"), "<"&$A32, INDIRECT("F"&$C$70&":F"), D$2) -> 0 | E31: =IFERROR(__xludf.DUMMYFUNCTION("TEXTJOIN("", "", TRUE, FILTER(INDIRECT(""U""&$C$70&"":U""), INDIRECT(""E""&$C$70&"":E"") = $B$1, INDIRECT(""B""&$C$70&"":B"") >= $A31, INDIRECT(""B""&$C$70&"":B"") <$A32))"),"#N/A") -> #N/A | F31: =SUMIFS(INDIRECT("C"&$C$70&":C"), INDIRECT("B"&$C$70&":B"), ">="&$A31, INDIRECT("B"&$C$70&":B"), "<"&$A32, INDIRECT("G"&$C$70&":G"), F$2) -> 0 | G31: =SUMIFS(INDIRECT("C"&$C$70&":C"), INDIRECT("B"&$C$70&":B"), ">="&$A31, INDIRECT("B"&$C$70&":B"), "<"&$A32, INDIRECT("G"&$C$70&":G"), G$2) -> 0 | H31: =SUMIFS(INDIRECT("C"&$C$70&":C"), INDIRECT("B"&$C$70&":B"), ">="&$A31, INDIRECT("B"&$C$70&":B"), "<"&$A32, INDIRECT("G"&$C$70&":G"), H$2) -> 0 | I31: =SUMIFS(INDIRECT("C"&$C$70&":C"), INDIRECT("B"&$C$70&":B"), ">="&$A31, INDIRECT("B"&$C$70&":B"), "<"&$A32, INDIRECT("G"&$C$70&":G"), I$2) -> 0 | J31: =SUMIFS(INDIRECT("C"&$C$70&":C"), INDIRECT("B"&$C$70&":B"), ">="&$A31, INDIRECT("B"&$C$70&":B"), "<"&$A32, INDIRECT("G"&$C$70&":G"), J$2) -> 0 | K31: =SUMIFS(INDIRECT("C"&$C$70&":C"), INDIRECT("B"&$C$70&":B"), ">="&$A31, INDIRECT("B"&$C$70&":B"), "<"&$A32, INDIRECT("G"&$C$70&":G"), K$2) -> 0 | L31: =IFERROR(__xludf.DUMMYFUNCTION("TEXTJOIN("", "", TRUE, FILTER(INDIRECT(""U""&$C$70&"":U""), INDIRECT(""E""&$C$70&"":E"") = $F$1, INDIRECT(""B""&$C$70&"":B"") >= $A31, INDIRECT(""B""&$C$70&"":B"") <$A32))"),"#N/A") -> #N/A
A32: 46357 | B32: =SUMIFS(INDIRECT("C"&$C$70&":C"), INDIRECT("B"&$C$70&":B"), ">="&$A32, INDIRECT("B"&$C$70&":B"), "<"&$A33, INDIRECT("F"&$C$70&":F"), B$2) -> 0 | C32: =SUMIFS(INDIRECT("C"&$C$70&":C"), INDIRECT("B"&$C$70&":B"), ">="&$A32, INDIRECT("B"&$C$70&":B"), "<"&$A33, INDIRECT("F"&$C$70&":F"), C$2) -> 0 | D32: =SUMIFS(INDIRECT("C"&$C$70&":C"), INDIRECT("B"&$C$70&":B"), ">="&$A32, INDIRECT("B"&$C$70&":B"), "<"&$A33, INDIRECT("F"&$C$70&":F"), D$2) -> 0 | E32: =IFERROR(__xludf.DUMMYFUNCTION("TEXTJOIN("", "", TRUE, FILTER(INDIRECT(""U""&$C$70&"":U""), INDIRECT(""E""&$C$70&"":E"") = $B$1, INDIRECT(""B""&$C$70&"":B"") >= $A32, INDIRECT(""B""&$C$70&"":B"") <$A33))"),"#N/A") -> #N/A | F32: =SUMIFS(INDIRECT("C"&$C$70&":C"), INDIRECT("B"&$C$70&":B"), ">="&$A32, INDIRECT("B"&$C$70&":B"), "<"&$A33, INDIRECT("G"&$C$70&":G"), F$2) -> 0 | G32: =SUMIFS(INDIRECT("C"&$C$70&":C"), INDIRECT("B"&$C$70&":B"), ">="&$A32, INDIRECT("B"&$C$70&":B"), "<"&$A33, INDIRECT("G"&$C$70&":G"), G$2) -> 0 | H32: =SUMIFS(INDIRECT("C"&$C$70&":C"), INDIRECT("B"&$C$70&":B"), ">="&$A32, INDIRECT("B"&$C$70&":B"), "<"&$A33, INDIRECT("G"&$C$70&":G"), H$2) -> 0 | I32: =SUMIFS(INDIRECT("C"&$C$70&":C"), INDIRECT("B"&$C$70&":B"), ">="&$A32, INDIRECT("B"&$C$70&":B"), "<"&$A33, INDIRECT("G"&$C$70&":G"), I$2) -> 0 | J32: =SUMIFS(INDIRECT("C"&$C$70&":C"), INDIRECT("B"&$C$70&":B"), ">="&$A32, INDIRECT("B"&$C$70&":B"), "<"&$A33, INDIRECT("G"&$C$70&":G"), J$2) -> 0 | K32: =SUMIFS(INDIRECT("C"&$C$70&":C"), INDIRECT("B"&$C$70&":B"), ">="&$A32, INDIRECT("B"&$C$70&":B"), "<"&$A33, INDIRECT("G"&$C$70&":G"), K$2) -> 0 | L32: =IFERROR(__xludf.DUMMYFUNCTION("TEXTJOIN("", "", TRUE, FILTER(INDIRECT(""U""&$C$70&"":U""), INDIRECT(""E""&$C$70&"":E"") = $F$1, INDIRECT(""B""&$C$70&"":B"") >= $A32, INDIRECT(""B""&$C$70&"":B"") <$A33))"),"#N/A") -> #N/A
B34: 生活 | D34: 稅金/利息 | F34: 房屋 | K34: 汽機車 | Q34: 其他 | S34: 備註
A35: 開銷 | B35: 生活花費 | C35: 電話費 | D35: 勞健保 | E35: 稅金 | F35: 房租(含文心1) | G35: 管理費 | H35: 水費 | I35: 電費 | J35: 瓦斯費 | K35: 車-保險稅金 | L35: 保養 | M35: 加油 | N35: Etag | O35: 停車 | P35: 其他(洗車,罰單,配件) | Q35: 公司認股 | R35: 其他 | S35: 備註
A36: 45474 | B36: =SUMIFS(INDIRECT("C"&$C$70&":C"), INDIRECT("B"&$C$70&":B"), ">="&$A36, INDIRECT("B"&$C$70&":B"), "<"&$A37, INDIRECT("H"&$C$70&":H"), "<>") - SUM($C36:$R36) -> 20888 | C36: =SUMIFS(INDIRECT("C"&$C$70&":C"), INDIRECT("B"&$C$70&":B"), ">="&$A36, INDIRECT("B"&$C$70&":B"), "<"&$A37, INDIRECT("J"&$C$70&":J"), C$35) -> 728 | D36: =SUMIFS(INDIRECT("C"&$C$70&":C"), INDIRECT("B"&$C$70&":B"), ">="&$A36, INDIRECT("B"&$C$70&":B"), "<"&$A37, INDIRECT("N"&$C$70&":N"), D$35) -> 2701 | E36: =SUMIFS(INDIRECT("C"&$C$70&":C"), INDIRECT("B"&$C$70&":B"), ">="&$A36, INDIRECT("B"&$C$70&":B"), "<"&$A37, INDIRECT("N"&$C$70&":N"), E$35) -> 7110 | F36: =SUMIFS(INDIRECT("C"&$C$70&":C"), INDIRECT("B"&$C$70&":B"), ">="&$A36, INDIRECT("B"&$C$70&":B"), "<"&$A37, INDIRECT("K"&$C$70&":K"), "文心1房貸代繳") + SUMIFS(INDIRECT("C"&$C$70&":C"), INDIRECT("B"&$C$70&":B"), ">="&$A36, INDIRECT("B"&$C$70&":B"), "<"&$A37, INDIRECT("K"&$C$70&":K"), "租屋") -> 0 | G36: =SUMIFS(INDIRECT("C"&$C$70&":C"), INDIRECT("B"&$C$70&":B"), ">="&$A36, INDIRECT("B"&$C$70&":B"), "<"&$A37, INDIRECT("K"&$C$70&":K"), G$35) -> 0 | H36: =SUMIFS(INDIRECT("C"&$C$70&":C"), INDIRECT("B"&$C$70&":B"), ">="&$A36, INDIRECT("B"&$C$70&":B"), "<"&$A37, INDIRECT("K"&$C$70&":K"), H$35) -> 0 | I36: =SUMIFS(INDIRECT("C"&$C$70&":C"), INDIRECT("B"&$C$70&":B"), ">="&$A36, INDIRECT("B"&$C$70&":B"), "<"&$A37, INDIRECT("K"&$C$70&":K"), I$35) -> 384 | J36: =SUMIFS(INDIRECT("C"&$C$70&":C"), INDIRECT("B"&$C$70&":B"), ">="&$A36, INDIRECT("B"&$C$70&":B"), "<"&$A37, INDIRECT("K"&$C$70&":K"), J$35) -> 0 | K36: =SUMIFS(INDIRECT("C"&$C$70&":C"), INDIRECT("B"&$C$70&":B"), ">="&$A36, INDIRECT("B"&$C$70&":B"), "<"&$A37, INDIRECT("L"&$C$70&":L"), K$35) -> 0 | L36: =SUMIFS(INDIRECT("C"&$C$70&":C"), INDIRECT("B"&$C$70&":B"), ">="&$A36, INDIRECT("B"&$C$70&":B"), "<"&$A37, INDIRECT("L"&$C$70&":L"), L$35) -> 0 | M36: =SUMIFS(INDIRECT("C"&$C$70&":C"), INDIRECT("B"&$C$70&":B"), ">="&$A36, INDIRECT("B"&$C$70&":B"), "<"&$A37, INDIRECT("L"&$C$70&":L"), M$35) -> 1421 | N36: =SUMIFS(INDIRECT("C"&$C$70&":C"), INDIRECT("B"&$C$70&":B"), ">="&$A36, INDIRECT("B"&$C$70&":B"), "<"&$A37, INDIRECT("L"&$C$70&":L"), N$35) -> 800 | O36: =SUMIFS(INDIRECT("C"&$C$70&":C"), INDIRECT("B"&$C$70&":B"), ">="&$A36, INDIRECT("B"&$C$70&":B"), "<"&$A37, INDIRECT("L"&$C$70&":L"), O$35) -> 115 | P36: =SUMIFS(INDIRECT("C"&$C$70&":C"), INDIRECT("B"&$C$70&":B"), ">="&$A36, INDIRECT("B"&$C$70&":B"), "<"&$A37, INDIRECT("L"&$C$70&":L"), P$35) -> 0 | Q36: =SUMIFS(INDIRECT("C"&$C$70&":C"), INDIRECT("B"&$C$70&":B"), ">="&$A36, INDIRECT("B"&$C$70&":B"), "<"&$A37, INDIRECT("R"&$C$70&":R"), Q$35) -> 3087 | R36: =SUMIFS(INDIRECT("C"&$C$70&":C"), INDIRECT("A"&$C$70&":A"), ">="&$A36, INDIRECT("A"&$C$70&":A"), "<"&$A37, INDIRECT("R"&$C$70&":R"), "<>公司認股", INDIRECT("R"&$C$70&":R"), "<>") -> 0 | S36: =IFERROR(__xludf.DUMMYFUNCTION("TEXTJOIN("", "", TRUE, FILTER(INDIRECT(""U""&$C$70&"":U""), INDIRECT(""H""&$C$70&"":H"") <>"""", INDIRECT(""B""&$C$70&"":B"") >= $A3, INDIRECT(""B""&$C$70&"":B"") <$A4))"),"$6600中瑋萬豪婚禮2人, $384竹南電費, $7110獎金稅") -> $6600中瑋萬豪婚禮2人, $384竹南電費, $7110獎金稅
A37: 45505 | B37: =SUMIFS(INDIRECT("C"&$C$70&":C"), INDIRECT("B"&$C$70&":B"), ">="&$A37, INDIRECT("B"&$C$70&":B"), "<"&$A38, INDIRECT("H"&$C$70&":H"), "<>") - SUM($C37:$R37) -> 52528 | C37: =SUMIFS(INDIRECT("C"&$C$70&":C"), INDIRECT("B"&$C$70&":B"), ">="&$A37, INDIRECT("B"&$C$70&":B"), "<"&$A38, INDIRECT("J"&$C$70&":J"), C$35) -> 0 | D37: =SUMIFS(INDIRECT("C"&$C$70&":C"), INDIRECT("B"&$C$70&":B"), ">="&$A37, INDIRECT("B"&$C$70&":B"), "<"&$A38, INDIRECT("N"&$C$70&":N"), D$35) -> 2701 | E37: =SUMIFS(INDIRECT("C"&$C$70&":C"), INDIRECT("B"&$C$70&":B"), ">="&$A37, INDIRECT("B"&$C$70&":B"), "<"&$A38, INDIRECT("N"&$C$70&":N"), E$35) -> 3260 | F37: =SUMIFS(INDIRECT("C"&$C$70&":C"), INDIRECT("B"&$C$70&":B"), ">="&$A37, INDIRECT("B"&$C$70&":B"), "<"&$A38, INDIRECT("K"&$C$70&":K"), "文心1房貸代繳") + SUMIFS(INDIRECT("C"&$C$70&":C"), INDIRECT("B"&$C$70&":B"), ">="&$A37, INDIRECT("B"&$C$70&":B"), "<"&$A38, INDIRECT("K"&$C$70&":K"), "租屋") -> 26000 | G37: =SUMIFS(INDIRECT("C"&$C$70&":C"), INDIRECT("B"&$C$70&":B"), ">="&$A37, INDIRECT("B"&$C$70&":B"), "<"&$A38, INDIRECT("K"&$C$70&":K"), G$35) -> 0 | H37: =SUMIFS(INDIRECT("C"&$C$70&":C"), INDIRECT("B"&$C$70&":B"), ">="&$A37, INDIRECT("B"&$C$70&":B"), "<"&$A38, INDIRECT("K"&$C$70&":K"), H$35) -> 0 | I37: =SUMIFS(INDIRECT("C"&$C$70&":C"), INDIRECT("B"&$C$70&":B"), ">="&$A37, INDIRECT("B"&$C$70&":B"), "<"&$A38, INDIRECT("K"&$C$70&":K"), I$35) -> 1679 | J37: =SUMIFS(INDIRECT("C"&$C$70&":C"), INDIRECT("B"&$C$70&":B"), ">="&$A37, INDIRECT("B"&$C$70&":B"), "<"&$A38, INDIRECT("K"&$C$70&":K"), J$35) -> 0 | K37: =SUMIFS(INDIRECT("C"&$C$70&":C"), INDIRECT("B"&$C$70&":B"), ">="&$A37, INDIRECT("B"&$C$70&":B"), "<"&$A38, INDIRECT("L"&$C$70&":L"), K$35) -> 0 | L37: =SUMIFS(INDIRECT("C"&$C$70&":C"), INDIRECT("B"&$C$70&":B"), ">="&$A37, INDIRECT("B"&$C$70&":B"), "<"&$A38, INDIRECT("L"&$C$70&":L"), L$35) -> 0 | M37: =SUMIFS(INDIRECT("C"&$C$70&":C"), INDIRECT("B"&$C$70&":B"), ">="&$A37, INDIRECT("B"&$C$70&":B"), "<"&$A38, INDIRECT("L"&$C$70&":L"), M$35) -> 1706 | N37: =SUMIFS(INDIRECT("C"&$C$70&":C"), INDIRECT("B"&$C$70&":B"), ">="&$A37, INDIRECT("B"&$C$70&":B"), "<"&$A38, INDIRECT("L"&$C$70&":L"), N$35) -> 0 | O37: =SUMIFS(INDIRECT("C"&$C$70&":C"), INDIRECT("B"&$C$70&":B"), ">="&$A37, INDIRECT("B"&$C$70&":B"), "<"&$A38, INDIRECT("L"&$C$70&":L"), O$35) -> 0 | P37: =SUMIFS(INDIRECT("C"&$C$70&":C"), INDIRECT("B"&$C$70&":B"), ">="&$A37, INDIRECT("B"&$C$70&":B"), "<"&$A38, INDIRECT("L"&$C$70&":L"), P$35) -> 0 | Q37: =SUMIFS(INDIRECT("C"&$C$70&":C"), INDIRECT("B"&$C$70&":B"), ">="&$A37, INDIRECT("B"&$C$70&":B"), "<"&$A38, INDIRECT("R"&$C$70&":R"), Q$35) -> 3087 | R37: =SUMIFS(INDIRECT("C"&$C$70&":C"), INDIRECT("A"&$C$70&":A"), ">="&$A37, INDIRECT("A"&$C$70&":A"), "<"&$A38, INDIRECT("R"&$C$70&":R"), "<>公司認股", INDIRECT("R"&$C$70&":R"), "<>") -> 0 | S37: =IFERROR(__xludf.DUMMYFUNCTION("TEXTJOIN("", "", TRUE, FILTER(INDIRECT(""U""&$C$70&"":U""), INDIRECT(""H""&$C$70&"":H"") <>"""", INDIRECT(""B""&$C$70&"":B"") >= $A4, INDIRECT(""B""&$C$70&"":B"") <$A5))"),"$1888麟洋紀念酒, $40000韓國旅遊兩人(大概值)") -> $1888麟洋紀念酒, $40000韓國旅遊兩人(大概值)
A38: 45536 | B38: =SUMIFS(INDIRECT("C"&$C$70&":C"), INDIRECT("B"&$C$70&":B"), ">="&$A38, INDIRECT("B"&$C$70&":B"), "<"&$A39, INDIRECT("H"&$C$70&":H"), "<>") - SUM($C38:$R38) -> 28800 | C38: =SUMIFS(INDIRECT("C"&$C$70&":C"), INDIRECT("B"&$C$70&":B"), ">="&$A38, INDIRECT("B"&$C$70&":B"), "<"&$A39, INDIRECT("J"&$C$70&":J"), C$35) -> 798 | D38: =SUMIFS(INDIRECT("C"&$C$70&":C"), INDIRECT("B"&$C$70&":B"), ">="&$A38, INDIRECT("B"&$C$70&":B"), "<"&$A39, INDIRECT("N"&$C$70&":N"), D$35) -> 2771 | E38: =SUMIFS(INDIRECT("C"&$C$70&":C"), INDIRECT("B"&$C$70&":B"), ">="&$A38, INDIRECT("B"&$C$70&":B"), "<"&$A39, INDIRECT("N"&$C$70&":N"), E$35) -> 3260 | F38: =SUMIFS(INDIRECT("C"&$C$70&":C"), INDIRECT("B"&$C$70&":B"), ">="&$A38, INDIRECT("B"&$C$70&":B"), "<"&$A39, INDIRECT("K"&$C$70&":K"), "文心1房貸代繳") + SUMIFS(INDIRECT("C"&$C$70&":C"), INDIRECT("B"&$C$70&":B"), ">="&$A38, INDIRECT("B"&$C$70&":B"), "<"&$A39, INDIRECT("K"&$C$70&":K"), "租屋") -> 26000 | G38: =SUMIFS(INDIRECT("C"&$C$70&":C"), INDIRECT("B"&$C$70&":B"), ">="&$A38, INDIRECT("B"&$C$70&":B"), "<"&$A39, INDIRECT("K"&$C$70&":K"), G$35) -> 6602 | H38: =SUMIFS(INDIRECT("C"&$C$70&":C"), INDIRECT("B"&$C$70&":B"), ">="&$A38, INDIRECT("B"&$C$70&":B"), "<"&$A39, INDIRECT("K"&$C$70&":K"), H$35) -> 205 | I38: =SUMIFS(INDIRECT("C"&$C$70&":C"), INDIRECT("B"&$C$70&":B"), ">="&$A38, INDIRECT("B"&$C$70&":B"), "<"&$A39, INDIRECT("K"&$C$70&":K"), I$35) -> 0 | J38: =SUMIFS(INDIRECT("C"&$C$70&":C"), INDIRECT("B"&$C$70&":B"), ">="&$A38, INDIRECT("B"&$C$70&":B"), "<"&$A39, INDIRECT("K"&$C$70&":K"), J$35) -> 305 | K38: =SUMIFS(INDIRECT("C"&$C$70&":C"), INDIRECT("B"&$C$70&":B"), ">="&$A38, INDIRECT("B"&$C$70&":B"), "<"&$A39, INDIRECT("L"&$C$70&":L"), K$35) -> 0 | L38: =SUMIFS(INDIRECT("C"&$C$70&":C"), INDIRECT("B"&$C$70&":B"), ">="&$A38, INDIRECT("B"&$C$70&":B"), "<"&$A39, INDIRECT("L"&$C$70&":L"), L$35) -> 0 | M38: =SUMIFS(INDIRECT("C"&$C$70&":C"), INDIRECT("B"&$C$70&":B"), ">="&$A38, INDIRECT("B"&$C$70&":B"), "<"&$A39, INDIRECT("L"&$C$70&":L"), M$35) -> 2185 | N38: =SUMIFS(INDIRECT("C"&$C$70&":C"), INDIRECT("B"&$C$70&":B"), ">="&$A38, INDIRECT("B"&$C$70&":B"), "<"&$A39, INDIRECT("L"&$C$70&":L"), N$35) -> 0 | O38: =SUMIFS(INDIRECT("C"&$C$70&":C"), INDIRECT("B"&$C$70&":B"), ">="&$A38, INDIRECT("B"&$C$70&":B"), "<"&$A39, INDIRECT("L"&$C$70&":L"), O$35) -> 220 | P38: =SUMIFS(INDIRECT("C"&$C$70&":C"), INDIRECT("B"&$C$70&":B"), ">="&$A38, INDIRECT("B"&$C$70&":B"), "<"&$A39, INDIRECT("L"&$C$70&":L"), P$35) -> 0 | Q38: =SUMIFS(INDIRECT("C"&$C$70&":C"), INDIRECT("B"&$C$70&":B"), ">="&$A38, INDIRECT("B"&$C$70&":B"), "<"&$A39, INDIRECT("R"&$C$70&":R"), Q$35) -> 3087 | R38: =SUMIFS(INDIRECT("C"&$C$70&":C"), INDIRECT("A"&$C$70&":A"), ">="&$A38, INDIRECT("A"&$C$70&":A"), "<"&$A39, INDIRECT("R"&$C$70&":R"), "<>公司認股", INDIRECT("R"&$C$70&":R"), "<>") -> 0 | S38: =IFERROR(__xludf.DUMMYFUNCTION("TEXTJOIN("", "", TRUE, FILTER(INDIRECT(""U""&$C$70&"":U""), INDIRECT(""H""&$C$70&"":H"") <>"""", INDIRECT(""B""&$C$70&"":B"") >= $A5, INDIRECT(""B""&$C$70&"":B"") <$A6))"),"$5000培揚婚禮兩人, $3010高雄寒軒") -> $5000培揚婚禮兩人, $3010高雄寒軒
A39: 45566 | B39: =SUMIFS(INDIRECT("C"&$C$70&":C"), INDIRECT("B"&$C$70&":B"), ">="&$A39, INDIRECT("B"&$C$70&":B"), "<"&$A40, INDIRECT("H"&$C$70&":H"), "<>") - SUM($C39:$R39) -> 104344 | C39: =SUMIFS(INDIRECT("C"&$C$70&":C"), INDIRECT("B"&$C$70&":B"), ">="&$A39, INDIRECT("B"&$C$70&":B"), "<"&$A40, INDIRECT("J"&$C$70&":J"), C$35) -> 0 | D39: =SUMIFS(INDIRECT("C"&$C$70&":C"), INDIRECT("B"&$C$70&":B"), ">="&$A39, INDIRECT("B"&$C$70&":B"), "<"&$A40, INDIRECT("N"&$C$70&":N"), D$35) -> 0 | E39: =SUMIFS(INDIRECT("C"&$C$70&":C"), INDIRECT("B"&$C$70&":B"), ">="&$A39, INDIRECT("B"&$C$70&":B"), "<"&$A40, INDIRECT("N"&$C$70&":N"), E$35) -> 1593 | F39: =SUMIFS(INDIRECT("C"&$C$70&":C"), INDIRECT("B"&$C$70&":B"), ">="&$A39, INDIRECT("B"&$C$70&":B"), "<"&$A40, INDIRECT("K"&$C$70&":K"), "文心1房貸代繳") + SUMIFS(INDIRECT("C"&$C$70&":C"), INDIRECT("B"&$C$70&":B"), ">="&$A39, INDIRECT("B"&$C$70&":B"), "<"&$A40, INDIRECT("K"&$C$70&":K"), "租屋") -> 26000 | G39: =SUMIFS(INDIRECT("C"&$C$70&":C"), INDIRECT("B"&$C$70&":B"), ">="&$A39, INDIRECT("B"&$C$70&":B"), "<"&$A40, INDIRECT("K"&$C$70&":K"), G$35) -> 0 | H39: =SUMIFS(INDIRECT("C"&$C$70&":C"), INDIRECT("B"&$C$70&":B"), ">="&$A39, INDIRECT("B"&$C$70&":B"), "<"&$A40, INDIRECT("K"&$C$70&":K"), H$35) -> 0 | I39: =SUMIFS(INDIRECT("C"&$C$70&":C"), INDIRECT("B"&$C$70&":B"), ">="&$A39, INDIRECT("B"&$C$70&":B"), "<"&$A40, INDIRECT("K"&$C$70&":K"), I$35) -> 1444 | J39: =SUMIFS(INDIRECT("C"&$C$70&":C"), INDIRECT("B"&$C$70&":B"), ">="&$A39, INDIRECT("B"&$C$70&":B"), "<"&$A40, INDIRECT("K"&$C$70&":K"), J$35) -> 0 | K39: =SUMIFS(INDIRECT("C"&$C$70&":C"), INDIRECT("B"&$C$70&":B"), ">="&$A39, INDIRECT("B"&$C$70&":B"), "<"&$A40, INDIRECT("L"&$C$70&":L"), K$35) -> 0 | L39: =SUMIFS(INDIRECT("C"&$C$70&":C"), INDIRECT("B"&$C$70&":B"), ">="&$A39, INDIRECT("B"&$C$70&":B"), "<"&$A40, INDIRECT("L"&$C$70&":L"), L$35) -> 0 | M39: =SUMIFS(INDIRECT("C"&$C$70&":C"), INDIRECT("B"&$C$70&":B"), ">="&$A39, INDIRECT("B"&$C$70&":B"), "<"&$A40, INDIRECT("L"&$C$70&":L"), M$35) -> 2961 | N39: =SUMIFS(INDIRECT("C"&$C$70&":C"), INDIRECT("B"&$C$70&":B"), ">="&$A39, INDIRECT("B"&$C$70&":B"), "<"&$A40, INDIRECT("L"&$C$70&":L"), N$35) -> 400 | O39: =SUMIFS(INDIRECT("C"&$C$70&":C"), INDIRECT("B"&$C$70&":B"), ">="&$A39, INDIRECT("B"&$C$70&":B"), "<"&$A40, INDIRECT("L"&$C$70&":L"), O$35) -> 400 | P39: =SUMIFS(INDIRECT("C"&$C$70&":C"), INDIRECT("B"&$C$70&":B"), ">="&$A39, INDIRECT("B"&$C$70&":B"), "<"&$A40, INDIRECT("L"&$C$70&":L"), P$35) -> 0 | Q39: =SUMIFS(INDIRECT("C"&$C$70&":C"), INDIRECT("B"&$C$70&":B"), ">="&$A39, INDIRECT("B"&$C$70&":B"), "<"&$A40, INDIRECT("R"&$C$70&":R"), Q$35) -> 0 | R39: =SUMIFS(INDIRECT("C"&$C$70&":C"), INDIRECT("A"&$C$70&":A"), ">="&$A39, INDIRECT("A"&$C$70&":A"), "<"&$A40, INDIRECT("R"&$C$70&":R"), "<>公司認股", INDIRECT("R"&$C$70&":R"), "<>") -> 0 | S39: =IFERROR(__xludf.DUMMYFUNCTION("TEXTJOIN("", "", TRUE, FILTER(INDIRECT(""U""&$C$70&"":U""), INDIRECT(""H""&$C$70&"":H"") <>"""", INDIRECT(""B""&$C$70&"":B"") >= $A6, INDIRECT(""B""&$C$70&"":B"") <$A7))"),"$5700溪頭米堤飯店訂金, $13167米堤飯店*3間（$6289*3-$5700訂金）, $13180燦坤AirPods pro2 $6590*2, $38910燦坤Panasonic 15公斤熱泵除濕式滾筒衣機<NA-V150RPH-K（夜幕黑）$53910-$15000寶補助, $3494寶鞋*2, $3578我鞋*2, $7999IKEA-MILSBO-玻璃門櫃, $1593獎金補充保費") -> $5700溪頭米堤飯店訂金, $13167米堤飯店*3間（$6289*3-$5700訂金）, $13180燦坤AirPods pro2 $6590*2, $38910燦坤Panasonic 15公斤熱泵除濕式滾筒衣機<NA-V150RPH-K（夜幕黑）$53910-$15000寶補助, $3494寶鞋*2, $3578我鞋*2, $7999IKEA-MILSBO-玻璃門櫃, $1593獎金補充保費
A40: 45597 | B40: =SUMIFS(INDIRECT("C"&$C$70&":C"), INDIRECT("B"&$C$70&":B"), ">="&$A40, INDIRECT("B"&$C$70&":B"), "<"&$A41, INDIRECT("H"&$C$70&":H"), "<>") - SUM($C40:$R40) -> 18420 | C40: =SUMIFS(INDIRECT("C"&$C$70&":C"), INDIRECT("B"&$C$70&":B"), ">="&$A40, INDIRECT("B"&$C$70&":B"), "<"&$A41, INDIRECT("J"&$C$70&":J"), C$35) -> 788 | D40: =SUMIFS(INDIRECT("C"&$C$70&":C"), INDIRECT("B"&$C$70&":B"), ">="&$A40, INDIRECT("B"&$C$70&":B"), "<"&$A41, INDIRECT("N"&$C$70&":N"), D$35) -> 2771 | E40: =SUMIFS(INDIRECT("C"&$C$70&":C"), INDIRECT("B"&$C$70&":B"), ">="&$A40, INDIRECT("B"&$C$70&":B"), "<"&$A41, INDIRECT("N"&$C$70&":N"), E$35) -> 3260 | F40: =SUMIFS(INDIRECT("C"&$C$70&":C"), INDIRECT("B"&$C$70&":B"), ">="&$A40, INDIRECT("B"&$C$70&":B"), "<"&$A41, INDIRECT("K"&$C$70&":K"), "文心1房貸代繳") + SUMIFS(INDIRECT("C"&$C$70&":C"), INDIRECT("B"&$C$70&":B"), ">="&$A40, INDIRECT("B"&$C$70&":B"), "<"&$A41, INDIRECT("K"&$C$70&":K"), "租屋") -> 26000 | G40: =SUMIFS(INDIRECT("C"&$C$70&":C"), INDIRECT("B"&$C$70&":B"), ">="&$A40, INDIRECT("B"&$C$70&":B"), "<"&$A41, INDIRECT("K"&$C$70&":K"), G$35) -> 6102 | H40: =SUMIFS(INDIRECT("C"&$C$70&":C"), INDIRECT("B"&$C$70&":B"), ">="&$A40, INDIRECT("B"&$C$70&":B"), "<"&$A41, INDIRECT("K"&$C$70&":K"), H$35) -> 151 | I40: =SUMIFS(INDIRECT("C"&$C$70&":C"), INDIRECT("B"&$C$70&":B"), ">="&$A40, INDIRECT("B"&$C$70&":B"), "<"&$A41, INDIRECT("K"&$C$70&":K"), I$35) -> 0 | J40: =SUMIFS(INDIRECT("C"&$C$70&":C"), INDIRECT("B"&$C$70&":B"), ">="&$A40, INDIRECT("B"&$C$70&":B"), "<"&$A41, INDIRECT("K"&$C$70&":K"), J$35) -> 387 | K40: =SUMIFS(INDIRECT("C"&$C$70&":C"), INDIRECT("B"&$C$70&":B"), ">="&$A40, INDIRECT("B"&$C$70&":B"), "<"&$A41, INDIRECT("L"&$C$70&":L"), K$35) -> 0 | L40: =SUMIFS(INDIRECT("C"&$C$70&":C"), INDIRECT("B"&$C$70&":B"), ">="&$A40, INDIRECT("B"&$C$70&":B"), "<"&$A41, INDIRECT("L"&$C$70&":L"), L$35) -> 0 | M40: =SUMIFS(INDIRECT("C"&$C$70&":C"), INDIRECT("B"&$C$70&":B"), ">="&$A40, INDIRECT("B"&$C$70&":B"), "<"&$A41, INDIRECT("L"&$C$70&":L"), M$35) -> 2661 | N40: =SUMIFS(INDIRECT("C"&$C$70&":C"), INDIRECT("B"&$C$70&":B"), ">="&$A40, INDIRECT("B"&$C$70&":B"), "<"&$A41, INDIRECT("L"&$C$70&":L"), N$35) -> 0 | O40: =SUMIFS(INDIRECT("C"&$C$70&":C"), INDIRECT("B"&$C$70&":B"), ">="&$A40, INDIRECT("B"&$C$70&":B"), "<"&$A41, INDIRECT("L"&$C$70&":L"), O$35) -> 20 | P40: =SUMIFS(INDIRECT("C"&$C$70&":C"), INDIRECT("B"&$C$70&":B"), ">="&$A40, INDIRECT("B"&$C$70&":B"), "<"&$A41, INDIRECT("L"&$C$70&":L"), P$35) -> 300 | Q40: =SUMIFS(INDIRECT("C"&$C$70&":C"), INDIRECT("B"&$C$70&":B"), ">="&$A40, INDIRECT("B"&$C$70&":B"), "<"&$A41, INDIRECT("R"&$C$70&":R"), Q$35) -> 3087 | R40: =SUMIFS(INDIRECT("C"&$C$70&":C"), INDIRECT("A"&$C$70&":A"), ">="&$A40, INDIRECT("A"&$C$70&":A"), "<"&$A41, INDIRECT("R"&$C$70&":R"), "<>公司認股", INDIRECT("R"&$C$70&":R"), "<>") -> 0 | S40: =IFERROR(__xludf.DUMMYFUNCTION("TEXTJOIN("", "", TRUE, FILTER(INDIRECT(""U""&$C$70&"":U""), INDIRECT(""H""&$C$70&"":H"") <>"""", INDIRECT(""B""&$C$70&"":B"") >= $A7, INDIRECT(""B""&$C$70&"":B"") <$A8))"),"$0此月開始,前月薪資扣款項目計入當月項目, $700請蓋幫買寶禮物, $233好市多續約，可參考照片-$2000寶補助隔週各項費用但記於此") -> $0此月開始,前月薪資扣款項目計入當月項目, $700請蓋幫買寶禮物, $233好市多續約，可參考照片-$2000寶補助隔週各項費用但記於此
A41: 45627 | B41: =SUMIFS(INDIRECT("C"&$C$70&":C"), INDIRECT("B"&$C$70&":B"), ">="&$A41, INDIRECT("B"&$C$70&":B"), "<"&$A42, INDIRECT("H"&$C$70&":H"), "<>") - SUM($C41:$R41) -> 28834 | C41: =SUMIFS(INDIRECT("C"&$C$70&":C"), INDIRECT("B"&$C$70&":B"), ">="&$A41, INDIRECT("B"&$C$70&":B"), "<"&$A42, INDIRECT("J"&$C$70&":J"), C$35) -> 0 | D41: =SUMIFS(INDIRECT("C"&$C$70&":C"), INDIRECT("B"&$C$70&":B"), ">="&$A41, INDIRECT("B"&$C$70&":B"), "<"&$A42, INDIRECT("N"&$C$70&":N"), D$35) -> 2771 | E41: =SUMIFS(INDIRECT("C"&$C$70&":C"), INDIRECT("B"&$C$70&":B"), ">="&$A41, INDIRECT("B"&$C$70&":B"), "<"&$A42, INDIRECT("N"&$C$70&":N"), E$35) -> 3260 | F41: =SUMIFS(INDIRECT("C"&$C$70&":C"), INDIRECT("B"&$C$70&":B"), ">="&$A41, INDIRECT("B"&$C$70&":B"), "<"&$A42, INDIRECT("K"&$C$70&":K"), "文心1房貸代繳") + SUMIFS(INDIRECT("C"&$C$70&":C"), INDIRECT("B"&$C$70&":B"), ">="&$A41, INDIRECT("B"&$C$70&":B"), "<"&$A42, INDIRECT("K"&$C$70&":K"), "租屋") -> 26000 | G41: =SUMIFS(INDIRECT("C"&$C$70&":C"), INDIRECT("B"&$C$70&":B"), ">="&$A41, INDIRECT("B"&$C$70&":B"), "<"&$A42, INDIRECT("K"&$C$70&":K"), G$35) -> 0 | H41: =SUMIFS(INDIRECT("C"&$C$70&":C"), INDIRECT("B"&$C$70&":B"), ">="&$A41, INDIRECT("B"&$C$70&":B"), "<"&$A42, INDIRECT("K"&$C$70&":K"), H$35) -> 0 | I41: =SUMIFS(INDIRECT("C"&$C$70&":C"), INDIRECT("B"&$C$70&":B"), ">="&$A41, INDIRECT("B"&$C$70&":B"), "<"&$A42, INDIRECT("K"&$C$70&":K"), I$35) -> 1196 | J41: =SUMIFS(INDIRECT("C"&$C$70&":C"), INDIRECT("B"&$C$70&":B"), ">="&$A41, INDIRECT("B"&$C$70&":B"), "<"&$A42, INDIRECT("K"&$C$70&":K"), J$35) -> 0 | K41: =SUMIFS(INDIRECT("C"&$C$70&":C"), INDIRECT("B"&$C$70&":B"), ">="&$A41, INDIRECT("B"&$C$70&":B"), "<"&$A42, INDIRECT("L"&$C$70&":L"), K$35) -> 0 | L41: =SUMIFS(INDIRECT("C"&$C$70&":C"), INDIRECT("B"&$C$70&":B"), ">="&$A41, INDIRECT("B"&$C$70&":B"), "<"&$A42, INDIRECT("L"&$C$70&":L"), L$35) -> 0 | M41: =SUMIFS(INDIRECT("C"&$C$70&":C"), INDIRECT("B"&$C$70&":B"), ">="&$A41, INDIRECT("B"&$C$70&":B"), "<"&$A42, INDIRECT("L"&$C$70&":L"), M$35) -> 704 | N41: =SUMIFS(INDIRECT("C"&$C$70&":C"), INDIRECT("B"&$C$70&":B"), ">="&$A41, INDIRECT("B"&$C$70&":B"), "<"&$A42, INDIRECT("L"&$C$70&":L"), N$35) -> 400 | O41: =SUMIFS(INDIRECT("C"&$C$70&":C"), INDIRECT("B"&$C$70&":B"), ">="&$A41, INDIRECT("B"&$C$70&":B"), "<"&$A42, INDIRECT("L"&$C$70&":L"), O$35) -> 40 | P41: =SUMIFS(INDIRECT("C"&$C$70&":C"), INDIRECT("B"&$C$70&":B"), ">="&$A41, INDIRECT("B"&$C$70&":B"), "<"&$A42, INDIRECT("L"&$C$70&":L"), P$35) -> 0 | Q41: =SUMIFS(INDIRECT("C"&$C$70&":C"), INDIRECT("B"&$C$70&":B"), ">="&$A41, INDIRECT("B"&$C$70&":B"), "<"&$A42, INDIRECT("R"&$C$70&":R"), Q$35) -> 3087 | R41: =SUMIFS(INDIRECT("C"&$C$70&":C"), INDIRECT("A"&$C$70&":A"), ">="&$A41, INDIRECT("A"&$C$70&":A"), "<"&$A42, INDIRECT("R"&$C$70&":R"), "<>公司認股", INDIRECT("R"&$C$70&":R"), "<>") -> 0 | S41: =IFERROR(__xludf.DUMMYFUNCTION("TEXTJOIN("", "", TRUE, FILTER(INDIRECT(""U""&$C$70&"":U""), INDIRECT(""H""&$C$70&"":H"") <>"""", INDIRECT(""B""&$C$70&"":B"") >= $A8, INDIRECT(""B""&$C$70&"":B"") <$A9))"),"$4358台南大員皇冠酒店, $3688除濕機hdh-12dy030B, $1171機車保險") -> $4358台南大員皇冠酒店, $3688除濕機hdh-12dy030B, $1171機車保險
A42: 45658 | B42: =SUMIFS(INDIRECT("C"&$C$70&":C"), INDIRECT("B"&$C$70&":B"), ">="&$A42, INDIRECT("B"&$C$70&":B"), "<"&$A43, INDIRECT("H"&$C$70&":H"), "<>") - SUM($C42:$R42) -> 73622 | C42: =SUMIFS(INDIRECT("C"&$C$70&":C"), INDIRECT("B"&$C$70&":B"), ">="&$A42, INDIRECT("B"&$C$70&":B"), "<"&$A43, INDIRECT("J"&$C$70&":J"), C$35) -> 698 | D42: =SUMIFS(INDIRECT("C"&$C$70&":C"), INDIRECT("B"&$C$70&":B"), ">="&$A42, INDIRECT("B"&$C$70&":B"), "<"&$A43, INDIRECT("N"&$C$70&":N"), D$35) -> 2738 | E42: =SUMIFS(INDIRECT("C"&$C$70&":C"), INDIRECT("B"&$C$70&":B"), ">="&$A42, INDIRECT("B"&$C$70&":B"), "<"&$A43, INDIRECT("N"&$C$70&":N"), E$35) -> 34163 | F42: =SUMIFS(INDIRECT("C"&$C$70&":C"), INDIRECT("B"&$C$70&":B"), ">="&$A42, INDIRECT("B"&$C$70&":B"), "<"&$A43, INDIRECT("K"&$C$70&":K"), "文心1房貸代繳") + SUMIFS(INDIRECT("C"&$C$70&":C"), INDIRECT("B"&$C$70&":B"), ">="&$A42, INDIRECT("B"&$C$70&":B"), "<"&$A43, INDIRECT("K"&$C$70&":K"), "租屋") -> 26000 | G42: =SUMIFS(INDIRECT("C"&$C$70&":C"), INDIRECT("B"&$C$70&":B"), ">="&$A42, INDIRECT("B"&$C$70&":B"), "<"&$A43, INDIRECT("K"&$C$70&":K"), G$35) -> 7802 | H42: =SUMIFS(INDIRECT("C"&$C$70&":C"), INDIRECT("B"&$C$70&":B"), ">="&$A42, INDIRECT("B"&$C$70&":B"), "<"&$A43, INDIRECT("K"&$C$70&":K"), H$35) -> 197 | I42: =SUMIFS(INDIRECT("C"&$C$70&":C"), INDIRECT("B"&$C$70&":B"), ">="&$A42, INDIRECT("B"&$C$70&":B"), "<"&$A43, INDIRECT("K"&$C$70&":K"), I$35) -> 0 | J42: =SUMIFS(INDIRECT("C"&$C$70&":C"), INDIRECT("B"&$C$70&":B"), ">="&$A42, INDIRECT("B"&$C$70&":B"), "<"&$A43, INDIRECT("K"&$C$70&":K"), J$35) -> 445 | K42: =SUMIFS(INDIRECT("C"&$C$70&":C"), INDIRECT("B"&$C$70&":B"), ">="&$A42, INDIRECT("B"&$C$70&":B"), "<"&$A43, INDIRECT("L"&$C$70&":L"), K$35) -> 28854 | L42: =SUMIFS(INDIRECT("C"&$C$70&":C"), INDIRECT("B"&$C$70&":B"), ">="&$A42, INDIRECT("B"&$C$70&":B"), "<"&$A43, INDIRECT("L"&$C$70&":L"), L$35) -> 0 | M42: =SUMIFS(INDIRECT("C"&$C$70&":C"), INDIRECT("B"&$C$70&":B"), ">="&$A42, INDIRECT("B"&$C$70&":B"), "<"&$A43, INDIRECT("L"&$C$70&":L"), M$35) -> 819 | N42: =SUMIFS(INDIRECT("C"&$C$70&":C"), INDIRECT("B"&$C$70&":B"), ">="&$A42, INDIRECT("B"&$C$70&":B"), "<"&$A43, INDIRECT("L"&$C$70&":L"), N$35) -> 0 | O42: =SUMIFS(INDIRECT("C"&$C$70&":C"), INDIRECT("B"&$C$70&":B"), ">="&$A42, INDIRECT("B"&$C$70&":B"), "<"&$A43, INDIRECT("L"&$C$70&":L"), O$35) -> 12 | P42: =SUMIFS(INDIRECT("C"&$C$70&":C"), INDIRECT("B"&$C$70&":B"), ">="&$A42, INDIRECT("B"&$C$70&":B"), "<"&$A43, INDIRECT("L"&$C$70&":L"), P$35) -> 0 | Q42: =SUMIFS(INDIRECT("C"&$C$70&":C"), INDIRECT("B"&$C$70&":B"), ">="&$A42, INDIRECT("B"&$C$70&":B"), "<"&$A43, INDIRECT("R"&$C$70&":R"), Q$35) -> 3087 | R42: =SUMIFS(INDIRECT("C"&$C$70&":C"), INDIRECT("A"&$C$70&":A"), ">="&$A42, INDIRECT("A"&$C$70&":A"), "<"&$A43, INDIRECT("R"&$C$70&":R"), "<>公司認股", INDIRECT("R"&$C$70&":R"), "<>") -> 0 | S42: =IFERROR(__xludf.DUMMYFUNCTION("TEXTJOIN("", "", TRUE, FILTER(INDIRECT(""U""&$C$70&"":U""), INDIRECT(""H""&$C$70&"":H"") <>"""", INDIRECT(""B""&$C$70&"":B"") >= $A9, INDIRECT(""B""&$C$70&"":B"") <$A10))"),"$5373澳門機票trip.com, $4000道格婚禮, $12000珠海行轉給蓋, $2999華齊堂燕窩禮盒, $13152寶紅包自己抽, $1599虎航台北-澳門機票（未搭乘，含之後退的機場稅費$500）, $6000給爸紅包") -> $5373澳門機票trip.com, $4000道格婚禮, $12000珠海行轉給蓋, $2999華齊堂燕窩禮盒, $13152寶紅包自己抽, $1599虎航台北-澳門機票（未搭乘，含之後退的機場稅費$500）, $6000給爸紅包
A43: 45689 | B43: =SUMIFS(INDIRECT("C"&$C$70&":C"), INDIRECT("B"&$C$70&":B"), ">="&$A43, INDIRECT("B"&$C$70&":B"), "<"&$A44, INDIRECT("H"&$C$70&":H"), "<>") - SUM($C43:$R43) -> 22026 | C43: =SUMIFS(INDIRECT("C"&$C$70&":C"), INDIRECT("B"&$C$70&":B"), ">="&$A43, INDIRECT("B"&$C$70&":B"), "<"&$A44, INDIRECT("J"&$C$70&":J"), C$35) -> 0 | D43: =SUMIFS(INDIRECT("C"&$C$70&":C"), INDIRECT("B"&$C$70&":B"), ">="&$A43, INDIRECT("B"&$C$70&":B"), "<"&$A44, INDIRECT("N"&$C$70&":N"), D$35) -> 2816 | E43: =SUMIFS(INDIRECT("C"&$C$70&":C"), INDIRECT("B"&$C$70&":B"), ">="&$A43, INDIRECT("B"&$C$70&":B"), "<"&$A44, INDIRECT("N"&$C$70&":N"), E$35) -> 3080 | F43: =SUMIFS(INDIRECT("C"&$C$70&":C"), INDIRECT("B"&$C$70&":B"), ">="&$A43, INDIRECT("B"&$C$70&":B"), "<"&$A44, INDIRECT("K"&$C$70&":K"), "文心1房貸代繳") + SUMIFS(INDIRECT("C"&$C$70&":C"), INDIRECT("B"&$C$70&":B"), ">="&$A43, INDIRECT("B"&$C$70&":B"), "<"&$A44, INDIRECT("K"&$C$70&":K"), "租屋") -> 26000 | G43: =SUMIFS(INDIRECT("C"&$C$70&":C"), INDIRECT("B"&$C$70&":B"), ">="&$A43, INDIRECT("B"&$C$70&":B"), "<"&$A44, INDIRECT("K"&$C$70&":K"), G$35) -> 0 | H43: =SUMIFS(INDIRECT("C"&$C$70&":C"), INDIRECT("B"&$C$70&":B"), ">="&$A43, INDIRECT("B"&$C$70&":B"), "<"&$A44, INDIRECT("K"&$C$70&":K"), H$35) -> 0 | I43: =SUMIFS(INDIRECT("C"&$C$70&":C"), INDIRECT("B"&$C$70&":B"), ">="&$A43, INDIRECT("B"&$C$70&":B"), "<"&$A44, INDIRECT("K"&$C$70&":K"), I$35) -> 1154 | J43: =SUMIFS(INDIRECT("C"&$C$70&":C"), INDIRECT("B"&$C$70&":B"), ">="&$A43, INDIRECT("B"&$C$70&":B"), "<"&$A44, INDIRECT("K"&$C$70&":K"), J$35) -> 0 | K43: =SUMIFS(INDIRECT("C"&$C$70&":C"), INDIRECT("B"&$C$70&":B"), ">="&$A43, INDIRECT("B"&$C$70&":B"), "<"&$A44, INDIRECT("L"&$C$70&":L"), K$35) -> 0 | L43: =SUMIFS(INDIRECT("C"&$C$70&":C"), INDIRECT("B"&$C$70&":B"), ">="&$A43, INDIRECT("B"&$C$70&":B"), "<"&$A44, INDIRECT("L"&$C$70&":L"), L$35) -> 0 | M43: =SUMIFS(INDIRECT("C"&$C$70&":C"), INDIRECT("B"&$C$70&":B"), ">="&$A43, INDIRECT("B"&$C$70&":B"), "<"&$A44, INDIRECT("L"&$C$70&":L"), M$35) -> 2755 | N43: =SUMIFS(INDIRECT("C"&$C$70&":C"), INDIRECT("B"&$C$70&":B"), ">="&$A43, INDIRECT("B"&$C$70&":B"), "<"&$A44, INDIRECT("L"&$C$70&":L"), N$35) -> 400 | O43: =SUMIFS(INDIRECT("C"&$C$70&":C"), INDIRECT("B"&$C$70&":B"), ">="&$A43, INDIRECT("B"&$C$70&":B"), "<"&$A44, INDIRECT("L"&$C$70&":L"), O$35) -> 285 | P43: =SUMIFS(INDIRECT("C"&$C$70&":C"), INDIRECT("B"&$C$70&":B"), ">="&$A43, INDIRECT("B"&$C$70&":B"), "<"&$A44, INDIRECT("L"&$C$70&":L"), P$35) -> 0 | Q43: =SUMIFS(INDIRECT("C"&$C$70&":C"), INDIRECT("B"&$C$70&":B"), ">="&$A43, INDIRECT("B"&$C$70&":B"), "<"&$A44, INDIRECT("R"&$C$70&":R"), Q$35) -> 3087 | R43: =SUMIFS(INDIRECT("C"&$C$70&":C"), INDIRECT("A"&$C$70&":A"), ">="&$A43, INDIRECT("A"&$C$70&":A"), "<"&$A44, INDIRECT("R"&$C$70&":R"), "<>公司認股", INDIRECT("R"&$C$70&":R"), "<>") -> 0 | S43: =IFERROR(__xludf.DUMMYFUNCTION("TEXTJOIN("", "", TRUE, FILTER(INDIRECT(""U""&$C$70&"":U""), INDIRECT(""H""&$C$70&"":H"") <>"""", INDIRECT(""B""&$C$70&"":B"") >= $A10, INDIRECT(""B""&$C$70&"":B"") <$A11))"),"")
A44: 45717 | B44: =SUMIFS(INDIRECT("C"&$C$70&":C"), INDIRECT("B"&$C$70&":B"), ">="&$A44, INDIRECT("B"&$C$70&":B"), "<"&$A45, INDIRECT("H"&$C$70&":H"), "<>") - SUM($C44:$R44) -> 66528 | C44: =SUMIFS(INDIRECT("C"&$C$70&":C"), INDIRECT("B"&$C$70&":B"), ">="&$A44, INDIRECT("B"&$C$70&":B"), "<"&$A45, INDIRECT("J"&$C$70&":J"), C$35) -> 722 | D44: =SUMIFS(INDIRECT("C"&$C$70&":C"), INDIRECT("B"&$C$70&":B"), ">="&$A44, INDIRECT("B"&$C$70&":B"), "<"&$A45, INDIRECT("N"&$C$70&":N"), D$35) -> 2816 | E44: =SUMIFS(INDIRECT("C"&$C$70&":C"), INDIRECT("B"&$C$70&":B"), ">="&$A44, INDIRECT("B"&$C$70&":B"), "<"&$A45, INDIRECT("N"&$C$70&":N"), E$35) -> 3080 | F44: =SUMIFS(INDIRECT("C"&$C$70&":C"), INDIRECT("B"&$C$70&":B"), ">="&$A44, INDIRECT("B"&$C$70&":B"), "<"&$A45, INDIRECT("K"&$C$70&":K"), "文心1房貸代繳") + SUMIFS(INDIRECT("C"&$C$70&":C"), INDIRECT("B"&$C$70&":B"), ">="&$A44, INDIRECT("B"&$C$70&":B"), "<"&$A45, INDIRECT("K"&$C$70&":K"), "租屋") -> 26000 | G44: =SUMIFS(INDIRECT("C"&$C$70&":C"), INDIRECT("B"&$C$70&":B"), ">="&$A44, INDIRECT("B"&$C$70&":B"), "<"&$A45, INDIRECT("K"&$C$70&":K"), G$35) -> 7802 | H44: =SUMIFS(INDIRECT("C"&$C$70&":C"), INDIRECT("B"&$C$70&":B"), ">="&$A44, INDIRECT("B"&$C$70&":B"), "<"&$A45, INDIRECT("K"&$C$70&":K"), H$35) -> 197 | I44: =SUMIFS(INDIRECT("C"&$C$70&":C"), INDIRECT("B"&$C$70&":B"), ">="&$A44, INDIRECT("B"&$C$70&":B"), "<"&$A45, INDIRECT("K"&$C$70&":K"), I$35) -> 0 | J44: =SUMIFS(INDIRECT("C"&$C$70&":C"), INDIRECT("B"&$C$70&":B"), ">="&$A44, INDIRECT("B"&$C$70&":B"), "<"&$A45, INDIRECT("K"&$C$70&":K"), J$35) -> 608 | K44: =SUMIFS(INDIRECT("C"&$C$70&":C"), INDIRECT("B"&$C$70&":B"), ">="&$A44, INDIRECT("B"&$C$70&":B"), "<"&$A45, INDIRECT("L"&$C$70&":L"), K$35) -> 0 | L44: =SUMIFS(INDIRECT("C"&$C$70&":C"), INDIRECT("B"&$C$70&":B"), ">="&$A44, INDIRECT("B"&$C$70&":B"), "<"&$A45, INDIRECT("L"&$C$70&":L"), L$35) -> 4162 | M44: =SUMIFS(INDIRECT("C"&$C$70&":C"), INDIRECT("B"&$C$70&":B"), ">="&$A44, INDIRECT("B"&$C$70&":B"), "<"&$A45, INDIRECT("L"&$C$70&":L"), M$35) -> 985 | N44: =SUMIFS(INDIRECT("C"&$C$70&":C"), INDIRECT("B"&$C$70&":B"), ">="&$A44, INDIRECT("B"&$C$70&":B"), "<"&$A45, INDIRECT("L"&$C$70&":L"), N$35) -> 0 | O44: =SUMIFS(INDIRECT("C"&$C$70&":C"), INDIRECT("B"&$C$70&":B"), ">="&$A44, INDIRECT("B"&$C$70&":B"), "<"&$A45, INDIRECT("L"&$C$70&":L"), O$35) -> 281 | P44: =SUMIFS(INDIRECT("C"&$C$70&":C"), INDIRECT("B"&$C$70&":B"), ">="&$A44, INDIRECT("B"&$C$70&":B"), "<"&$A45, INDIRECT("L"&$C$70&":L"), P$35) -> 100 | Q44: =SUMIFS(INDIRECT("C"&$C$70&":C"), INDIRECT("B"&$C$70&":B"), ">="&$A44, INDIRECT("B"&$C$70&":B"), "<"&$A45, INDIRECT("R"&$C$70&":R"), Q$35) -> 3087 | R44: =SUMIFS(INDIRECT("C"&$C$70&":C"), INDIRECT("A"&$C$70&":A"), ">="&$A44, INDIRECT("A"&$C$70&":A"), "<"&$A45, INDIRECT("R"&$C$70&":R"), "<>公司認股", INDIRECT("R"&$C$70&":R"), "<>") -> 0 | S44: =IFERROR(__xludf.DUMMYFUNCTION("TEXTJOIN("", "", TRUE, FILTER(INDIRECT(""U""&$C$70&"":U""), INDIRECT(""H""&$C$70&"":H"") <>"""", INDIRECT(""B""&$C$70&"":B"") >= $A11, INDIRECT(""B""&$C$70&"":B"") <$A12))"),"$49000哥洗衣機") -> $49000哥洗衣機
A45: 45748 | B45: =SUMIFS(INDIRECT("C"&$C$70&":C"), INDIRECT("B"&$C$70&":B"), ">="&$A45, INDIRECT("B"&$C$70&":B"), "<"&$A46, INDIRECT("H"&$C$70&":H"), "<>") - SUM($C45:$R45) -> 32937 | C45: =SUMIFS(INDIRECT("C"&$C$70&":C"), INDIRECT("B"&$C$70&":B"), ">="&$A45, INDIRECT("B"&$C$70&":B"), "<"&$A46, INDIRECT("J"&$C$70&":J"), C$35) -> 0 | D45: =SUMIFS(INDIRECT("C"&$C$70&":C"), INDIRECT("B"&$C$70&":B"), ">="&$A45, INDIRECT("B"&$C$70&":B"), "<"&$A46, INDIRECT("N"&$C$70&":N"), D$35) -> 2816 | E45: =SUMIFS(INDIRECT("C"&$C$70&":C"), INDIRECT("B"&$C$70&":B"), ">="&$A45, INDIRECT("B"&$C$70&":B"), "<"&$A46, INDIRECT("N"&$C$70&":N"), E$35) -> 4793 | F45: =SUMIFS(INDIRECT("C"&$C$70&":C"), INDIRECT("B"&$C$70&":B"), ">="&$A45, INDIRECT("B"&$C$70&":B"), "<"&$A46, INDIRECT("K"&$C$70&":K"), "文心1房貸代繳") + SUMIFS(INDIRECT("C"&$C$70&":C"), INDIRECT("B"&$C$70&":B"), ">="&$A45, INDIRECT("B"&$C$70&":B"), "<"&$A46, INDIRECT("K"&$C$70&":K"), "租屋") -> 26000 | G45: =SUMIFS(INDIRECT("C"&$C$70&":C"), INDIRECT("B"&$C$70&":B"), ">="&$A45, INDIRECT("B"&$C$70&":B"), "<"&$A46, INDIRECT("K"&$C$70&":K"), G$35) -> 0 | H45: =SUMIFS(INDIRECT("C"&$C$70&":C"), INDIRECT("B"&$C$70&":B"), ">="&$A45, INDIRECT("B"&$C$70&":B"), "<"&$A46, INDIRECT("K"&$C$70&":K"), H$35) -> 0 | I45: =SUMIFS(INDIRECT("C"&$C$70&":C"), INDIRECT("B"&$C$70&":B"), ">="&$A45, INDIRECT("B"&$C$70&":B"), "<"&$A46, INDIRECT("K"&$C$70&":K"), I$35) -> 1068 | J45: =SUMIFS(INDIRECT("C"&$C$70&":C"), INDIRECT("B"&$C$70&":B"), ">="&$A45, INDIRECT("B"&$C$70&":B"), "<"&$A46, INDIRECT("K"&$C$70&":K"), J$35) -> 0 | K45: =SUMIFS(INDIRECT("C"&$C$70&":C"), INDIRECT("B"&$C$70&":B"), ">="&$A45, INDIRECT("B"&$C$70&":B"), "<"&$A46, INDIRECT("L"&$C$70&":L"), K$35) -> 7120 | L45: =SUMIFS(INDIRECT("C"&$C$70&":C"), INDIRECT("B"&$C$70&":B"), ">="&$A45, INDIRECT("B"&$C$70&":B"), "<"&$A46, INDIRECT("L"&$C$70&":L"), L$35) -> 0 | M45: =SUMIFS(INDIRECT("C"&$C$70&":C"), INDIRECT("B"&$C$70&":B"), ">="&$A45, INDIRECT("B"&$C$70&":B"), "<"&$A46, INDIRECT("L"&$C$70&":L"), M$35) -> 1312 | N45: =SUMIFS(INDIRECT("C"&$C$70&":C"), INDIRECT("B"&$C$70&":B"), ">="&$A45, INDIRECT("B"&$C$70&":B"), "<"&$A46, INDIRECT("L"&$C$70&":L"), N$35) -> 0 | O45: =SUMIFS(INDIRECT("C"&$C$70&":C"), INDIRECT("B"&$C$70&":B"), ">="&$A45, INDIRECT("B"&$C$70&":B"), "<"&$A46, INDIRECT("L"&$C$70&":L"), O$35) -> 420 | P45: =SUMIFS(INDIRECT("C"&$C$70&":C"), INDIRECT("B"&$C$70&":B"), ">="&$A45, INDIRECT("B"&$C$70&":B"), "<"&$A46, INDIRECT("L"&$C$70&":L"), P$35) -> 0 | Q45: =SUMIFS(INDIRECT("C"&$C$70&":C"), INDIRECT("B"&$C$70&":B"), ">="&$A45, INDIRECT("B"&$C$70&":B"), "<"&$A46, INDIRECT("R"&$C$70&":R"), Q$35) -> 3087 | R45: =SUMIFS(INDIRECT("C"&$C$70&":C"), INDIRECT("A"&$C$70&":A"), ">="&$A45, INDIRECT("A"&$C$70&":A"), "<"&$A46, INDIRECT("R"&$C$70&":R"), "<>公司認股", INDIRECT("R"&$C$70&":R"), "<>") -> 0 | S45: =IFERROR(__xludf.DUMMYFUNCTION("TEXTJOIN("", "", TRUE, FILTER(INDIRECT(""U""&$C$70&"":U""), INDIRECT(""H""&$C$70&"":H"") <>"""", INDIRECT(""B""&$C$70&"":B"") >= $A12, INDIRECT(""B""&$C$70&"":B"") <$A13))"),"$4000牙齒膠原蛋白, $6626三鐵226k接力, $7120牌照稅, $5694泓品牛排, $2744海底撈") -> $4000牙齒膠原蛋白, $6626三鐵226k接力, $7120牌照稅, $5694泓品牛排, $2744海底撈
A46: 45778 | B46: =SUMIFS(INDIRECT("C"&$C$70&":C"), INDIRECT("B"&$C$70&":B"), ">="&$A46, INDIRECT("B"&$C$70&":B"), "<"&$A47, INDIRECT("H"&$C$70&":H"), "<>") - SUM($C46:$R46) -> 37321 | C46: =SUMIFS(INDIRECT("C"&$C$70&":C"), INDIRECT("B"&$C$70&":B"), ">="&$A46, INDIRECT("B"&$C$70&":B"), "<"&$A47, INDIRECT("J"&$C$70&":J"), C$35) -> 788 | D46: =SUMIFS(INDIRECT("C"&$C$70&":C"), INDIRECT("B"&$C$70&":B"), ">="&$A46, INDIRECT("B"&$C$70&":B"), "<"&$A47, INDIRECT("N"&$C$70&":N"), D$35) -> 2826 | E46: =SUMIFS(INDIRECT("C"&$C$70&":C"), INDIRECT("B"&$C$70&":B"), ">="&$A46, INDIRECT("B"&$C$70&":B"), "<"&$A47, INDIRECT("N"&$C$70&":N"), E$35) -> 3080 | F46: =SUMIFS(INDIRECT("C"&$C$70&":C"), INDIRECT("B"&$C$70&":B"), ">="&$A46, INDIRECT("B"&$C$70&":B"), "<"&$A47, INDIRECT("K"&$C$70&":K"), "文心1房貸代繳") + SUMIFS(INDIRECT("C"&$C$70&":C"), INDIRECT("B"&$C$70&":B"), ">="&$A46, INDIRECT("B"&$C$70&":B"), "<"&$A47, INDIRECT("K"&$C$70&":K"), "租屋") -> 26000 | G46: =SUMIFS(INDIRECT("C"&$C$70&":C"), INDIRECT("B"&$C$70&":B"), ">="&$A46, INDIRECT("B"&$C$70&":B"), "<"&$A47, INDIRECT("K"&$C$70&":K"), G$35) -> 7802 | H46: =SUMIFS(INDIRECT("C"&$C$70&":C"), INDIRECT("B"&$C$70&":B"), ">="&$A46, INDIRECT("B"&$C$70&":B"), "<"&$A47, INDIRECT("K"&$C$70&":K"), H$35) -> 220 | I46: =SUMIFS(INDIRECT("C"&$C$70&":C"), INDIRECT("B"&$C$70&":B"), ">="&$A46, INDIRECT("B"&$C$70&":B"), "<"&$A47, INDIRECT("K"&$C$70&":K"), I$35) -> 0 | J46: =SUMIFS(INDIRECT("C"&$C$70&":C"), INDIRECT("B"&$C$70&":B"), ">="&$A46, INDIRECT("B"&$C$70&":B"), "<"&$A47, INDIRECT("K"&$C$70&":K"), J$35) -> 585 | K46: =SUMIFS(INDIRECT("C"&$C$70&":C"), INDIRECT("B"&$C$70&":B"), ">="&$A46, INDIRECT("B"&$C$70&":B"), "<"&$A47, INDIRECT("L"&$C$70&":L"), K$35) -> 0 | L46: =SUMIFS(INDIRECT("C"&$C$70&":C"), INDIRECT("B"&$C$70&":B"), ">="&$A46, INDIRECT("B"&$C$70&":B"), "<"&$A47, INDIRECT("L"&$C$70&":L"), L$35) -> 0 | M46: =SUMIFS(INDIRECT("C"&$C$70&":C"), INDIRECT("B"&$C$70&":B"), ">="&$A46, INDIRECT("B"&$C$70&":B"), "<"&$A47, INDIRECT("L"&$C$70&":L"), M$35) -> 976 | N46: =SUMIFS(INDIRECT("C"&$C$70&":C"), INDIRECT("B"&$C$70&":B"), ">="&$A46, INDIRECT("B"&$C$70&":B"), "<"&$A47, INDIRECT("L"&$C$70&":L"), N$35) -> 0 | O46: =SUMIFS(INDIRECT("C"&$C$70&":C"), INDIRECT("B"&$C$70&":B"), ">="&$A46, INDIRECT("B"&$C$70&":B"), "<"&$A47, INDIRECT("L"&$C$70&":L"), O$35) -> 264 | P46: =SUMIFS(INDIRECT("C"&$C$70&":C"), INDIRECT("B"&$C$70&":B"), ">="&$A46, INDIRECT("B"&$C$70&":B"), "<"&$A47, INDIRECT("L"&$C$70&":L"), P$35) -> 0 | Q46: =SUMIFS(INDIRECT("C"&$C$70&":C"), INDIRECT("B"&$C$70&":B"), ">="&$A46, INDIRECT("B"&$C$70&":B"), "<"&$A47, INDIRECT("R"&$C$70&":R"), Q$35) -> 4116 | R46: =SUMIFS(INDIRECT("C"&$C$70&":C"), INDIRECT("A"&$C$70&":A"), ">="&$A46, INDIRECT("A"&$C$70&":A"), "<"&$A47, INDIRECT("R"&$C$70&":R"), "<>公司認股", INDIRECT("R"&$C$70&":R"), "<>") -> 0 | S46: =IFERROR(__xludf.DUMMYFUNCTION("TEXTJOIN("", "", TRUE, FILTER(INDIRECT(""U""&$C$70&"":U""), INDIRECT(""H""&$C$70&"":H"") <>"""", INDIRECT(""B""&$C$70&"":B"") >= $A13, INDIRECT(""B""&$C$70&"":B"") <$A14))"),"$30, $5800, $4328IKEA水龍頭") -> $30, $5800, $4328IKEA水龍頭
A47: 45809 | B47: =SUMIFS(INDIRECT("C"&$C$70&":C"), INDIRECT("B"&$C$70&":B"), ">="&$A47, INDIRECT("B"&$C$70&":B"), "<"&$A48, INDIRECT("H"&$C$70&":H"), "<>") - SUM($C47:$R47) -> 76482 | C47: =SUMIFS(INDIRECT("C"&$C$70&":C"), INDIRECT("B"&$C$70&":B"), ">="&$A47, INDIRECT("B"&$C$70&":B"), "<"&$A48, INDIRECT("J"&$C$70&":J"), C$35) -> 0 | D47: =SUMIFS(INDIRECT("C"&$C$70&":C"), INDIRECT("B"&$C$70&":B"), ">="&$A47, INDIRECT("B"&$C$70&":B"), "<"&$A48, INDIRECT("N"&$C$70&":N"), D$35) -> 2828 | E47: =SUMIFS(INDIRECT("C"&$C$70&":C"), INDIRECT("B"&$C$70&":B"), ">="&$A47, INDIRECT("B"&$C$70&":B"), "<"&$A48, INDIRECT("N"&$C$70&":N"), E$35) -> 3860 | F47: =SUMIFS(INDIRECT("C"&$C$70&":C"), INDIRECT("B"&$C$70&":B"), ">="&$A47, INDIRECT("B"&$C$70&":B"), "<"&$A48, INDIRECT("K"&$C$70&":K"), "文心1房貸代繳") + SUMIFS(INDIRECT("C"&$C$70&":C"), INDIRECT("B"&$C$70&":B"), ">="&$A47, INDIRECT("B"&$C$70&":B"), "<"&$A48, INDIRECT("K"&$C$70&":K"), "租屋") -> 26000 | G47: =SUMIFS(INDIRECT("C"&$C$70&":C"), INDIRECT("B"&$C$70&":B"), ">="&$A47, INDIRECT("B"&$C$70&":B"), "<"&$A48, INDIRECT("K"&$C$70&":K"), G$35) -> 0 | H47: =SUMIFS(INDIRECT("C"&$C$70&":C"), INDIRECT("B"&$C$70&":B"), ">="&$A47, INDIRECT("B"&$C$70&":B"), "<"&$A48, INDIRECT("K"&$C$70&":K"), H$35) -> 0 | I47: =SUMIFS(INDIRECT("C"&$C$70&":C"), INDIRECT("B"&$C$70&":B"), ">="&$A47, INDIRECT("B"&$C$70&":B"), "<"&$A48, INDIRECT("K"&$C$70&":K"), I$35) -> 1303 | J47: =SUMIFS(INDIRECT("C"&$C$70&":C"), INDIRECT("B"&$C$70&":B"), ">="&$A47, INDIRECT("B"&$C$70&":B"), "<"&$A48, INDIRECT("K"&$C$70&":K"), J$35) -> 0 | K47: =SUMIFS(INDIRECT("C"&$C$70&":C"), INDIRECT("B"&$C$70&":B"), ">="&$A47, INDIRECT("B"&$C$70&":B"), "<"&$A48, INDIRECT("L"&$C$70&":L"), K$35) -> 0 | L47: =SUMIFS(INDIRECT("C"&$C$70&":C"), INDIRECT("B"&$C$70&":B"), ">="&$A47, INDIRECT("B"&$C$70&":B"), "<"&$A48, INDIRECT("L"&$C$70&":L"), L$35) -> 0 | M47: =SUMIFS(INDIRECT("C"&$C$70&":C"), INDIRECT("B"&$C$70&":B"), ">="&$A47, INDIRECT("B"&$C$70&":B"), "<"&$A48, INDIRECT("L"&$C$70&":L"), M$35) -> 2100 | N47: =SUMIFS(INDIRECT("C"&$C$70&":C"), INDIRECT("B"&$C$70&":B"), ">="&$A47, INDIRECT("B"&$C$70&":B"), "<"&$A48, INDIRECT("L"&$C$70&":L"), N$35) -> 400 | O47: =SUMIFS(INDIRECT("C"&$C$70&":C"), INDIRECT("B"&$C$70&":B"), ">="&$A47, INDIRECT("B"&$C$70&":B"), "<"&$A48, INDIRECT("L"&$C$70&":L"), O$35) -> 340 | P47: =SUMIFS(INDIRECT("C"&$C$70&":C"), INDIRECT("B"&$C$70&":B"), ">="&$A47, INDIRECT("B"&$C$70&":B"), "<"&$A48, INDIRECT("L"&$C$70&":L"), P$35) -> 0 | Q47: =SUMIFS(INDIRECT("C"&$C$70&":C"), INDIRECT("B"&$C$70&":B"), ">="&$A47, INDIRECT("B"&$C$70&":B"), "<"&$A48, INDIRECT("R"&$C$70&":R"), Q$35) -> 4292 | R47: =SUMIFS(INDIRECT("C"&$C$70&":C"), INDIRECT("A"&$C$70&":A"), ">="&$A47, INDIRECT("A"&$C$70&":A"), "<"&$A48, INDIRECT("R"&$C$70&":R"), "<>公司認股", INDIRECT("R"&$C$70&":R"), "<>") -> 0 | S47: =IFERROR(__xludf.DUMMYFUNCTION("TEXTJOIN("", "", TRUE, FILTER(INDIRECT(""U""&$C$70&"":U""), INDIRECT(""H""&$C$70&"":H"") <>"""", INDIRECT(""B""&$C$70&"":B"") >= $A14, INDIRECT(""B""&$C$70&"":B"") <$A15))"),"$20000哥生小孩紅包, $5000根管治療, $1500機車清油管, $15000長庚體檢, $6900H2O豪華景觀客房, $8052豪享自助餐*6人") -> $20000哥生小孩紅包, $5000根管治療, $1500機車清油管, $15000長庚體檢, $6900H2O豪華景觀客房, $8052豪享自助餐*6人
A48: 45839 | B48: =SUMIFS(INDIRECT("C"&$C$70&":C"), INDIRECT("B"&$C$70&":B"), ">="&$A48, INDIRECT("B"&$C$70&":B"), "<"&$A49, INDIRECT("H"&$C$70&":H"), "<>") - SUM($C48:$R48) -> 137494 | C48: =SUMIFS(INDIRECT("C"&$C$70&":C"), INDIRECT("B"&$C$70&":B"), ">="&$A48, INDIRECT("B"&$C$70&":B"), "<"&$A49, INDIRECT("J"&$C$70&":J"), C$35) -> 728 | D48: =SUMIFS(INDIRECT("C"&$C$70&":C"), INDIRECT("B"&$C$70&":B"), ">="&$A48, INDIRECT("B"&$C$70&":B"), "<"&$A49, INDIRECT("N"&$C$70&":N"), D$35) -> 2828 | E48: =SUMIFS(INDIRECT("C"&$C$70&":C"), INDIRECT("B"&$C$70&":B"), ">="&$A48, INDIRECT("B"&$C$70&":B"), "<"&$A49, INDIRECT("N"&$C$70&":N"), E$35) -> 11041 | F48: =SUMIFS(INDIRECT("C"&$C$70&":C"), INDIRECT("B"&$C$70&":B"), ">="&$A48, INDIRECT("B"&$C$70&":B"), "<"&$A49, INDIRECT("K"&$C$70&":K"), "文心1房貸代繳") + SUMIFS(INDIRECT("C"&$C$70&":C"), INDIRECT("B"&$C$70&":B"), ">="&$A48, INDIRECT("B"&$C$70&":B"), "<"&$A49, INDIRECT("K"&$C$70&":K"), "租屋") -> 26000 | G48: =SUMIFS(INDIRECT("C"&$C$70&":C"), INDIRECT("B"&$C$70&":B"), ">="&$A48, INDIRECT("B"&$C$70&":B"), "<"&$A49, INDIRECT("K"&$C$70&":K"), G$35) -> 7802 | H48: =SUMIFS(INDIRECT("C"&$C$70&":C"), INDIRECT("B"&$C$70&":B"), ">="&$A48, INDIRECT("B"&$C$70&":B"), "<"&$A49, INDIRECT("K"&$C$70&":K"), H$35) -> 197 | I48: =SUMIFS(INDIRECT("C"&$C$70&":C"), INDIRECT("B"&$C$70&":B"), ">="&$A48, INDIRECT("B"&$C$70&":B"), "<"&$A49, INDIRECT("K"&$C$70&":K"), I$35) -> 0 | J48: =SUMIFS(INDIRECT("C"&$C$70&":C"), INDIRECT("B"&$C$70&":B"), ">="&$A48, INDIRECT("B"&$C$70&":B"), "<"&$A49, INDIRECT("K"&$C$70&":K"), J$35) -> 422 | K48: =SUMIFS(INDIRECT("C"&$C$70&":C"), INDIRECT("B"&$C$70&":B"), ">="&$A48, INDIRECT("B"&$C$70&":B"), "<"&$A49, INDIRECT("L"&$C$70&":L"), K$35) -> 5250 | L48: =SUMIFS(INDIRECT("C"&$C$70&":C"), INDIRECT("B"&$C$70&":B"), ">="&$A48, INDIRECT("B"&$C$70&":B"), "<"&$A49, INDIRECT("L"&$C$70&":L"), L$35) -> 0 | M48: =SUMIFS(INDIRECT("C"&$C$70&":C"), INDIRECT("B"&$C$70&":B"), ">="&$A48, INDIRECT("B"&$C$70&":B"), "<"&$A49, INDIRECT("L"&$C$70&":L"), M$35) -> 1055 | N48: =SUMIFS(INDIRECT("C"&$C$70&":C"), INDIRECT("B"&$C$70&":B"), ">="&$A48, INDIRECT("B"&$C$70&":B"), "<"&$A49, INDIRECT("L"&$C$70&":L"), N$35) -> 0 | O48: =SUMIFS(INDIRECT("C"&$C$70&":C"), INDIRECT("B"&$C$70&":B"), ">="&$A48, INDIRECT("B"&$C$70&":B"), "<"&$A49, INDIRECT("L"&$C$70&":L"), O$35) -> 594 | P48: =SUMIFS(INDIRECT("C"&$C$70&":C"), INDIRECT("B"&$C$70&":B"), ">="&$A48, INDIRECT("B"&$C$70&":B"), "<"&$A49, INDIRECT("L"&$C$70&":L"), P$35) -> 0 | Q48: =SUMIFS(INDIRECT("C"&$C$70&":C"), INDIRECT("B"&$C$70&":B"), ">="&$A48, INDIRECT("B"&$C$70&":B"), "<"&$A49, INDIRECT("R"&$C$70&":R"), Q$35) -> 4292 | R48: =SUMIFS(INDIRECT("C"&$C$70&":C"), INDIRECT("A"&$C$70&":A"), ">="&$A48, INDIRECT("A"&$C$70&":A"), "<"&$A49, INDIRECT("R"&$C$70&":R"), "<>公司認股", INDIRECT("R"&$C$70&":R"), "<>") -> 0 | S48: =IFERROR(__xludf.DUMMYFUNCTION("TEXTJOIN("", "", TRUE, FILTER(INDIRECT(""U""&$C$70&"":U""), INDIRECT(""H""&$C$70&"":H"") <>"""", INDIRECT(""B""&$C$70&"":B"") >= $A15, INDIRECT(""B""&$C$70&"":B"") <$A16))"),"$5000根管治療, $5000根管治療, $4800汽車燃料費, $2163拼多多廚房櫃, $103622婚戒") -> $5000根管治療, $5000根管治療, $4800汽車燃料費, $2163拼多多廚房櫃, $103622婚戒
A49: 45870 | B49: =SUMIFS(INDIRECT("C"&$C$70&":C"), INDIRECT("B"&$C$70&":B"), ">="&$A49, INDIRECT("B"&$C$70&":B"), "<"&$A50, INDIRECT("H"&$C$70&":H"), "<>") - SUM($C49:$R49) -> 21493 | C49: =SUMIFS(INDIRECT("C"&$C$70&":C"), INDIRECT("B"&$C$70&":B"), ">="&$A49, INDIRECT("B"&$C$70&":B"), "<"&$A50, INDIRECT("J"&$C$70&":J"), C$35) -> 0 | D49: =SUMIFS(INDIRECT("C"&$C$70&":C"), INDIRECT("B"&$C$70&":B"), ">="&$A49, INDIRECT("B"&$C$70&":B"), "<"&$A50, INDIRECT("N"&$C$70&":N"), D$35) -> 2828 | E49: =SUMIFS(INDIRECT("C"&$C$70&":C"), INDIRECT("B"&$C$70&":B"), ">="&$A49, INDIRECT("B"&$C$70&":B"), "<"&$A50, INDIRECT("N"&$C$70&":N"), E$35) -> 4400 | F49: =SUMIFS(INDIRECT("C"&$C$70&":C"), INDIRECT("B"&$C$70&":B"), ">="&$A49, INDIRECT("B"&$C$70&":B"), "<"&$A50, INDIRECT("K"&$C$70&":K"), "文心1房貸代繳") + SUMIFS(INDIRECT("C"&$C$70&":C"), INDIRECT("B"&$C$70&":B"), ">="&$A49, INDIRECT("B"&$C$70&":B"), "<"&$A50, INDIRECT("K"&$C$70&":K"), "租屋") -> 26000 | G49: =SUMIFS(INDIRECT("C"&$C$70&":C"), INDIRECT("B"&$C$70&":B"), ">="&$A49, INDIRECT("B"&$C$70&":B"), "<"&$A50, INDIRECT("K"&$C$70&":K"), G$35) -> 0 | H49: =SUMIFS(INDIRECT("C"&$C$70&":C"), INDIRECT("B"&$C$70&":B"), ">="&$A49, INDIRECT("B"&$C$70&":B"), "<"&$A50, INDIRECT("K"&$C$70&":K"), H$35) -> 0 | I49: =SUMIFS(INDIRECT("C"&$C$70&":C"), INDIRECT("B"&$C$70&":B"), ">="&$A49, INDIRECT("B"&$C$70&":B"), "<"&$A50, INDIRECT("K"&$C$70&":K"), I$35) -> 1701 | J49: =SUMIFS(INDIRECT("C"&$C$70&":C"), INDIRECT("B"&$C$70&":B"), ">="&$A49, INDIRECT("B"&$C$70&":B"), "<"&$A50, INDIRECT("K"&$C$70&":K"), J$35) -> 0 | K49: =SUMIFS(INDIRECT("C"&$C$70&":C"), INDIRECT("B"&$C$70&":B"), ">="&$A49, INDIRECT("B"&$C$70&":B"), "<"&$A50, INDIRECT("L"&$C$70&":L"), K$35) -> 0 | L49: =SUMIFS(INDIRECT("C"&$C$70&":C"), INDIRECT("B"&$C$70&":B"), ">="&$A49, INDIRECT("B"&$C$70&":B"), "<"&$A50, INDIRECT("L"&$C$70&":L"), L$35) -> 0 | M49: =SUMIFS(INDIRECT("C"&$C$70&":C"), INDIRECT("B"&$C$70&":B"), ">="&$A49, INDIRECT("B"&$C$70&":B"), "<"&$A50, INDIRECT("L"&$C$70&":L"), M$35) -> 2613 | N49: =SUMIFS(INDIRECT("C"&$C$70&":C"), INDIRECT("B"&$C$70&":B"), ">="&$A49, INDIRECT("B"&$C$70&":B"), "<"&$A50, INDIRECT("L"&$C$70&":L"), N$35) -> 400 | O49: =SUMIFS(INDIRECT("C"&$C$70&":C"), INDIRECT("B"&$C$70&":B"), ">="&$A49, INDIRECT("B"&$C$70&":B"), "<"&$A50, INDIRECT("L"&$C$70&":L"), O$35) -> 376 | P49: =SUMIFS(INDIRECT("C"&$C$70&":C"), INDIRECT("B"&$C$70&":B"), ">="&$A49, INDIRECT("B"&$C$70&":B"), "<"&$A50, INDIRECT("L"&$C$70&":L"), P$35) -> 600 | Q49: =SUMIFS(INDIRECT("C"&$C$70&":C"), INDIRECT("B"&$C$70&":B"), ">="&$A49, INDIRECT("B"&$C$70&":B"), "<"&$A50, INDIRECT("R"&$C$70&":R"), Q$35) -> 4292 | R49: =SUMIFS(INDIRECT("C"&$C$70&":C"), INDIRECT("A"&$C$70&":A"), ">="&$A49, INDIRECT("A"&$C$70&":A"), "<"&$A50, INDIRECT("R"&$C$70&":R"), "<>公司認股", INDIRECT("R"&$C$70&":R"), "<>") -> 0 | S49: =IFERROR(__xludf.DUMMYFUNCTION("TEXTJOIN("", "", TRUE, FILTER(INDIRECT(""U""&$C$70&"":U""), INDIRECT(""H""&$C$70&"":H"") <>"""", INDIRECT(""B""&$C$70&"":B"") >= $A16, INDIRECT(""B""&$C$70&"":B"") <$A17))"),"$5000根管治療") -> $5000根管治療
A50: 45901 | B50: =SUMIFS(INDIRECT("C"&$C$70&":C"), INDIRECT("B"&$C$70&":B"), ">="&$A50, INDIRECT("B"&$C$70&":B"), "<"&$A51, INDIRECT("H"&$C$70&":H"), "<>") - SUM($C50:$R50) -> 27123 | C50: =SUMIFS(INDIRECT("C"&$C$70&":C"), INDIRECT("B"&$C$70&":B"), ">="&$A50, INDIRECT("B"&$C$70&":B"), "<"&$A51, INDIRECT("J"&$C$70&":J"), C$35) -> 698 | D50: =SUMIFS(INDIRECT("C"&$C$70&":C"), INDIRECT("B"&$C$70&":B"), ">="&$A50, INDIRECT("B"&$C$70&":B"), "<"&$A51, INDIRECT("N"&$C$70&":N"), D$35) -> 2828 | E50: =SUMIFS(INDIRECT("C"&$C$70&":C"), INDIRECT("B"&$C$70&":B"), ">="&$A50, INDIRECT("B"&$C$70&":B"), "<"&$A51, INDIRECT("N"&$C$70&":N"), E$35) -> 3860 | F50: =SUMIFS(INDIRECT("C"&$C$70&":C"), INDIRECT("B"&$C$70&":B"), ">="&$A50, INDIRECT("B"&$C$70&":B"), "<"&$A51, INDIRECT("K"&$C$70&":K"), "文心1房貸代繳") + SUMIFS(INDIRECT("C"&$C$70&":C"), INDIRECT("B"&$C$70&":B"), ">="&$A50, INDIRECT("B"&$C$70&":B"), "<"&$A51, INDIRECT("K"&$C$70&":K"), "租屋") -> 26000 | G50: =SUMIFS(INDIRECT("C"&$C$70&":C"), INDIRECT("B"&$C$70&":B"), ">="&$A50, INDIRECT("B"&$C$70&":B"), "<"&$A51, INDIRECT("K"&$C$70&":K"), G$35) -> 7802 | H50: =SUMIFS(INDIRECT("C"&$C$70&":C"), INDIRECT("B"&$C$70&":B"), ">="&$A50, INDIRECT("B"&$C$70&":B"), "<"&$A51, INDIRECT("K"&$C$70&":K"), H$35) -> 205 | I50: =SUMIFS(INDIRECT("C"&$C$70&":C"), INDIRECT("B"&$C$70&":B"), ">="&$A50, INDIRECT("B"&$C$70&":B"), "<"&$A51, INDIRECT("K"&$C$70&":K"), I$35) -> 0 | J50: =SUMIFS(INDIRECT("C"&$C$70&":C"), INDIRECT("B"&$C$70&":B"), ">="&$A50, INDIRECT("B"&$C$70&":B"), "<"&$A51, INDIRECT("K"&$C$70&":K"), J$35) -> 433 | K50: =SUMIFS(INDIRECT("C"&$C$70&":C"), INDIRECT("B"&$C$70&":B"), ">="&$A50, INDIRECT("B"&$C$70&":B"), "<"&$A51, INDIRECT("L"&$C$70&":L"), K$35) -> 0 | L50: =SUMIFS(INDIRECT("C"&$C$70&":C"), INDIRECT("B"&$C$70&":B"), ">="&$A50, INDIRECT("B"&$C$70&":B"), "<"&$A51, INDIRECT("L"&$C$70&":L"), L$35) -> 0 | M50: =SUMIFS(INDIRECT("C"&$C$70&":C"), INDIRECT("B"&$C$70&":B"), ">="&$A50, INDIRECT("B"&$C$70&":B"), "<"&$A51, INDIRECT("L"&$C$70&":L"), M$35) -> 2268 | N50: =SUMIFS(INDIRECT("C"&$C$70&":C"), INDIRECT("B"&$C$70&":B"), ">="&$A50, INDIRECT("B"&$C$70&":B"), "<"&$A51, INDIRECT("L"&$C$70&":L"), N$35) -> 400 | O50: =SUMIFS(INDIRECT("C"&$C$70&":C"), INDIRECT("B"&$C$70&":B"), ">="&$A50, INDIRECT("B"&$C$70&":B"), "<"&$A51, INDIRECT("L"&$C$70&":L"), O$35) -> 299 | P50: =SUMIFS(INDIRECT("C"&$C$70&":C"), INDIRECT("B"&$C$70&":B"), ">="&$A50, INDIRECT("B"&$C$70&":B"), "<"&$A51, INDIRECT("L"&$C$70&":L"), P$35) -> 0 | Q50: =SUMIFS(INDIRECT("C"&$C$70&":C"), INDIRECT("B"&$C$70&":B"), ">="&$A50, INDIRECT("B"&$C$70&":B"), "<"&$A51, INDIRECT("R"&$C$70&":R"), Q$35) -> 4292 | R50: =SUMIFS(INDIRECT("C"&$C$70&":C"), INDIRECT("A"&$C$70&":A"), ">="&$A50, INDIRECT("A"&$C$70&":A"), "<"&$A51, INDIRECT("R"&$C$70&":R"), "<>公司認股", INDIRECT("R"&$C$70&":R"), "<>") -> 0 | S50: =IFERROR(__xludf.DUMMYFUNCTION("TEXTJOIN("", "", TRUE, FILTER(INDIRECT(""U""&$C$70&"":U""), INDIRECT(""H""&$C$70&"":H"") <>"""", INDIRECT(""B""&$C$70&"":B"") >= $A17, INDIRECT(""B""&$C$70&"":B"") <$A18))"),"$1800點痣") -> $1800點痣
A51: 45931 | B51: =SUMIFS(INDIRECT("C"&$C$70&":C"), INDIRECT("B"&$C$70&":B"), ">="&$A51, INDIRECT("B"&$C$70&":B"), "<"&$A52, INDIRECT("H"&$C$70&":H"), "<>") - SUM($C51:$R51) -> 78516 | C51: =SUMIFS(INDIRECT("C"&$C$70&":C"), INDIRECT("B"&$C$70&":B"), ">="&$A51, INDIRECT("B"&$C$70&":B"), "<"&$A52, INDIRECT("J"&$C$70&":J"), C$35) -> 0 | D51: =SUMIFS(INDIRECT("C"&$C$70&":C"), INDIRECT("B"&$C$70&":B"), ">="&$A51, INDIRECT("B"&$C$70&":B"), "<"&$A52, INDIRECT("N"&$C$70&":N"), D$35) -> 2898 | E51: =SUMIFS(INDIRECT("C"&$C$70&":C"), INDIRECT("B"&$C$70&":B"), ">="&$A51, INDIRECT("B"&$C$70&":B"), "<"&$A52, INDIRECT("N"&$C$70&":N"), E$35) -> 3620 | F51: =SUMIFS(INDIRECT("C"&$C$70&":C"), INDIRECT("B"&$C$70&":B"), ">="&$A51, INDIRECT("B"&$C$70&":B"), "<"&$A52, INDIRECT("K"&$C$70&":K"), "文心1房貸代繳") + SUMIFS(INDIRECT("C"&$C$70&":C"), INDIRECT("B"&$C$70&":B"), ">="&$A51, INDIRECT("B"&$C$70&":B"), "<"&$A52, INDIRECT("K"&$C$70&":K"), "租屋") -> 26000 | G51: =SUMIFS(INDIRECT("C"&$C$70&":C"), INDIRECT("B"&$C$70&":B"), ">="&$A51, INDIRECT("B"&$C$70&":B"), "<"&$A52, INDIRECT("K"&$C$70&":K"), G$35) -> 0 | H51: =SUMIFS(INDIRECT("C"&$C$70&":C"), INDIRECT("B"&$C$70&":B"), ">="&$A51, INDIRECT("B"&$C$70&":B"), "<"&$A52, INDIRECT("K"&$C$70&":K"), H$35) -> 0 | I51: =SUMIFS(INDIRECT("C"&$C$70&":C"), INDIRECT("B"&$C$70&":B"), ">="&$A51, INDIRECT("B"&$C$70&":B"), "<"&$A52, INDIRECT("K"&$C$70&":K"), I$35) -> 1746 | J51: =SUMIFS(INDIRECT("C"&$C$70&":C"), INDIRECT("B"&$C$70&":B"), ">="&$A51, INDIRECT("B"&$C$70&":B"), "<"&$A52, INDIRECT("K"&$C$70&":K"), J$35) -> 0 | K51: =SUMIFS(INDIRECT("C"&$C$70&":C"), INDIRECT("B"&$C$70&":B"), ">="&$A51, INDIRECT("B"&$C$70&":B"), "<"&$A52, INDIRECT("L"&$C$70&":L"), K$35) -> 0 | L51: =SUMIFS(INDIRECT("C"&$C$70&":C"), INDIRECT("B"&$C$70&":B"), ">="&$A51, INDIRECT("B"&$C$70&":B"), "<"&$A52, INDIRECT("L"&$C$70&":L"), L$35) -> 0 | M51: =SUMIFS(INDIRECT("C"&$C$70&":C"), INDIRECT("B"&$C$70&":B"), ">="&$A51, INDIRECT("B"&$C$70&":B"), "<"&$A52, INDIRECT("L"&$C$70&":L"), M$35) -> 219 | N51: =SUMIFS(INDIRECT("C"&$C$70&":C"), INDIRECT("B"&$C$70&":B"), ">="&$A51, INDIRECT("B"&$C$70&":B"), "<"&$A52, INDIRECT("L"&$C$70&":L"), N$35) -> 0 | O51: =SUMIFS(INDIRECT("C"&$C$70&":C"), INDIRECT("B"&$C$70&":B"), ">="&$A51, INDIRECT("B"&$C$70&":B"), "<"&$A52, INDIRECT("L"&$C$70&":L"), O$35) -> 95 | P51: =SUMIFS(INDIRECT("C"&$C$70&":C"), INDIRECT("B"&$C$70&":B"), ">="&$A51, INDIRECT("B"&$C$70&":B"), "<"&$A52, INDIRECT("L"&$C$70&":L"), P$35) -> 0 | Q51: =SUMIFS(INDIRECT("C"&$C$70&":C"), INDIRECT("B"&$C$70&":B"), ">="&$A51, INDIRECT("B"&$C$70&":B"), "<"&$A52, INDIRECT("R"&$C$70&":R"), Q$35) -> 4292 | R51: =SUMIFS(INDIRECT("C"&$C$70&":C"), INDIRECT("A"&$C$70&":A"), ">="&$A51, INDIRECT("A"&$C$70&":A"), "<"&$A52, INDIRECT("R"&$C$70&":R"), "<>公司認股", INDIRECT("R"&$C$70&":R"), "<>") -> 0 | S51: =IFERROR(__xludf.DUMMYFUNCTION("TEXTJOIN("", "", TRUE, FILTER(INDIRECT(""U""&$C$70&"":U""), INDIRECT(""H""&$C$70&"":H"") <>"""", INDIRECT(""B""&$C$70&"":B"") >= $A18, INDIRECT(""B""&$C$70&"":B"") <$A19))"),"$6000贊助寶學畫畫, $48900冰箱") -> $6000贊助寶學畫畫, $48900冰箱
A52: 45962 | B52: =SUMIFS(INDIRECT("C"&$C$70&":C"), INDIRECT("B"&$C$70&":B"), ">="&$A52, INDIRECT("B"&$C$70&":B"), "<"&$A53, INDIRECT("H"&$C$70&":H"), "<>") - SUM($C52:$R52) -> 101959 | C52: =SUMIFS(INDIRECT("C"&$C$70&":C"), INDIRECT("B"&$C$70&":B"), ">="&$A52, INDIRECT("B"&$C$70&":B"), "<"&$A53, INDIRECT("J"&$C$70&":J"), C$35) -> 794 | D52: =SUMIFS(INDIRECT("C"&$C$70&":C"), INDIRECT("B"&$C$70&":B"), ">="&$A52, INDIRECT("B"&$C$70&":B"), "<"&$A53, INDIRECT("N"&$C$70&":N"), D$35) -> 6201 | E52: =SUMIFS(INDIRECT("C"&$C$70&":C"), INDIRECT("B"&$C$70&":B"), ">="&$A52, INDIRECT("B"&$C$70&":B"), "<"&$A53, INDIRECT("N"&$C$70&":N"), E$35) -> 3500 | F52: =SUMIFS(INDIRECT("C"&$C$70&":C"), INDIRECT("B"&$C$70&":B"), ">="&$A52, INDIRECT("B"&$C$70&":B"), "<"&$A53, INDIRECT("K"&$C$70&":K"), "文心1房貸代繳") + SUMIFS(INDIRECT("C"&$C$70&":C"), INDIRECT("B"&$C$70&":B"), ">="&$A52, INDIRECT("B"&$C$70&":B"), "<"&$A53, INDIRECT("K"&$C$70&":K"), "租屋") -> 26000 | G52: =SUMIFS(INDIRECT("C"&$C$70&":C"), INDIRECT("B"&$C$70&":B"), ">="&$A52, INDIRECT("B"&$C$70&":B"), "<"&$A53, INDIRECT("K"&$C$70&":K"), G$35) -> 7302 | H52: =SUMIFS(INDIRECT("C"&$C$70&":C"), INDIRECT("B"&$C$70&":B"), ">="&$A52, INDIRECT("B"&$C$70&":B"), "<"&$A53, INDIRECT("K"&$C$70&":K"), H$35) -> 213 | I52: =SUMIFS(INDIRECT("C"&$C$70&":C"), INDIRECT("B"&$C$70&":B"), ">="&$A52, INDIRECT("B"&$C$70&":B"), "<"&$A53, INDIRECT("K"&$C$70&":K"), I$35) -> 0 | J52: =SUMIFS(INDIRECT("C"&$C$70&":C"), INDIRECT("B"&$C$70&":B"), ">="&$A52, INDIRECT("B"&$C$70&":B"), "<"&$A53, INDIRECT("K"&$C$70&":K"), J$35) -> 433 | K52: =SUMIFS(INDIRECT("C"&$C$70&":C"), INDIRECT("B"&$C$70&":B"), ">="&$A52, INDIRECT("B"&$C$70&":B"), "<"&$A53, INDIRECT("L"&$C$70&":L"), K$35) -> 0 | L52: =SUMIFS(INDIRECT("C"&$C$70&":C"), INDIRECT("B"&$C$70&":B"), ">="&$A52, INDIRECT("B"&$C$70&":B"), "<"&$A53, INDIRECT("L"&$C$70&":L"), L$35) -> 0 | M52: =SUMIFS(INDIRECT("C"&$C$70&":C"), INDIRECT("B"&$C$70&":B"), ">="&$A52, INDIRECT("B"&$C$70&":B"), "<"&$A53, INDIRECT("L"&$C$70&":L"), M$35) -> 1714 | N52: =SUMIFS(INDIRECT("C"&$C$70&":C"), INDIRECT("B"&$C$70&":B"), ">="&$A52, INDIRECT("B"&$C$70&":B"), "<"&$A53, INDIRECT("L"&$C$70&":L"), N$35) -> 0 | O52: =SUMIFS(INDIRECT("C"&$C$70&":C"), INDIRECT("B"&$C$70&":B"), ">="&$A52, INDIRECT("B"&$C$70&":B"), "<"&$A53, INDIRECT("L"&$C$70&":L"), O$35) -> 95 | P52: =SUMIFS(INDIRECT("C"&$C$70&":C"), INDIRECT("B"&$C$70&":B"), ">="&$A52, INDIRECT("B"&$C$70&":B"), "<"&$A53, INDIRECT("L"&$C$70&":L"), P$35) -> 180 | Q52: =SUMIFS(INDIRECT("C"&$C$70&":C"), INDIRECT("B"&$C$70&":B"), ">="&$A52, INDIRECT("B"&$C$70&":B"), "<"&$A53, INDIRECT("R"&$C$70&":R"), Q$35) -> 4292 | R52: =SUMIFS(INDIRECT("C"&$C$70&":C"), INDIRECT("A"&$C$70&":A"), ">="&$A52, INDIRECT("A"&$C$70&":A"), "<"&$A53, INDIRECT("R"&$C$70&":R"), "<>公司認股", INDIRECT("R"&$C$70&":R"), "<>") -> 0 | S52: =IFERROR(__xludf.DUMMYFUNCTION("TEXTJOIN("", "", TRUE, FILTER(INDIRECT(""U""&$C$70&"":U""), INDIRECT(""H""&$C$70&"":H"") <>"""", INDIRECT(""B""&$C$70&"":B"") >= $A19, INDIRECT(""B""&$C$70&"":B"") <$A20))"),"$58492日本大阪行, $5900濾芯, $8400速達通網路, $14900除濕機") -> $58492日本大阪行, $5900濾芯, $8400速達通網路, $14900除濕機
A53: 45992 | B53: =SUMIFS(INDIRECT("C"&$C$70&":C"), INDIRECT("B"&$C$70&":B"), ">="&$A53, INDIRECT("B"&$C$70&":B"), "<"&$A54, INDIRECT("H"&$C$70&":H"), "<>") - SUM($C53:$R53) -> 35895 | C53: =SUMIFS(INDIRECT("C"&$C$70&":C"), INDIRECT("B"&$C$70&":B"), ">="&$A53, INDIRECT("B"&$C$70&":B"), "<"&$A54, INDIRECT("J"&$C$70&":J"), C$35) -> 0 | D53: =SUMIFS(INDIRECT("C"&$C$70&":C"), INDIRECT("B"&$C$70&":B"), ">="&$A53, INDIRECT("B"&$C$70&":B"), "<"&$A54, INDIRECT("N"&$C$70&":N"), D$35) -> 6729 | E53: =SUMIFS(INDIRECT("C"&$C$70&":C"), INDIRECT("B"&$C$70&":B"), ">="&$A53, INDIRECT("B"&$C$70&":B"), "<"&$A54, INDIRECT("N"&$C$70&":N"), E$35) -> 3500 | F53: =SUMIFS(INDIRECT("C"&$C$70&":C"), INDIRECT("B"&$C$70&":B"), ">="&$A53, INDIRECT("B"&$C$70&":B"), "<"&$A54, INDIRECT("K"&$C$70&":K"), "文心1房貸代繳") + SUMIFS(INDIRECT("C"&$C$70&":C"), INDIRECT("B"&$C$70&":B"), ">="&$A53, INDIRECT("B"&$C$70&":B"), "<"&$A54, INDIRECT("K"&$C$70&":K"), "租屋") -> 26000 | G53: =SUMIFS(INDIRECT("C"&$C$70&":C"), INDIRECT("B"&$C$70&":B"), ">="&$A53, INDIRECT("B"&$C$70&":B"), "<"&$A54, INDIRECT("K"&$C$70&":K"), G$35) -> 0 | H53: =SUMIFS(INDIRECT("C"&$C$70&":C"), INDIRECT("B"&$C$70&":B"), ">="&$A53, INDIRECT("B"&$C$70&":B"), "<"&$A54, INDIRECT("K"&$C$70&":K"), H$35) -> 0 | I53: =SUMIFS(INDIRECT("C"&$C$70&":C"), INDIRECT("B"&$C$70&":B"), ">="&$A53, INDIRECT("B"&$C$70&":B"), "<"&$A54, INDIRECT("K"&$C$70&":K"), I$35) -> 1102 | J53: =SUMIFS(INDIRECT("C"&$C$70&":C"), INDIRECT("B"&$C$70&":B"), ">="&$A53, INDIRECT("B"&$C$70&":B"), "<"&$A54, INDIRECT("K"&$C$70&":K"), J$35) -> 0 | K53: =SUMIFS(INDIRECT("C"&$C$70&":C"), INDIRECT("B"&$C$70&":B"), ">="&$A53, INDIRECT("B"&$C$70&":B"), "<"&$A54, INDIRECT("L"&$C$70&":L"), K$35) -> 0 | L53: =SUMIFS(INDIRECT("C"&$C$70&":C"), INDIRECT("B"&$C$70&":B"), ">="&$A53, INDIRECT("B"&$C$70&":B"), "<"&$A54, INDIRECT("L"&$C$70&":L"), L$35) -> 0 | M53: =SUMIFS(INDIRECT("C"&$C$70&":C"), INDIRECT("B"&$C$70&":B"), ">="&$A53, INDIRECT("B"&$C$70&":B"), "<"&$A54, INDIRECT("L"&$C$70&":L"), M$35) -> 3090 | N53: =SUMIFS(INDIRECT("C"&$C$70&":C"), INDIRECT("B"&$C$70&":B"), ">="&$A53, INDIRECT("B"&$C$70&":B"), "<"&$A54, INDIRECT("L"&$C$70&":L"), N$35) -> 800 | O53: =SUMIFS(INDIRECT("C"&$C$70&":C"), INDIRECT("B"&$C$70&":B"), ">="&$A53, INDIRECT("B"&$C$70&":B"), "<"&$A54, INDIRECT("L"&$C$70&":L"), O$35) -> 521 | P53: =SUMIFS(INDIRECT("C"&$C$70&":C"), INDIRECT("B"&$C$70&":B"), ">="&$A53, INDIRECT("B"&$C$70&":B"), "<"&$A54, INDIRECT("L"&$C$70&":L"), P$35) -> 0 | Q53: =SUMIFS(INDIRECT("C"&$C$70&":C"), INDIRECT("B"&$C$70&":B"), ">="&$A53, INDIRECT("B"&$C$70&":B"), "<"&$A54, INDIRECT("R"&$C$70&":R"), Q$35) -> 4292 | R53: =SUMIFS(INDIRECT("C"&$C$70&":C"), INDIRECT("A"&$C$70&":A"), ">="&$A53, INDIRECT("A"&$C$70&":A"), "<"&$A54, INDIRECT("R"&$C$70&":R"), "<>公司認股", INDIRECT("R"&$C$70&":R"), "<>") -> 0 | S53: =IFERROR(__xludf.DUMMYFUNCTION("TEXTJOIN("", "", TRUE, FILTER(INDIRECT(""U""&$C$70&"":U""), INDIRECT(""H""&$C$70&"":H"") <>"""", INDIRECT(""B""&$C$70&"":B"") >= $A20, INDIRECT(""B""&$C$70&"":B"") <$A21))"),"$4400冠州新公司") -> $4400冠州新公司
A54: 46023 | B54: =SUMIFS(INDIRECT("C"&$C$70&":C"), INDIRECT("B"&$C$70&":B"), ">="&$A54, INDIRECT("B"&$C$70&":B"), "<"&$A55, INDIRECT("H"&$C$70&":H"), "<>") - SUM($C54:$R54) -> 71564 | C54: =SUMIFS(INDIRECT("C"&$C$70&":C"), INDIRECT("B"&$C$70&":B"), ">="&$A54, INDIRECT("B"&$C$70&":B"), "<"&$A55, INDIRECT("J"&$C$70&":J"), C$35) -> 788 | D54: =SUMIFS(INDIRECT("C"&$C$70&":C"), INDIRECT("B"&$C$70&":B"), ">="&$A54, INDIRECT("B"&$C$70&":B"), "<"&$A55, INDIRECT("N"&$C$70&":N"), D$35) -> 6156 | E54: =SUMIFS(INDIRECT("C"&$C$70&":C"), INDIRECT("B"&$C$70&":B"), ">="&$A54, INDIRECT("B"&$C$70&":B"), "<"&$A55, INDIRECT("N"&$C$70&":N"), E$35) -> 3450 | F54: =SUMIFS(INDIRECT("C"&$C$70&":C"), INDIRECT("B"&$C$70&":B"), ">="&$A54, INDIRECT("B"&$C$70&":B"), "<"&$A55, INDIRECT("K"&$C$70&":K"), "文心1房貸代繳") + SUMIFS(INDIRECT("C"&$C$70&":C"), INDIRECT("B"&$C$70&":B"), ">="&$A54, INDIRECT("B"&$C$70&":B"), "<"&$A55, INDIRECT("K"&$C$70&":K"), "租屋") -> 26000 | G54: =SUMIFS(INDIRECT("C"&$C$70&":C"), INDIRECT("B"&$C$70&":B"), ">="&$A54, INDIRECT("B"&$C$70&":B"), "<"&$A55, INDIRECT("K"&$C$70&":K"), G$35) -> 7802 | H54: =SUMIFS(INDIRECT("C"&$C$70&":C"), INDIRECT("B"&$C$70&":B"), ">="&$A54, INDIRECT("B"&$C$70&":B"), "<"&$A55, INDIRECT("K"&$C$70&":K"), H$35) -> 197 | I54: =SUMIFS(INDIRECT("C"&$C$70&":C"), INDIRECT("B"&$C$70&":B"), ">="&$A54, INDIRECT("B"&$C$70&":B"), "<"&$A55, INDIRECT("K"&$C$70&":K"), I$35) -> 0 | J54: =SUMIFS(INDIRECT("C"&$C$70&":C"), INDIRECT("B"&$C$70&":B"), ">="&$A54, INDIRECT("B"&$C$70&":B"), "<"&$A55, INDIRECT("K"&$C$70&":K"), J$35) -> 550 | K54: =SUMIFS(INDIRECT("C"&$C$70&":C"), INDIRECT("B"&$C$70&":B"), ">="&$A54, INDIRECT("B"&$C$70&":B"), "<"&$A55, INDIRECT("L"&$C$70&":L"), K$35) -> 27434 | L54: =SUMIFS(INDIRECT("C"&$C$70&":C"), INDIRECT("B"&$C$70&":B"), ">="&$A54, INDIRECT("B"&$C$70&":B"), "<"&$A55, INDIRECT("L"&$C$70&":L"), L$35) -> 0 | M54: =SUMIFS(INDIRECT("C"&$C$70&":C"), INDIRECT("B"&$C$70&":B"), ">="&$A54, INDIRECT("B"&$C$70&":B"), "<"&$A55, INDIRECT("L"&$C$70&":L"), M$35) -> 2460 | N54: =SUMIFS(INDIRECT("C"&$C$70&":C"), INDIRECT("B"&$C$70&":B"), ">="&$A54, INDIRECT("B"&$C$70&":B"), "<"&$A55, INDIRECT("L"&$C$70&":L"), N$35) -> 0 | O54: =SUMIFS(INDIRECT("C"&$C$70&":C"), INDIRECT("B"&$C$70&":B"), ">="&$A54, INDIRECT("B"&$C$70&":B"), "<"&$A55, INDIRECT("L"&$C$70&":L"), O$35) -> 504 | P54: =SUMIFS(INDIRECT("C"&$C$70&":C"), INDIRECT("B"&$C$70&":B"), ">="&$A54, INDIRECT("B"&$C$70&":B"), "<"&$A55, INDIRECT("L"&$C$70&":L"), P$35) -> 250 | Q54: =SUMIFS(INDIRECT("C"&$C$70&":C"), INDIRECT("B"&$C$70&":B"), ">="&$A54, INDIRECT("B"&$C$70&":B"), "<"&$A55, INDIRECT("R"&$C$70&":R"), Q$35) -> 4292 | R54: =SUMIFS(INDIRECT("C"&$C$70&":C"), INDIRECT("A"&$C$70&":A"), ">="&$A54, INDIRECT("A"&$C$70&":A"), "<"&$A55, INDIRECT("R"&$C$70&":R"), "<>公司認股", INDIRECT("R"&$C$70&":R"), "<>") -> 0 | S54: =IFERROR(__xludf.DUMMYFUNCTION("TEXTJOIN("", "", TRUE, FILTER(INDIRECT(""U""&$C$70&"":U""), INDIRECT(""H""&$C$70&"":H"") <>"""", INDIRECT(""B""&$C$70&"":B"") >= $A21, INDIRECT(""B""&$C$70&"":B"") <$A22))"),"$26583汽車乙式保險, $52900婚紗") -> $26583汽車乙式保險, $52900婚紗
A55: 46054 | B55: =SUMIFS(INDIRECT("C"&$C$70&":C"), INDIRECT("B"&$C$70&":B"), ">="&$A55, INDIRECT("B"&$C$70&":B"), "<"&$A56, INDIRECT("H"&$C$70&":H"), "<>") - SUM($C55:$R55) -> 40521 | C55: =SUMIFS(INDIRECT("C"&$C$70&":C"), INDIRECT("B"&$C$70&":B"), ">="&$A55, INDIRECT("B"&$C$70&":B"), "<"&$A56, INDIRECT("J"&$C$70&":J"), C$35) -> 0 | D55: =SUMIFS(INDIRECT("C"&$C$70&":C"), INDIRECT("B"&$C$70&":B"), ">="&$A55, INDIRECT("B"&$C$70&":B"), "<"&$A56, INDIRECT("N"&$C$70&":N"), D$35) -> 6156 | E55: =SUMIFS(INDIRECT("C"&$C$70&":C"), INDIRECT("B"&$C$70&":B"), ">="&$A55, INDIRECT("B"&$C$70&":B"), "<"&$A56, INDIRECT("N"&$C$70&":N"), E$35) -> 3390 | F55: =SUMIFS(INDIRECT("C"&$C$70&":C"), INDIRECT("B"&$C$70&":B"), ">="&$A55, INDIRECT("B"&$C$70&":B"), "<"&$A56, INDIRECT("K"&$C$70&":K"), "文心1房貸代繳") + SUMIFS(INDIRECT("C"&$C$70&":C"), INDIRECT("B"&$C$70&":B"), ">="&$A55, INDIRECT("B"&$C$70&":B"), "<"&$A56, INDIRECT("K"&$C$70&":K"), "租屋") -> 26000 | G55: =SUMIFS(INDIRECT("C"&$C$70&":C"), INDIRECT("B"&$C$70&":B"), ">="&$A55, INDIRECT("B"&$C$70&":B"), "<"&$A56, INDIRECT("K"&$C$70&":K"), G$35) -> 0 | H55: =SUMIFS(INDIRECT("C"&$C$70&":C"), INDIRECT("B"&$C$70&":B"), ">="&$A55, INDIRECT("B"&$C$70&":B"), "<"&$A56, INDIRECT("K"&$C$70&":K"), H$35) -> 0 | I55: =SUMIFS(INDIRECT("C"&$C$70&":C"), INDIRECT("B"&$C$70&":B"), ">="&$A55, INDIRECT("B"&$C$70&":B"), "<"&$A56, INDIRECT("K"&$C$70&":K"), I$35) -> 965 | J55: =SUMIFS(INDIRECT("C"&$C$70&":C"), INDIRECT("B"&$C$70&":B"), ">="&$A55, INDIRECT("B"&$C$70&":B"), "<"&$A56, INDIRECT("K"&$C$70&":K"), J$35) -> 0 | K55: =SUMIFS(INDIRECT("C"&$C$70&":C"), INDIRECT("B"&$C$70&":B"), ">="&$A55, INDIRECT("B"&$C$70&":B"), "<"&$A56, INDIRECT("L"&$C$70&":L"), K$35) -> 0 | L55: =SUMIFS(INDIRECT("C"&$C$70&":C"), INDIRECT("B"&$C$70&":B"), ">="&$A55, INDIRECT("B"&$C$70&":B"), "<"&$A56, INDIRECT("L"&$C$70&":L"), L$35) -> 0 | M55: =SUMIFS(INDIRECT("C"&$C$70&":C"), INDIRECT("B"&$C$70&":B"), ">="&$A55, INDIRECT("B"&$C$70&":B"), "<"&$A56, INDIRECT("L"&$C$70&":L"), M$35) -> 1519 | N55: =SUMIFS(INDIRECT("C"&$C$70&":C"), INDIRECT("B"&$C$70&":B"), ">="&$A55, INDIRECT("B"&$C$70&":B"), "<"&$A56, INDIRECT("L"&$C$70&":L"), N$35) -> 0 | O55: =SUMIFS(INDIRECT("C"&$C$70&":C"), INDIRECT("B"&$C$70&":B"), ">="&$A55, INDIRECT("B"&$C$70&":B"), "<"&$A56, INDIRECT("L"&$C$70&":L"), O$35) -> 70 | P55: =SUMIFS(INDIRECT("C"&$C$70&":C"), INDIRECT("B"&$C$70&":B"), ">="&$A55, INDIRECT("B"&$C$70&":B"), "<"&$A56, INDIRECT("L"&$C$70&":L"), P$35) -> 4500 | Q55: =SUMIFS(INDIRECT("C"&$C$70&":C"), INDIRECT("B"&$C$70&":B"), ">="&$A55, INDIRECT("B"&$C$70&":B"), "<"&$A56, INDIRECT("R"&$C$70&":R"), Q$35) -> 4292 | R55: =SUMIFS(INDIRECT("C"&$C$70&":C"), INDIRECT("A"&$C$70&":A"), ">="&$A55, INDIRECT("A"&$C$70&":A"), "<"&$A56, INDIRECT("R"&$C$70&":R"), "<>公司認股", INDIRECT("R"&$C$70&":R"), "<>") -> 0 | S55: =IFERROR(__xludf.DUMMYFUNCTION("TEXTJOIN("", "", TRUE, FILTER(INDIRECT(""U""&$C$70&"":U""), INDIRECT(""H""&$C$70&"":H"") <>"""", INDIRECT(""B""&$C$70&"":B"") >= $A22, INDIRECT(""B""&$C$70&"":B"") <$A23))"),"$4500換輪胎, $12200紅包奶$2000，姪子$2000，寶$8200") -> $4500換輪胎, $12200紅包奶$2000，姪子$2000，寶$8200
A56: 46082 | B56: =SUMIFS(INDIRECT("C"&$C$70&":C"), INDIRECT("B"&$C$70&":B"), ">="&$A56, INDIRECT("B"&$C$70&":B"), "<"&$A57, INDIRECT("H"&$C$70&":H"), "<>") - SUM($C56:$R56) -> 42070 | C56: =SUMIFS(INDIRECT("C"&$C$70&":C"), INDIRECT("B"&$C$70&":B"), ">="&$A56, INDIRECT("B"&$C$70&":B"), "<"&$A57, INDIRECT("J"&$C$70&":J"), C$35) -> 638 | D56: =SUMIFS(INDIRECT("C"&$C$70&":C"), INDIRECT("B"&$C$70&":B"), ">="&$A56, INDIRECT("B"&$C$70&":B"), "<"&$A57, INDIRECT("N"&$C$70&":N"), D$35) -> 6201 | E56: =SUMIFS(INDIRECT("C"&$C$70&":C"), INDIRECT("B"&$C$70&":B"), ">="&$A56, INDIRECT("B"&$C$70&":B"), "<"&$A57, INDIRECT("N"&$C$70&":N"), E$35) -> 3450 | F56: =SUMIFS(INDIRECT("C"&$C$70&":C"), INDIRECT("B"&$C$70&":B"), ">="&$A56, INDIRECT("B"&$C$70&":B"), "<"&$A57, INDIRECT("K"&$C$70&":K"), "文心1房貸代繳") + SUMIFS(INDIRECT("C"&$C$70&":C"), INDIRECT("B"&$C$70&":B"), ">="&$A56, INDIRECT("B"&$C$70&":B"), "<"&$A57, INDIRECT("K"&$C$70&":K"), "租屋") -> 26000 | G56: =SUMIFS(INDIRECT("C"&$C$70&":C"), INDIRECT("B"&$C$70&":B"), ">="&$A56, INDIRECT("B"&$C$70&":B"), "<"&$A57, INDIRECT("K"&$C$70&":K"), G$35) -> 7802 | H56: =SUMIFS(INDIRECT("C"&$C$70&":C"), INDIRECT("B"&$C$70&":B"), ">="&$A56, INDIRECT("B"&$C$70&":B"), "<"&$A57, INDIRECT("K"&$C$70&":K"), H$35) -> 205 | I56: =SUMIFS(INDIRECT("C"&$C$70&":C"), INDIRECT("B"&$C$70&":B"), ">="&$A56, INDIRECT("B"&$C$70&":B"), "<"&$A57, INDIRECT("K"&$C$70&":K"), I$35) -> 0 | J56: =SUMIFS(INDIRECT("C"&$C$70&":C"), INDIRECT("B"&$C$70&":B"), ">="&$A56, INDIRECT("B"&$C$70&":B"), "<"&$A57, INDIRECT("K"&$C$70&":K"), J$35) -> 528 | K56: =SUMIFS(INDIRECT("C"&$C$70&":C"), INDIRECT("B"&$C$70&":B"), ">="&$A56, INDIRECT("B"&$C$70&":B"), "<"&$A57, INDIRECT("L"&$C$70&":L"), K$35) -> 0 | L56: =SUMIFS(INDIRECT("C"&$C$70&":C"), INDIRECT("B"&$C$70&":B"), ">="&$A56, INDIRECT("B"&$C$70&":B"), "<"&$A57, INDIRECT("L"&$C$70&":L"), L$35) -> 0 | M56: =SUMIFS(INDIRECT("C"&$C$70&":C"), INDIRECT("B"&$C$70&":B"), ">="&$A56, INDIRECT("B"&$C$70&":B"), "<"&$A57, INDIRECT("L"&$C$70&":L"), M$35) -> 1847 | N56: =SUMIFS(INDIRECT("C"&$C$70&":C"), INDIRECT("B"&$C$70&":B"), ">="&$A56, INDIRECT("B"&$C$70&":B"), "<"&$A57, INDIRECT("L"&$C$70&":L"), N$35) -> 400 | O56: =SUMIFS(INDIRECT("C"&$C$70&":C"), INDIRECT("B"&$C$70&":B"), ">="&$A56, INDIRECT("B"&$C$70&":B"), "<"&$A57, INDIRECT("L"&$C$70&":L"), O$35) -> 606 | P56: =SUMIFS(INDIRECT("C"&$C$70&":C"), INDIRECT("B"&$C$70&":B"), ">="&$A56, INDIRECT("B"&$C$70&":B"), "<"&$A57, INDIRECT("L"&$C$70&":L"), P$35) -> 200 | Q56: =SUMIFS(INDIRECT("C"&$C$70&":C"), INDIRECT("B"&$C$70&":B"), ">="&$A56, INDIRECT("B"&$C$70&":B"), "<"&$A57, INDIRECT("R"&$C$70&":R"), Q$35) -> 4292 | R56: =SUMIFS(INDIRECT("C"&$C$70&":C"), INDIRECT("A"&$C$70&":A"), ">="&$A56, INDIRECT("A"&$C$70&":A"), "<"&$A57, INDIRECT("R"&$C$70&":R"), "<>公司認股", INDIRECT("R"&$C$70&":R"), "<>") -> 0 | S56: =IFERROR(__xludf.DUMMYFUNCTION("TEXTJOIN("", "", TRUE, FILTER(INDIRECT(""U""&$C$70&"":U""), INDIRECT(""H""&$C$70&"":H"") <>"""", INDIRECT(""B""&$C$70&"":B"") >= $A23, INDIRECT(""B""&$C$70&"":B"") <$A24))"),"$2800金太太婚紗場地, $5000捐款") -> $2800金太太婚紗場地, $5000捐款
A57: 46113 | B57: =SUMIFS(INDIRECT("C"&$C$70&":C"), INDIRECT("B"&$C$70&":B"), ">="&$A57, INDIRECT("B"&$C$70&":B"), "<"&$A58, INDIRECT("H"&$C$70&":H"), "<>") - SUM($C57:$R57) -> 25523 | C57: =SUMIFS(INDIRECT("C"&$C$70&":C"), INDIRECT("B"&$C$70&":B"), ">="&$A57, INDIRECT("B"&$C$70&":B"), "<"&$A58, INDIRECT("J"&$C$70&":J"), C$35) -> 0 | D57: =SUMIFS(INDIRECT("C"&$C$70&":C"), INDIRECT("B"&$C$70&":B"), ">="&$A57, INDIRECT("B"&$C$70&":B"), "<"&$A58, INDIRECT("N"&$C$70&":N"), D$35) -> 6307 | E57: =SUMIFS(INDIRECT("C"&$C$70&":C"), INDIRECT("B"&$C$70&":B"), ">="&$A57, INDIRECT("B"&$C$70&":B"), "<"&$A58, INDIRECT("N"&$C$70&":N"), E$35) -> 4050 | F57: =SUMIFS(INDIRECT("C"&$C$70&":C"), INDIRECT("B"&$C$70&":B"), ">="&$A57, INDIRECT("B"&$C$70&":B"), "<"&$A58, INDIRECT("K"&$C$70&":K"), "文心1房貸代繳") + SUMIFS(INDIRECT("C"&$C$70&":C"), INDIRECT("B"&$C$70&":B"), ">="&$A57, INDIRECT("B"&$C$70&":B"), "<"&$A58, INDIRECT("K"&$C$70&":K"), "租屋") -> 26000 | G57: =SUMIFS(INDIRECT("C"&$C$70&":C"), INDIRECT("B"&$C$70&":B"), ">="&$A57, INDIRECT("B"&$C$70&":B"), "<"&$A58, INDIRECT("K"&$C$70&":K"), G$35) -> 0 | H57: =SUMIFS(INDIRECT("C"&$C$70&":C"), INDIRECT("B"&$C$70&":B"), ">="&$A57, INDIRECT("B"&$C$70&":B"), "<"&$A58, INDIRECT("K"&$C$70&":K"), H$35) -> 0 | I57: =SUMIFS(INDIRECT("C"&$C$70&":C"), INDIRECT("B"&$C$70&":B"), ">="&$A57, INDIRECT("B"&$C$70&":B"), "<"&$A58, INDIRECT("K"&$C$70&":K"), I$35) -> 1050 | J57: =SUMIFS(INDIRECT("C"&$C$70&":C"), INDIRECT("B"&$C$70&":B"), ">="&$A57, INDIRECT("B"&$C$70&":B"), "<"&$A58, INDIRECT("K"&$C$70&":K"), J$35) -> 0 | K57: =SUMIFS(INDIRECT("C"&$C$70&":C"), INDIRECT("B"&$C$70&":B"), ">="&$A57, INDIRECT("B"&$C$70&":B"), "<"&$A58, INDIRECT("L"&$C$70&":L"), K$35) -> 7120 | L57: =SUMIFS(INDIRECT("C"&$C$70&":C"), INDIRECT("B"&$C$70&":B"), ">="&$A57, INDIRECT("B"&$C$70&":B"), "<"&$A58, INDIRECT("L"&$C$70&":L"), L$35) -> 0 | M57: =SUMIFS(INDIRECT("C"&$C$70&":C"), INDIRECT("B"&$C$70&":B"), ">="&$A57, INDIRECT("B"&$C$70&":B"), "<"&$A58, INDIRECT("L"&$C$70&":L"), M$35) -> 1745 | N57: =SUMIFS(INDIRECT("C"&$C$70&":C"), INDIRECT("B"&$C$70&":B"), ">="&$A57, INDIRECT("B"&$C$70&":B"), "<"&$A58, INDIRECT("L"&$C$70&":L"), N$35) -> 0 | O57: =SUMIFS(INDIRECT("C"&$C$70&":C"), INDIRECT("B"&$C$70&":B"), ">="&$A57, INDIRECT("B"&$C$70&":B"), "<"&$A58, INDIRECT("L"&$C$70&":L"), O$35) -> 142 | P57: =SUMIFS(INDIRECT("C"&$C$70&":C"), INDIRECT("B"&$C$70&":B"), ">="&$A57, INDIRECT("B"&$C$70&":B"), "<"&$A58, INDIRECT("L"&$C$70&":L"), P$35) -> 1200 | Q57: =SUMIFS(INDIRECT("C"&$C$70&":C"), INDIRECT("B"&$C$70&":B"), ">="&$A57, INDIRECT("B"&$C$70&":B"), "<"&$A58, INDIRECT("R"&$C$70&":R"), Q$35) -> 4292 | R57: =SUMIFS(INDIRECT("C"&$C$70&":C"), INDIRECT("A"&$C$70&":A"), ">="&$A57, INDIRECT("A"&$C$70&":A"), "<"&$A58, INDIRECT("R"&$C$70&":R"), "<>公司認股", INDIRECT("R"&$C$70&":R"), "<>") -> 0 | S57: =IFERROR(__xludf.DUMMYFUNCTION("TEXTJOIN("", "", TRUE, FILTER(INDIRECT(""U""&$C$70&"":U""), INDIRECT(""H""&$C$70&"":H"") <>"""", INDIRECT(""B""&$C$70&"":B"") >= $A24, INDIRECT(""B""&$C$70&"":B"") <$A25))"),"$3956寶puma鞋+運動內衣, $7120牌照稅") -> $3956寶puma鞋+運動內衣, $7120牌照稅
A58: 46143 | B58: =SUMIFS(INDIRECT("C"&$C$70&":C"), INDIRECT("B"&$C$70&":B"), ">="&$A58, INDIRECT("B"&$C$70&":B"), "<"&$A59, INDIRECT("H"&$C$70&":H"), "<>") - SUM($C58:$R58) -> 24041 | C58: =SUMIFS(INDIRECT("C"&$C$70&":C"), INDIRECT("B"&$C$70&":B"), ">="&$A58, INDIRECT("B"&$C$70&":B"), "<"&$A59, INDIRECT("J"&$C$70&":J"), C$35) -> 1506 | D58: =SUMIFS(INDIRECT("C"&$C$70&":C"), INDIRECT("B"&$C$70&":B"), ">="&$A58, INDIRECT("B"&$C$70&":B"), "<"&$A59, INDIRECT("N"&$C$70&":N"), D$35) -> 8465 | E58: =SUMIFS(INDIRECT("C"&$C$70&":C"), INDIRECT("B"&$C$70&":B"), ">="&$A58, INDIRECT("B"&$C$70&":B"), "<"&$A59, INDIRECT("N"&$C$70&":N"), E$35) -> 104379 | F58: =SUMIFS(INDIRECT("C"&$C$70&":C"), INDIRECT("B"&$C$70&":B"), ">="&$A58, INDIRECT("B"&$C$70&":B"), "<"&$A59, INDIRECT("K"&$C$70&":K"), "文心1房貸代繳") + SUMIFS(INDIRECT("C"&$C$70&":C"), INDIRECT("B"&$C$70&":B"), ">="&$A58, INDIRECT("B"&$C$70&":B"), "<"&$A59, INDIRECT("K"&$C$70&":K"), "租屋") -> 26000 | G58: =SUMIFS(INDIRECT("C"&$C$70&":C"), INDIRECT("B"&$C$70&":B"), ">="&$A58, INDIRECT("B"&$C$70&":B"), "<"&$A59, INDIRECT("K"&$C$70&":K"), G$35) -> 7802 | H58: =SUMIFS(INDIRECT("C"&$C$70&":C"), INDIRECT("B"&$C$70&":B"), ">="&$A58, INDIRECT("B"&$C$70&":B"), "<"&$A59, INDIRECT("K"&$C$70&":K"), H$35) -> 230 | I58: =SUMIFS(INDIRECT("C"&$C$70&":C"), INDIRECT("B"&$C$70&":B"), ">="&$A58, INDIRECT("B"&$C$70&":B"), "<"&$A59, INDIRECT("K"&$C$70&":K"), I$35) -> 0 | J58: =SUMIFS(INDIRECT("C"&$C$70&":C"), INDIRECT("B"&$C$70&":B"), ">="&$A58, INDIRECT("B"&$C$70&":B"), "<"&$A59, INDIRECT("K"&$C$70&":K"), J$35) -> 558 | K58: =SUMIFS(INDIRECT("C"&$C$70&":C"), INDIRECT("B"&$C$70&":B"), ">="&$A58, INDIRECT("B"&$C$70&":B"), "<"&$A59, INDIRECT("L"&$C$70&":L"), K$35) -> 0 | L58: =SUMIFS(INDIRECT("C"&$C$70&":C"), INDIRECT("B"&$C$70&":B"), ">="&$A58, INDIRECT("B"&$C$70&":B"), "<"&$A59, INDIRECT("L"&$C$70&":L"), L$35) -> 10670 | M58: =SUMIFS(INDIRECT("C"&$C$70&":C"), INDIRECT("B"&$C$70&":B"), ">="&$A58, INDIRECT("B"&$C$70&":B"), "<"&$A59, INDIRECT("L"&$C$70&":L"), M$35) -> 2580 | N58: =SUMIFS(INDIRECT("C"&$C$70&":C"), INDIRECT("B"&$C$70&":B"), ">="&$A58, INDIRECT("B"&$C$70&":B"), "<"&$A59, INDIRECT("L"&$C$70&":L"), N$35) -> 400 | O58: =SUMIFS(INDIRECT("C"&$C$70&":C"), INDIRECT("B"&$C$70&":B"), ">="&$A58, INDIRECT("B"&$C$70&":B"), "<"&$A59, INDIRECT("L"&$C$70&":L"), O$35) -> 80 | P58: =SUMIFS(INDIRECT("C"&$C$70&":C"), INDIRECT("B"&$C$70&":B"), ">="&$A58, INDIRECT("B"&$C$70&":B"), "<"&$A59, INDIRECT("L"&$C$70&":L"), P$35) -> 50 | Q58: =SUMIFS(INDIRECT("C"&$C$70&":C"), INDIRECT("B"&$C$70&":B"), ">="&$A58, INDIRECT("B"&$C$70&":B"), "<"&$A59, INDIRECT("R"&$C$70&":R"), Q$35) -> 4292 | R58: =SUMIFS(INDIRECT("C"&$C$70&":C"), INDIRECT("A"&$C$70&":A"), ">="&$A58, INDIRECT("A"&$C$70&":A"), "<"&$A59, INDIRECT("R"&$C$70&":R"), "<>公司認股", INDIRECT("R"&$C$70&":R"), "<>") -> 0 | S58: =IFERROR(__xludf.DUMMYFUNCTION("TEXTJOIN("", "", TRUE, FILTER(INDIRECT(""U""&$C$70&"":U""), INDIRECT(""H""&$C$70&"":H"") <>"""", INDIRECT(""B""&$C$70&"":B"") >= $A25, INDIRECT(""B""&$C$70&"":B"") <$A26))"),"$95804所得稅") -> $95804所得稅
A59: 46174 | B59: =SUMIFS(INDIRECT("C"&$C$70&":C"), INDIRECT("B"&$C$70&":B"), ">="&$A59, INDIRECT("B"&$C$70&":B"), "<"&$A60, INDIRECT("H"&$C$70&":H"), "<>") - SUM($C59:$R59) -> 85490 | C59: =SUMIFS(INDIRECT("C"&$C$70&":C"), INDIRECT("B"&$C$70&":B"), ">="&$A59, INDIRECT("B"&$C$70&":B"), "<"&$A60, INDIRECT("J"&$C$70&":J"), C$35) -> 0 | D59: =SUMIFS(INDIRECT("C"&$C$70&":C"), INDIRECT("B"&$C$70&":B"), ">="&$A59, INDIRECT("B"&$C$70&":B"), "<"&$A60, INDIRECT("N"&$C$70&":N"), D$35) -> 6203 | E59: =SUMIFS(INDIRECT("C"&$C$70&":C"), INDIRECT("B"&$C$70&":B"), ">="&$A59, INDIRECT("B"&$C$70&":B"), "<"&$A60, INDIRECT("N"&$C$70&":N"), E$35) -> 3810 | F59: =SUMIFS(INDIRECT("C"&$C$70&":C"), INDIRECT("B"&$C$70&":B"), ">="&$A59, INDIRECT("B"&$C$70&":B"), "<"&$A60, INDIRECT("K"&$C$70&":K"), "文心1房貸代繳") + SUMIFS(INDIRECT("C"&$C$70&":C"), INDIRECT("B"&$C$70&":B"), ">="&$A59, INDIRECT("B"&$C$70&":B"), "<"&$A60, INDIRECT("K"&$C$70&":K"), "租屋") -> 26000 | G59: =SUMIFS(INDIRECT("C"&$C$70&":C"), INDIRECT("B"&$C$70&":B"), ">="&$A59, INDIRECT("B"&$C$70&":B"), "<"&$A60, INDIRECT("K"&$C$70&":K"), G$35) -> 0 | H59: =SUMIFS(INDIRECT("C"&$C$70&":C"), INDIRECT("B"&$C$70&":B"), ">="&$A59, INDIRECT("B"&$C$70&":B"), "<"&$A60, INDIRECT("K"&$C$70&":K"), H$35) -> 0 | I59: =SUMIFS(INDIRECT("C"&$C$70&":C"), INDIRECT("B"&$C$70&":B"), ">="&$A59, INDIRECT("B"&$C$70&":B"), "<"&$A60, INDIRECT("K"&$C$70&":K"), I$35) -> 1268 | J59: =SUMIFS(INDIRECT("C"&$C$70&":C"), INDIRECT("B"&$C$70&":B"), ">="&$A59, INDIRECT("B"&$C$70&":B"), "<"&$A60, INDIRECT("K"&$C$70&":K"), J$35) -> 0 | K59: =SUMIFS(INDIRECT("C"&$C$70&":C"), INDIRECT("B"&$C$70&":B"), ">="&$A59, INDIRECT("B"&$C$70&":B"), "<"&$A60, INDIRECT("L"&$C$70&":L"), K$35) -> 0 | L59: =SUMIFS(INDIRECT("C"&$C$70&":C"), INDIRECT("B"&$C$70&":B"), ">="&$A59, INDIRECT("B"&$C$70&":B"), "<"&$A60, INDIRECT("L"&$C$70&":L"), L$35) -> 0 | M59: =SUMIFS(INDIRECT("C"&$C$70&":C"), INDIRECT("B"&$C$70&":B"), ">="&$A59, INDIRECT("B"&$C$70&":B"), "<"&$A60, INDIRECT("L"&$C$70&":L"), M$35) -> 3080 | N59: =SUMIFS(INDIRECT("C"&$C$70&":C"), INDIRECT("B"&$C$70&":B"), ">="&$A59, INDIRECT("B"&$C$70&":B"), "<"&$A60, INDIRECT("L"&$C$70&":L"), N$35) -> 800 | O59: =SUMIFS(INDIRECT("C"&$C$70&":C"), INDIRECT("B"&$C$70&":B"), ">="&$A59, INDIRECT("B"&$C$70&":B"), "<"&$A60, INDIRECT("L"&$C$70&":L"), O$35) -> 356 | P59: =SUMIFS(INDIRECT("C"&$C$70&":C"), INDIRECT("B"&$C$70&":B"), ">="&$A59, INDIRECT("B"&$C$70&":B"), "<"&$A60, INDIRECT("L"&$C$70&":L"), P$35) -> 0 | Q59: =SUMIFS(INDIRECT("C"&$C$70&":C"), INDIRECT("B"&$C$70&":B"), ">="&$A59, INDIRECT("B"&$C$70&":B"), "<"&$A60, INDIRECT("R"&$C$70&":R"), Q$35) -> 4412 | R59: =SUMIFS(INDIRECT("C"&$C$70&":C"), INDIRECT("A"&$C$70&":A"), ">="&$A59, INDIRECT("A"&$C$70&":A"), "<"&$A60, INDIRECT("R"&$C$70&":R"), "<>公司認股", INDIRECT("R"&$C$70&":R"), "<>") -> 0 | S59: =IFERROR(__xludf.DUMMYFUNCTION("TEXTJOIN("", "", TRUE, FILTER(INDIRECT(""U""&$C$70&"":U""), INDIRECT(""H""&$C$70&"":H"") <>"""", INDIRECT(""B""&$C$70&"":B"") >= $A26, INDIRECT(""B""&$C$70&"":B"") <$A27))"),"$68521韓國旅遊") -> $68521韓國旅遊
A60: 46204 | B60: =SUMIFS(INDIRECT("C"&$C$70&":C"), INDIRECT("B"&$C$70&":B"), ">="&$A60, INDIRECT("B"&$C$70&":B"), "<"&$A61, INDIRECT("H"&$C$70&":H"), "<>") - SUM($C60:$R60) -> 8739 | C60: =SUMIFS(INDIRECT("C"&$C$70&":C"), INDIRECT("B"&$C$70&":B"), ">="&$A60, INDIRECT("B"&$C$70&":B"), "<"&$A61, INDIRECT("J"&$C$70&":J"), C$35) -> 0 | D60: =SUMIFS(INDIRECT("C"&$C$70&":C"), INDIRECT("B"&$C$70&":B"), ">="&$A60, INDIRECT("B"&$C$70&":B"), "<"&$A61, INDIRECT("N"&$C$70&":N"), D$35) -> 6203 | E60: =SUMIFS(INDIRECT("C"&$C$70&":C"), INDIRECT("B"&$C$70&":B"), ">="&$A60, INDIRECT("B"&$C$70&":B"), "<"&$A61, INDIRECT("N"&$C$70&":N"), E$35) -> 3810 | F60: =SUMIFS(INDIRECT("C"&$C$70&":C"), INDIRECT("B"&$C$70&":B"), ">="&$A60, INDIRECT("B"&$C$70&":B"), "<"&$A61, INDIRECT("K"&$C$70&":K"), "文心1房貸代繳") + SUMIFS(INDIRECT("C"&$C$70&":C"), INDIRECT("B"&$C$70&":B"), ">="&$A60, INDIRECT("B"&$C$70&":B"), "<"&$A61, INDIRECT("K"&$C$70&":K"), "租屋") -> 0 | G60: =SUMIFS(INDIRECT("C"&$C$70&":C"), INDIRECT("B"&$C$70&":B"), ">="&$A60, INDIRECT("B"&$C$70&":B"), "<"&$A61, INDIRECT("K"&$C$70&":K"), G$35) -> 7802 | H60: =SUMIFS(INDIRECT("C"&$C$70&":C"), INDIRECT("B"&$C$70&":B"), ">="&$A60, INDIRECT("B"&$C$70&":B"), "<"&$A61, INDIRECT("K"&$C$70&":K"), H$35) -> 0 | I60: =SUMIFS(INDIRECT("C"&$C$70&":C"), INDIRECT("B"&$C$70&":B"), ">="&$A60, INDIRECT("B"&$C$70&":B"), "<"&$A61, INDIRECT("K"&$C$70&":K"), I$35) -> 0 | J60: =SUMIFS(INDIRECT("C"&$C$70&":C"), INDIRECT("B"&$C$70&":B"), ">="&$A60, INDIRECT("B"&$C$70&":B"), "<"&$A61, INDIRECT("K"&$C$70&":K"), J$35) -> 0 | K60: =SUMIFS(INDIRECT("C"&$C$70&":C"), INDIRECT("B"&$C$70&":B"), ">="&$A60, INDIRECT("B"&$C$70&":B"), "<"&$A61, INDIRECT("L"&$C$70&":L"), K$35) -> 0 | L60: =SUMIFS(INDIRECT("C"&$C$70&":C"), INDIRECT("B"&$C$70&":B"), ">="&$A60, INDIRECT("B"&$C$70&":B"), "<"&$A61, INDIRECT("L"&$C$70&":L"), L$35) -> 0 | M60: =SUMIFS(INDIRECT("C"&$C$70&":C"), INDIRECT("B"&$C$70&":B"), ">="&$A60, INDIRECT("B"&$C$70&":B"), "<"&$A61, INDIRECT("L"&$C$70&":L"), M$35) -> 921 | N60: =SUMIFS(INDIRECT("C"&$C$70&":C"), INDIRECT("B"&$C$70&":B"), ">="&$A60, INDIRECT("B"&$C$70&":B"), "<"&$A61, INDIRECT("L"&$C$70&":L"), N$35) -> 0 | O60: =SUMIFS(INDIRECT("C"&$C$70&":C"), INDIRECT("B"&$C$70&":B"), ">="&$A60, INDIRECT("B"&$C$70&":B"), "<"&$A61, INDIRECT("L"&$C$70&":L"), O$35) -> 0 | P60: =SUMIFS(INDIRECT("C"&$C$70&":C"), INDIRECT("B"&$C$70&":B"), ">="&$A60, INDIRECT("B"&$C$70&":B"), "<"&$A61, INDIRECT("L"&$C$70&":L"), P$35) -> 0 | Q60: =SUMIFS(INDIRECT("C"&$C$70&":C"), INDIRECT("B"&$C$70&":B"), ">="&$A60, INDIRECT("B"&$C$70&":B"), "<"&$A61, INDIRECT("R"&$C$70&":R"), Q$35) -> 4412 | R60: =SUMIFS(INDIRECT("C"&$C$70&":C"), INDIRECT("A"&$C$70&":A"), ">="&$A60, INDIRECT("A"&$C$70&":A"), "<"&$A61, INDIRECT("R"&$C$70&":R"), "<>公司認股", INDIRECT("R"&$C$70&":R"), "<>") -> 0 | S60: =IFERROR(__xludf.DUMMYFUNCTION("TEXTJOIN("", "", TRUE, FILTER(INDIRECT(""U""&$C$70&"":U""), INDIRECT(""H""&$C$70&"":H"") <>"""", INDIRECT(""B""&$C$70&"":B"") >= $A27, INDIRECT(""B""&$C$70&"":B"") <$A28))"),"")
A61: 46235 | B61: =SUMIFS(INDIRECT("C"&$C$70&":C"), INDIRECT("B"&$C$70&":B"), ">="&$A61, INDIRECT("B"&$C$70&":B"), "<"&$A62, INDIRECT("H"&$C$70&":H"), "<>") - SUM($C61:$R61) -> 0 | C61: =SUMIFS(INDIRECT("C"&$C$70&":C"), INDIRECT("B"&$C$70&":B"), ">="&$A61, INDIRECT("B"&$C$70&":B"), "<"&$A62, INDIRECT("J"&$C$70&":J"), C$35) -> 0 | D61: =SUMIFS(INDIRECT("C"&$C$70&":C"), INDIRECT("B"&$C$70&":B"), ">="&$A61, INDIRECT("B"&$C$70&":B"), "<"&$A62, INDIRECT("N"&$C$70&":N"), D$35) -> 0 | E61: =SUMIFS(INDIRECT("C"&$C$70&":C"), INDIRECT("B"&$C$70&":B"), ">="&$A61, INDIRECT("B"&$C$70&":B"), "<"&$A62, INDIRECT("N"&$C$70&":N"), E$35) -> 0 | F61: =SUMIFS(INDIRECT("C"&$C$70&":C"), INDIRECT("B"&$C$70&":B"), ">="&$A61, INDIRECT("B"&$C$70&":B"), "<"&$A62, INDIRECT("K"&$C$70&":K"), "文心1房貸代繳") + SUMIFS(INDIRECT("C"&$C$70&":C"), INDIRECT("B"&$C$70&":B"), ">="&$A61, INDIRECT("B"&$C$70&":B"), "<"&$A62, INDIRECT("K"&$C$70&":K"), "租屋") -> 0 | G61: =SUMIFS(INDIRECT("C"&$C$70&":C"), INDIRECT("B"&$C$70&":B"), ">="&$A61, INDIRECT("B"&$C$70&":B"), "<"&$A62, INDIRECT("K"&$C$70&":K"), G$35) -> 0 | H61: =SUMIFS(INDIRECT("C"&$C$70&":C"), INDIRECT("B"&$C$70&":B"), ">="&$A61, INDIRECT("B"&$C$70&":B"), "<"&$A62, INDIRECT("K"&$C$70&":K"), H$35) -> 0 | I61: =SUMIFS(INDIRECT("C"&$C$70&":C"), INDIRECT("B"&$C$70&":B"), ">="&$A61, INDIRECT("B"&$C$70&":B"), "<"&$A62, INDIRECT("K"&$C$70&":K"), I$35) -> 0 | J61: =SUMIFS(INDIRECT("C"&$C$70&":C"), INDIRECT("B"&$C$70&":B"), ">="&$A61, INDIRECT("B"&$C$70&":B"), "<"&$A62, INDIRECT("K"&$C$70&":K"), J$35) -> 0 | K61: =SUMIFS(INDIRECT("C"&$C$70&":C"), INDIRECT("B"&$C$70&":B"), ">="&$A61, INDIRECT("B"&$C$70&":B"), "<"&$A62, INDIRECT("L"&$C$70&":L"), K$35) -> 0 | L61: =SUMIFS(INDIRECT("C"&$C$70&":C"), INDIRECT("B"&$C$70&":B"), ">="&$A61, INDIRECT("B"&$C$70&":B"), "<"&$A62, INDIRECT("L"&$C$70&":L"), L$35) -> 0 | M61: =SUMIFS(INDIRECT("C"&$C$70&":C"), INDIRECT("B"&$C$70&":B"), ">="&$A61, INDIRECT("B"&$C$70&":B"), "<"&$A62, INDIRECT("L"&$C$70&":L"), M$35) -> 0 | N61: =SUMIFS(INDIRECT("C"&$C$70&":C"), INDIRECT("B"&$C$70&":B"), ">="&$A61, INDIRECT("B"&$C$70&":B"), "<"&$A62, INDIRECT("L"&$C$70&":L"), N$35) -> 0 | O61: =SUMIFS(INDIRECT("C"&$C$70&":C"), INDIRECT("B"&$C$70&":B"), ">="&$A61, INDIRECT("B"&$C$70&":B"), "<"&$A62, INDIRECT("L"&$C$70&":L"), O$35) -> 0 | P61: =SUMIFS(INDIRECT("C"&$C$70&":C"), INDIRECT("B"&$C$70&":B"), ">="&$A61, INDIRECT("B"&$C$70&":B"), "<"&$A62, INDIRECT("L"&$C$70&":L"), P$35) -> 0 | Q61: =SUMIFS(INDIRECT("C"&$C$70&":C"), INDIRECT("B"&$C$70&":B"), ">="&$A61, INDIRECT("B"&$C$70&":B"), "<"&$A62, INDIRECT("R"&$C$70&":R"), Q$35) -> 0 | R61: =SUMIFS(INDIRECT("C"&$C$70&":C"), INDIRECT("A"&$C$70&":A"), ">="&$A61, INDIRECT("A"&$C$70&":A"), "<"&$A62, INDIRECT("R"&$C$70&":R"), "<>公司認股", INDIRECT("R"&$C$70&":R"), "<>") -> 0 | S61: =IFERROR(__xludf.DUMMYFUNCTION("TEXTJOIN("", "", TRUE, FILTER(INDIRECT(""U""&$C$70&"":U""), INDIRECT(""H""&$C$70&"":H"") <>"""", INDIRECT(""B""&$C$70&"":B"") >= $A28, INDIRECT(""B""&$C$70&"":B"") <$A29))"),"#N/A") -> #N/A
A62: 46266 | B62: =SUMIFS(INDIRECT("C"&$C$70&":C"), INDIRECT("B"&$C$70&":B"), ">="&$A62, INDIRECT("B"&$C$70&":B"), "<"&$A63, INDIRECT("H"&$C$70&":H"), "<>") - SUM($C62:$R62) -> 0 | C62: =SUMIFS(INDIRECT("C"&$C$70&":C"), INDIRECT("B"&$C$70&":B"), ">="&$A62, INDIRECT("B"&$C$70&":B"), "<"&$A63, INDIRECT("J"&$C$70&":J"), C$35) -> 0 | D62: =SUMIFS(INDIRECT("C"&$C$70&":C"), INDIRECT("B"&$C$70&":B"), ">="&$A62, INDIRECT("B"&$C$70&":B"), "<"&$A63, INDIRECT("N"&$C$70&":N"), D$35) -> 0 | E62: =SUMIFS(INDIRECT("C"&$C$70&":C"), INDIRECT("B"&$C$70&":B"), ">="&$A62, INDIRECT("B"&$C$70&":B"), "<"&$A63, INDIRECT("N"&$C$70&":N"), E$35) -> 0 | F62: =SUMIFS(INDIRECT("C"&$C$70&":C"), INDIRECT("B"&$C$70&":B"), ">="&$A62, INDIRECT("B"&$C$70&":B"), "<"&$A63, INDIRECT("K"&$C$70&":K"), "文心1房貸代繳") + SUMIFS(INDIRECT("C"&$C$70&":C"), INDIRECT("B"&$C$70&":B"), ">="&$A62, INDIRECT("B"&$C$70&":B"), "<"&$A63, INDIRECT("K"&$C$70&":K"), "租屋") -> 0 | G62: =SUMIFS(INDIRECT("C"&$C$70&":C"), INDIRECT("B"&$C$70&":B"), ">="&$A62, INDIRECT("B"&$C$70&":B"), "<"&$A63, INDIRECT("K"&$C$70&":K"), G$35) -> 0 | H62: =SUMIFS(INDIRECT("C"&$C$70&":C"), INDIRECT("B"&$C$70&":B"), ">="&$A62, INDIRECT("B"&$C$70&":B"), "<"&$A63, INDIRECT("K"&$C$70&":K"), H$35) -> 0 | I62: =SUMIFS(INDIRECT("C"&$C$70&":C"), INDIRECT("B"&$C$70&":B"), ">="&$A62, INDIRECT("B"&$C$70&":B"), "<"&$A63, INDIRECT("K"&$C$70&":K"), I$35) -> 0 | J62: =SUMIFS(INDIRECT("C"&$C$70&":C"), INDIRECT("B"&$C$70&":B"), ">="&$A62, INDIRECT("B"&$C$70&":B"), "<"&$A63, INDIRECT("K"&$C$70&":K"), J$35) -> 0 | K62: =SUMIFS(INDIRECT("C"&$C$70&":C"), INDIRECT("B"&$C$70&":B"), ">="&$A62, INDIRECT("B"&$C$70&":B"), "<"&$A63, INDIRECT("L"&$C$70&":L"), K$35) -> 0 | L62: =SUMIFS(INDIRECT("C"&$C$70&":C"), INDIRECT("B"&$C$70&":B"), ">="&$A62, INDIRECT("B"&$C$70&":B"), "<"&$A63, INDIRECT("L"&$C$70&":L"), L$35) -> 0 | M62: =SUMIFS(INDIRECT("C"&$C$70&":C"), INDIRECT("B"&$C$70&":B"), ">="&$A62, INDIRECT("B"&$C$70&":B"), "<"&$A63, INDIRECT("L"&$C$70&":L"), M$35) -> 0 | N62: =SUMIFS(INDIRECT("C"&$C$70&":C"), INDIRECT("B"&$C$70&":B"), ">="&$A62, INDIRECT("B"&$C$70&":B"), "<"&$A63, INDIRECT("L"&$C$70&":L"), N$35) -> 0 | O62: =SUMIFS(INDIRECT("C"&$C$70&":C"), INDIRECT("B"&$C$70&":B"), ">="&$A62, INDIRECT("B"&$C$70&":B"), "<"&$A63, INDIRECT("L"&$C$70&":L"), O$35) -> 0 | P62: =SUMIFS(INDIRECT("C"&$C$70&":C"), INDIRECT("B"&$C$70&":B"), ">="&$A62, INDIRECT("B"&$C$70&":B"), "<"&$A63, INDIRECT("L"&$C$70&":L"), P$35) -> 0 | Q62: =SUMIFS(INDIRECT("C"&$C$70&":C"), INDIRECT("B"&$C$70&":B"), ">="&$A62, INDIRECT("B"&$C$70&":B"), "<"&$A63, INDIRECT("R"&$C$70&":R"), Q$35) -> 0 | R62: =SUMIFS(INDIRECT("C"&$C$70&":C"), INDIRECT("A"&$C$70&":A"), ">="&$A62, INDIRECT("A"&$C$70&":A"), "<"&$A63, INDIRECT("R"&$C$70&":R"), "<>公司認股", INDIRECT("R"&$C$70&":R"), "<>") -> 0 | S62: =IFERROR(__xludf.DUMMYFUNCTION("TEXTJOIN("", "", TRUE, FILTER(INDIRECT(""U""&$C$70&"":U""), INDIRECT(""H""&$C$70&"":H"") <>"""", INDIRECT(""B""&$C$70&"":B"") >= $A29, INDIRECT(""B""&$C$70&"":B"") <$A30))"),"#N/A") -> #N/A
A63: 46296 | B63: =SUMIFS(INDIRECT("C"&$C$70&":C"), INDIRECT("B"&$C$70&":B"), ">="&$A63, INDIRECT("B"&$C$70&":B"), "<"&$A64, INDIRECT("H"&$C$70&":H"), "<>") - SUM($C63:$R63) -> 2030 | C63: =SUMIFS(INDIRECT("C"&$C$70&":C"), INDIRECT("B"&$C$70&":B"), ">="&$A63, INDIRECT("B"&$C$70&":B"), "<"&$A64, INDIRECT("J"&$C$70&":J"), C$35) -> 0 | D63: =SUMIFS(INDIRECT("C"&$C$70&":C"), INDIRECT("B"&$C$70&":B"), ">="&$A63, INDIRECT("B"&$C$70&":B"), "<"&$A64, INDIRECT("N"&$C$70&":N"), D$35) -> 0 | E63: =SUMIFS(INDIRECT("C"&$C$70&":C"), INDIRECT("B"&$C$70&":B"), ">="&$A63, INDIRECT("B"&$C$70&":B"), "<"&$A64, INDIRECT("N"&$C$70&":N"), E$35) -> 0 | F63: =SUMIFS(INDIRECT("C"&$C$70&":C"), INDIRECT("B"&$C$70&":B"), ">="&$A63, INDIRECT("B"&$C$70&":B"), "<"&$A64, INDIRECT("K"&$C$70&":K"), "文心1房貸代繳") + SUMIFS(INDIRECT("C"&$C$70&":C"), INDIRECT("B"&$C$70&":B"), ">="&$A63, INDIRECT("B"&$C$70&":B"), "<"&$A64, INDIRECT("K"&$C$70&":K"), "租屋") -> 0 | G63: =SUMIFS(INDIRECT("C"&$C$70&":C"), INDIRECT("B"&$C$70&":B"), ">="&$A63, INDIRECT("B"&$C$70&":B"), "<"&$A64, INDIRECT("K"&$C$70&":K"), G$35) -> 0 | H63: =SUMIFS(INDIRECT("C"&$C$70&":C"), INDIRECT("B"&$C$70&":B"), ">="&$A63, INDIRECT("B"&$C$70&":B"), "<"&$A64, INDIRECT("K"&$C$70&":K"), H$35) -> 0 | I63: =SUMIFS(INDIRECT("C"&$C$70&":C"), INDIRECT("B"&$C$70&":B"), ">="&$A63, INDIRECT("B"&$C$70&":B"), "<"&$A64, INDIRECT("K"&$C$70&":K"), I$35) -> 0 | J63: =SUMIFS(INDIRECT("C"&$C$70&":C"), INDIRECT("B"&$C$70&":B"), ">="&$A63, INDIRECT("B"&$C$70&":B"), "<"&$A64, INDIRECT("K"&$C$70&":K"), J$35) -> 0 | K63: =SUMIFS(INDIRECT("C"&$C$70&":C"), INDIRECT("B"&$C$70&":B"), ">="&$A63, INDIRECT("B"&$C$70&":B"), "<"&$A64, INDIRECT("L"&$C$70&":L"), K$35) -> 0 | L63: =SUMIFS(INDIRECT("C"&$C$70&":C"), INDIRECT("B"&$C$70&":B"), ">="&$A63, INDIRECT("B"&$C$70&":B"), "<"&$A64, INDIRECT("L"&$C$70&":L"), L$35) -> 0 | M63: =SUMIFS(INDIRECT("C"&$C$70&":C"), INDIRECT("B"&$C$70&":B"), ">="&$A63, INDIRECT("B"&$C$70&":B"), "<"&$A64, INDIRECT("L"&$C$70&":L"), M$35) -> 0 | N63: =SUMIFS(INDIRECT("C"&$C$70&":C"), INDIRECT("B"&$C$70&":B"), ">="&$A63, INDIRECT("B"&$C$70&":B"), "<"&$A64, INDIRECT("L"&$C$70&":L"), N$35) -> 0 | O63: =SUMIFS(INDIRECT("C"&$C$70&":C"), INDIRECT("B"&$C$70&":B"), ">="&$A63, INDIRECT("B"&$C$70&":B"), "<"&$A64, INDIRECT("L"&$C$70&":L"), O$35) -> 0 | P63: =SUMIFS(INDIRECT("C"&$C$70&":C"), INDIRECT("B"&$C$70&":B"), ">="&$A63, INDIRECT("B"&$C$70&":B"), "<"&$A64, INDIRECT("L"&$C$70&":L"), P$35) -> 0 | Q63: =SUMIFS(INDIRECT("C"&$C$70&":C"), INDIRECT("B"&$C$70&":B"), ">="&$A63, INDIRECT("B"&$C$70&":B"), "<"&$A64, INDIRECT("R"&$C$70&":R"), Q$35) -> 0 | R63: =SUMIFS(INDIRECT("C"&$C$70&":C"), INDIRECT("A"&$C$70&":A"), ">="&$A63, INDIRECT("A"&$C$70&":A"), "<"&$A64, INDIRECT("R"&$C$70&":R"), "<>公司認股", INDIRECT("R"&$C$70&":R"), "<>") -> 0 | S63: =IFERROR(__xludf.DUMMYFUNCTION("TEXTJOIN("", "", TRUE, FILTER(INDIRECT(""U""&$C$70&"":U""), INDIRECT(""H""&$C$70&"":H"") <>"""", INDIRECT(""B""&$C$70&"":B"") >= $A30, INDIRECT(""B""&$C$70&"":B"") <$A31))"),"")
A64: 46327 | B64: =SUMIFS(INDIRECT("C"&$C$70&":C"), INDIRECT("B"&$C$70&":B"), ">="&$A64, INDIRECT("B"&$C$70&":B"), "<"&$A65, INDIRECT("H"&$C$70&":H"), "<>") - SUM($C64:$R64) -> 0 | C64: =SUMIFS(INDIRECT("C"&$C$70&":C"), INDIRECT("B"&$C$70&":B"), ">="&$A64, INDIRECT("B"&$C$70&":B"), "<"&$A65, INDIRECT("J"&$C$70&":J"), C$35) -> 0 | D64: =SUMIFS(INDIRECT("C"&$C$70&":C"), INDIRECT("B"&$C$70&":B"), ">="&$A64, INDIRECT("B"&$C$70&":B"), "<"&$A65, INDIRECT("N"&$C$70&":N"), D$35) -> 0 | E64: =SUMIFS(INDIRECT("C"&$C$70&":C"), INDIRECT("B"&$C$70&":B"), ">="&$A64, INDIRECT("B"&$C$70&":B"), "<"&$A65, INDIRECT("N"&$C$70&":N"), E$35) -> 0 | F64: =SUMIFS(INDIRECT("C"&$C$70&":C"), INDIRECT("B"&$C$70&":B"), ">="&$A64, INDIRECT("B"&$C$70&":B"), "<"&$A65, INDIRECT("K"&$C$70&":K"), "文心1房貸代繳") + SUMIFS(INDIRECT("C"&$C$70&":C"), INDIRECT("B"&$C$70&":B"), ">="&$A64, INDIRECT("B"&$C$70&":B"), "<"&$A65, INDIRECT("K"&$C$70&":K"), "租屋") -> 0 | G64: =SUMIFS(INDIRECT("C"&$C$70&":C"), INDIRECT("B"&$C$70&":B"), ">="&$A64, INDIRECT("B"&$C$70&":B"), "<"&$A65, INDIRECT("K"&$C$70&":K"), G$35) -> 0 | H64: =SUMIFS(INDIRECT("C"&$C$70&":C"), INDIRECT("B"&$C$70&":B"), ">="&$A64, INDIRECT("B"&$C$70&":B"), "<"&$A65, INDIRECT("K"&$C$70&":K"), H$35) -> 0 | I64: =SUMIFS(INDIRECT("C"&$C$70&":C"), INDIRECT("B"&$C$70&":B"), ">="&$A64, INDIRECT("B"&$C$70&":B"), "<"&$A65, INDIRECT("K"&$C$70&":K"), I$35) -> 0 | J64: =SUMIFS(INDIRECT("C"&$C$70&":C"), INDIRECT("B"&$C$70&":B"), ">="&$A64, INDIRECT("B"&$C$70&":B"), "<"&$A65, INDIRECT("K"&$C$70&":K"), J$35) -> 0 | K64: =SUMIFS(INDIRECT("C"&$C$70&":C"), INDIRECT("B"&$C$70&":B"), ">="&$A64, INDIRECT("B"&$C$70&":B"), "<"&$A65, INDIRECT("L"&$C$70&":L"), K$35) -> 0 | L64: =SUMIFS(INDIRECT("C"&$C$70&":C"), INDIRECT("B"&$C$70&":B"), ">="&$A64, INDIRECT("B"&$C$70&":B"), "<"&$A65, INDIRECT("L"&$C$70&":L"), L$35) -> 0 | M64: =SUMIFS(INDIRECT("C"&$C$70&":C"), INDIRECT("B"&$C$70&":B"), ">="&$A64, INDIRECT("B"&$C$70&":B"), "<"&$A65, INDIRECT("L"&$C$70&":L"), M$35) -> 0 | N64: =SUMIFS(INDIRECT("C"&$C$70&":C"), INDIRECT("B"&$C$70&":B"), ">="&$A64, INDIRECT("B"&$C$70&":B"), "<"&$A65, INDIRECT("L"&$C$70&":L"), N$35) -> 0 | O64: =SUMIFS(INDIRECT("C"&$C$70&":C"), INDIRECT("B"&$C$70&":B"), ">="&$A64, INDIRECT("B"&$C$70&":B"), "<"&$A65, INDIRECT("L"&$C$70&":L"), O$35) -> 0 | P64: =SUMIFS(INDIRECT("C"&$C$70&":C"), INDIRECT("B"&$C$70&":B"), ">="&$A64, INDIRECT("B"&$C$70&":B"), "<"&$A65, INDIRECT("L"&$C$70&":L"), P$35) -> 0 | Q64: =SUMIFS(INDIRECT("C"&$C$70&":C"), INDIRECT("B"&$C$70&":B"), ">="&$A64, INDIRECT("B"&$C$70&":B"), "<"&$A65, INDIRECT("R"&$C$70&":R"), Q$35) -> 0 | R64: =SUMIFS(INDIRECT("C"&$C$70&":C"), INDIRECT("A"&$C$70&":A"), ">="&$A64, INDIRECT("A"&$C$70&":A"), "<"&$A65, INDIRECT("R"&$C$70&":R"), "<>公司認股", INDIRECT("R"&$C$70&":R"), "<>") -> 0 | S64: =IFERROR(__xludf.DUMMYFUNCTION("TEXTJOIN("", "", TRUE, FILTER(INDIRECT(""U""&$C$70&"":U""), INDIRECT(""H""&$C$70&"":H"") <>"""", INDIRECT(""B""&$C$70&"":B"") >= $A31, INDIRECT(""B""&$C$70&"":B"") <$A32))"),"#N/A") -> #N/A
A65: 46357 | B65: =SUMIFS(INDIRECT("C"&$C$70&":C"), INDIRECT("B"&$C$70&":B"), ">="&$A65, INDIRECT("B"&$C$70&":B"), "<"&$A66, INDIRECT("H"&$C$70&":H"), "<>") - SUM($C65:$R65) -> 0 | C65: =SUMIFS(INDIRECT("C"&$C$70&":C"), INDIRECT("B"&$C$70&":B"), ">="&$A65, INDIRECT("B"&$C$70&":B"), "<"&$A66, INDIRECT("J"&$C$70&":J"), C$35) -> 0 | D65: =SUMIFS(INDIRECT("C"&$C$70&":C"), INDIRECT("B"&$C$70&":B"), ">="&$A65, INDIRECT("B"&$C$70&":B"), "<"&$A66, INDIRECT("N"&$C$70&":N"), D$35) -> 0 | E65: =SUMIFS(INDIRECT("C"&$C$70&":C"), INDIRECT("B"&$C$70&":B"), ">="&$A65, INDIRECT("B"&$C$70&":B"), "<"&$A66, INDIRECT("N"&$C$70&":N"), E$35) -> 0 | F65: =SUMIFS(INDIRECT("C"&$C$70&":C"), INDIRECT("B"&$C$70&":B"), ">="&$A65, INDIRECT("B"&$C$70&":B"), "<"&$A66, INDIRECT("K"&$C$70&":K"), "文心1房貸代繳") + SUMIFS(INDIRECT("C"&$C$70&":C"), INDIRECT("B"&$C$70&":B"), ">="&$A65, INDIRECT("B"&$C$70&":B"), "<"&$A66, INDIRECT("K"&$C$70&":K"), "租屋") -> 0 | G65: =SUMIFS(INDIRECT("C"&$C$70&":C"), INDIRECT("B"&$C$70&":B"), ">="&$A65, INDIRECT("B"&$C$70&":B"), "<"&$A66, INDIRECT("K"&$C$70&":K"), G$35) -> 0 | H65: =SUMIFS(INDIRECT("C"&$C$70&":C"), INDIRECT("B"&$C$70&":B"), ">="&$A65, INDIRECT("B"&$C$70&":B"), "<"&$A66, INDIRECT("K"&$C$70&":K"), H$35) -> 0 | I65: =SUMIFS(INDIRECT("C"&$C$70&":C"), INDIRECT("B"&$C$70&":B"), ">="&$A65, INDIRECT("B"&$C$70&":B"), "<"&$A66, INDIRECT("K"&$C$70&":K"), I$35) -> 0 | J65: =SUMIFS(INDIRECT("C"&$C$70&":C"), INDIRECT("B"&$C$70&":B"), ">="&$A65, INDIRECT("B"&$C$70&":B"), "<"&$A66, INDIRECT("K"&$C$70&":K"), J$35) -> 0 | K65: =SUMIFS(INDIRECT("C"&$C$70&":C"), INDIRECT("B"&$C$70&":B"), ">="&$A65, INDIRECT("B"&$C$70&":B"), "<"&$A66, INDIRECT("L"&$C$70&":L"), K$35) -> 0 | L65: =SUMIFS(INDIRECT("C"&$C$70&":C"), INDIRECT("B"&$C$70&":B"), ">="&$A65, INDIRECT("B"&$C$70&":B"), "<"&$A66, INDIRECT("L"&$C$70&":L"), L$35) -> 0 | M65: =SUMIFS(INDIRECT("C"&$C$70&":C"), INDIRECT("B"&$C$70&":B"), ">="&$A65, INDIRECT("B"&$C$70&":B"), "<"&$A66, INDIRECT("L"&$C$70&":L"), M$35) -> 0 | N65: =SUMIFS(INDIRECT("C"&$C$70&":C"), INDIRECT("B"&$C$70&":B"), ">="&$A65, INDIRECT("B"&$C$70&":B"), "<"&$A66, INDIRECT("L"&$C$70&":L"), N$35) -> 0 | O65: =SUMIFS(INDIRECT("C"&$C$70&":C"), INDIRECT("B"&$C$70&":B"), ">="&$A65, INDIRECT("B"&$C$70&":B"), "<"&$A66, INDIRECT("L"&$C$70&":L"), O$35) -> 0 | P65: =SUMIFS(INDIRECT("C"&$C$70&":C"), INDIRECT("B"&$C$70&":B"), ">="&$A65, INDIRECT("B"&$C$70&":B"), "<"&$A66, INDIRECT("L"&$C$70&":L"), P$35) -> 0 | Q65: =SUMIFS(INDIRECT("C"&$C$70&":C"), INDIRECT("B"&$C$70&":B"), ">="&$A65, INDIRECT("B"&$C$70&":B"), "<"&$A66, INDIRECT("R"&$C$70&":R"), Q$35) -> 0 | R65: =SUMIFS(INDIRECT("C"&$C$70&":C"), INDIRECT("A"&$C$70&":A"), ">="&$A65, INDIRECT("A"&$C$70&":A"), "<"&$A66, INDIRECT("R"&$C$70&":R"), "<>公司認股", INDIRECT("R"&$C$70&":R"), "<>") -> 0 | S65: =IFERROR(__xludf.DUMMYFUNCTION("TEXTJOIN("", "", TRUE, FILTER(INDIRECT(""U""&$C$70&"":U""), INDIRECT(""H""&$C$70&"":H"") <>"""", INDIRECT(""B""&$C$70&"":B"") >= $A32, INDIRECT(""B""&$C$70&"":B"") <$A33))"),"#N/A") -> #N/A
A67: Params | B67: Source_title_row_index | C67: Source_start_row_index | D67: Source_row_count | E67: Source_row_end_index
B68: =MATCH("時間戳記",'收支紀錄'!$A:$A, 0) -> 1 | C68: =$B$68+1 -> 2 | D68: {=COUNT(INDIRECT("'收支紀錄'!A"&$C$68&":A"))} -> 1666 | E68: =C68+D68 - 1 -> 1667
B69: Cal_title_row_index | C69: Cal_start_row_index | D69: Cal_row_count | E69: Cal_row_end_index | F69: Source_Cal_Row_Gap
B70: =MATCH("時間戳記",$A:$A, 0) -> 75 | C70: =$B$70+1 -> 76 | D70: {=COUNT(INDIRECT("A"&$C$70&":A"))} -> 1666 | E70: =C70+D70 - 1 -> 1741 | F70: =E68+(C70-C68)-E70 -> 0
C71: Source_Cal_Start_Gap
C72: =C70-C68 -> 74
A74: 資料來源
A75: 時間戳記 | B75: Date(Cal.) | C75: 金額(NTD) | D75: 輸入日期 | E75: 收入主分類 | F75: 工作選項 | G75: 其他業外選項 | H75: 支出主分類 | I75: 食品酒水選項 | J75: 日常生活選項 | K75: 房屋支出選項 | L75: 行車交通選項 | M75: 休閒娛樂選項 | N75: 稅金保險選項 | O75: 醫療費用選項 | P75: 進修學習選項 | Q75: 人情往來 | R75: 其他投資選項 | S75: 備註 | T75: 是否紀錄於總表? | U75: $金額+備註(by公式)
A76: =IFERROR(__xludf.DUMMYFUNCTION("INDIRECT(""'收支紀錄'!A""&TO_TEXT(ROW()-$C$72))"),45487.51281059028) -> 45487.513 | B76: =IFERROR(__xludf.DUMMYFUNCTION("IF(ISBLANK(D76), """", IF(ISDATE(D76), D76, IF(D76=""今天"", A76, IF(D76=""昨天 (-1 day)"", A76-1, IF(D76=""前天 (-2 days)"", A76-2, IF(D76=""明天 (+1 day)"", A76+1, DATE(LEFT(D76,4), MID(D76,5,2), RIGHT(D76,2))))))))"),45487.0) -> 45487 | C76: =IFERROR(__xludf.DUMMYFUNCTION("INDIRECT(""'收支紀錄'!C""&TO_TEXT(ROW()-$C$72))"),82.0) -> 82 | D76: =IFERROR(__xludf.DUMMYFUNCTION("INDIRECT(""'收支紀錄'!D""&TO_TEXT(ROW()-$C$72))"),45487.0) -> 45487 | E76: =IFERROR(__xludf.DUMMYFUNCTION("INDIRECT(""'收支紀錄'!E""&TO_TEXT(ROW()-$C$72))"),"") | F76: =IFERROR(__xludf.DUMMYFUNCTION("INDIRECT(""'收支紀錄'!F""&TO_TEXT(ROW()-$C$72))"),"") | G76: =IFERROR(__xludf.DUMMYFUNCTION("INDIRECT(""'收支紀錄'!G""&TO_TEXT(ROW()-$C$72))"),"") | H76: =IFERROR(__xludf.DUMMYFUNCTION("INDIRECT(""'收支紀錄'!H""&TO_TEXT(ROW()-$C$72))"),"行車交通") -> 行車交通 | I76: =IFERROR(__xludf.DUMMYFUNCTION("INDIRECT(""'收支紀錄'!I""&TO_TEXT(ROW()-$C$72))"),"") | J76: =IFERROR(__xludf.DUMMYFUNCTION("INDIRECT(""'收支紀錄'!J""&TO_TEXT(ROW()-$C$72))"),"") | K76: =IFERROR(__xludf.DUMMYFUNCTION("INDIRECT(""'收支紀錄'!K""&TO_TEXT(ROW()-$C$72))"),"") | L76: =IFERROR(__xludf.DUMMYFUNCTION("INDIRECT(""'收支紀錄'!L""&TO_TEXT(ROW()-$C$72))"),"火車費") -> 火車費 | M76: =IFERROR(__xludf.DUMMYFUNCTION("INDIRECT(""'收支紀錄'!M""&TO_TEXT(ROW()-$C$72))"),"") | N76: =IFERROR(__xludf.DUMMYFUNCTION("INDIRECT(""'收支紀錄'!N""&TO_TEXT(ROW()-$C$72))"),"") | O76: =IFERROR(__xludf.DUMMYFUNCTION("INDIRECT(""'收支紀錄'!O""&TO_TEXT(ROW()-$C$72))"),"") | P76: =IFERROR(__xludf.DUMMYFUNCTION("INDIRECT(""'收支紀錄'!P""&TO_TEXT(ROW()-$C$72))"),"") | Q76: =IFERROR(__xludf.DUMMYFUNCTION("INDIRECT(""'收支紀錄'!Q""&TO_TEXT(ROW()-$C$72))"),"") | R76: =IFERROR(__xludf.DUMMYFUNCTION("INDIRECT(""'收支紀錄'!R""&TO_TEXT(ROW()-$C$72))"),"") | S76: =IFERROR(__xludf.DUMMYFUNCTION("INDIRECT(""'收支紀錄'!S""&TO_TEXT(ROW()-$C$72))"),"") | T76: =IFERROR(__xludf.DUMMYFUNCTION("INDIRECT(""'收支紀錄'!T""&TO_TEXT(ROW()-$C$72))"),"") | U76: =IFERROR(__xludf.DUMMYFUNCTION("IF(T76=""是"",TEXTJOIN("""", TRUE, ""$"", TO_TEXT(C76), S76),"""")"),"")
A77: =IFERROR(__xludf.DUMMYFUNCTION("INDIRECT(""'收支紀錄'!A""&TO_TEXT(ROW()-$C$72))"),45487.51320346065) -> 45487.513 | B77: =IFERROR(__xludf.DUMMYFUNCTION("IF(ISBLANK(D77), """", IF(ISDATE(D77), D77, IF(D77=""今天"", A77, IF(D77=""昨天 (-1 day)"", A77-1, IF(D77=""前天 (-2 days)"", A77-2, IF(D77=""明天 (+1 day)"", A77+1, DATE(LEFT(D77,4), MID(D77,5,2), RIGHT(D77,2))))))))"),45487.0) -> 45487 | C77: =IFERROR(__xludf.DUMMYFUNCTION("INDIRECT(""'收支紀錄'!C""&TO_TEXT(ROW()-$C$72))"),148.0) -> 148 | D77: =IFERROR(__xludf.DUMMYFUNCTION("INDIRECT(""'收支紀錄'!D""&TO_TEXT(ROW()-$C$72))"),45487.0) -> 45487 | E77: =IFERROR(__xludf.DUMMYFUNCTION("INDIRECT(""'收支紀錄'!E""&TO_TEXT(ROW()-$C$72))"),"") | F77: =IFERROR(__xludf.DUMMYFUNCTION("INDIRECT(""'收支紀錄'!F""&TO_TEXT(ROW()-$C$72))"),"") | G77: =IFERROR(__xludf.DUMMYFUNCTION("INDIRECT(""'收支紀錄'!G""&TO_TEXT(ROW()-$C$72))"),"") | H77: =IFERROR(__xludf.DUMMYFUNCTION("INDIRECT(""'收支紀錄'!H""&TO_TEXT(ROW()-$C$72))"),"行車交通") -> 行車交通 | I77: =IFERROR(__xludf.DUMMYFUNCTION("INDIRECT(""'收支紀錄'!I""&TO_TEXT(ROW()-$C$72))"),"") | J77: =IFERROR(__xludf.DUMMYFUNCTION("INDIRECT(""'收支紀錄'!J""&TO_TEXT(ROW()-$C$72))"),"") | K77: =IFERROR(__xludf.DUMMYFUNCTION("INDIRECT(""'收支紀錄'!K""&TO_TEXT(ROW()-$C$72))"),"") | L77: =IFERROR(__xludf.DUMMYFUNCTION("INDIRECT(""'收支紀錄'!L""&TO_TEXT(ROW()-$C$72))"),"加油") -> 加油 | M77: =IFERROR(__xludf.DUMMYFUNCTION("INDIRECT(""'收支紀錄'!M""&TO_TEXT(ROW()-$C$72))"),"") | N77: =IFERROR(__xludf.DUMMYFUNCTION("INDIRECT(""'收支紀錄'!N""&TO_TEXT(ROW()-$C$72))"),"") | O77: =IFERROR(__xludf.DUMMYFUNCTION("INDIRECT(""'收支紀錄'!O""&TO_TEXT(ROW()-$C$72))"),"") | P77: =IFERROR(__xludf.DUMMYFUNCTION("INDIRECT(""'收支紀錄'!P""&TO_TEXT(ROW()-$C$72))"),"") | Q77: =IFERROR(__xludf.DUMMYFUNCTION("INDIRECT(""'收支紀錄'!Q""&TO_TEXT(ROW()-$C$72))"),"") | R77: =IFERROR(__xludf.DUMMYFUNCTION("INDIRECT(""'收支紀錄'!R""&TO_TEXT(ROW()-$C$72))"),"") | S77: =IFERROR(__xludf.DUMMYFUNCTION("INDIRECT(""'收支紀錄'!S""&TO_TEXT(ROW()-$C$72))"),"") | T77: =IFERROR(__xludf.DUMMYFUNCTION("INDIRECT(""'收支紀錄'!T""&TO_TEXT(ROW()-$C$72))"),"") | U77: =IFERROR(__xludf.DUMMYFUNCTION("IF(T77=""是"",TEXTJOIN("""", TRUE, ""$"", TO_TEXT(C77), S77),"""")"),"")
A78: =IFERROR(__xludf.DUMMYFUNCTION("INDIRECT(""'收支紀錄'!A""&TO_TEXT(ROW()-$C$72))"),45487.513509895834) -> 45487.514 | B78: =IFERROR(__xludf.DUMMYFUNCTION("IF(ISBLANK(D78), """", IF(ISDATE(D78), D78, IF(D78=""今天"", A78, IF(D78=""昨天 (-1 day)"", A78-1, IF(D78=""前天 (-2 days)"", A78-2, IF(D78=""明天 (+1 day)"", A78+1, DATE(LEFT(D78,4), MID(D78,5,2), RIGHT(D78,2))))))))"),45487.0) -> 45487 | C78: =IFERROR(__xludf.DUMMYFUNCTION("INDIRECT(""'收支紀錄'!C""&TO_TEXT(ROW()-$C$72))"),100.0) -> 100 | D78: =IFERROR(__xludf.DUMMYFUNCTION("INDIRECT(""'收支紀錄'!D""&TO_TEXT(ROW()-$C$72))"),45487.0) -> 45487 | E78: =IFERROR(__xludf.DUMMYFUNCTION("INDIRECT(""'收支紀錄'!E""&TO_TEXT(ROW()-$C$72))"),"") | F78: =IFERROR(__xludf.DUMMYFUNCTION("INDIRECT(""'收支紀錄'!F""&TO_TEXT(ROW()-$C$72))"),"") | G78: =IFERROR(__xludf.DUMMYFUNCTION("INDIRECT(""'收支紀錄'!G""&TO_TEXT(ROW()-$C$72))"),"") | H78: =IFERROR(__xludf.DUMMYFUNCTION("INDIRECT(""'收支紀錄'!H""&TO_TEXT(ROW()-$C$72))"),"休閒娛樂") -> 休閒娛樂 | I78: =IFERROR(__xludf.DUMMYFUNCTION("INDIRECT(""'收支紀錄'!I""&TO_TEXT(ROW()-$C$72))"),"") | J78: =IFERROR(__xludf.DUMMYFUNCTION("INDIRECT(""'收支紀錄'!J""&TO_TEXT(ROW()-$C$72))"),"") | K78: =IFERROR(__xludf.DUMMYFUNCTION("INDIRECT(""'收支紀錄'!K""&TO_TEXT(ROW()-$C$72))"),"") | L78: =IFERROR(__xludf.DUMMYFUNCTION("INDIRECT(""'收支紀錄'!L""&TO_TEXT(ROW()-$C$72))"),"") | M78: =IFERROR(__xludf.DUMMYFUNCTION("INDIRECT(""'收支紀錄'!M""&TO_TEXT(ROW()-$C$72))"),"運動健身") -> 運動健身 | N78: =IFERROR(__xludf.DUMMYFUNCTION("INDIRECT(""'收支紀錄'!N""&TO_TEXT(ROW()-$C$72))"),"") | O78: =IFERROR(__xludf.DUMMYFUNCTION("INDIRECT(""'收支紀錄'!O""&TO_TEXT(ROW()-$C$72))"),"") | P78: =IFERROR(__xludf.DUMMYFUNCTION("INDIRECT(""'收支紀錄'!P""&TO_TEXT(ROW()-$C$72))"),"") | Q78: =IFERROR(__xludf.DUMMYFUNCTION("INDIRECT(""'收支紀錄'!Q""&TO_TEXT(ROW()-$C$72))"),"") | R78: =IFERROR(__xludf.DUMMYFUNCTION("INDIRECT(""'收支紀錄'!R""&TO_TEXT(ROW()-$C$72))"),"") | S78: =IFERROR(__xludf.DUMMYFUNCTION("INDIRECT(""'收支紀錄'!S""&TO_TEXT(ROW()-$C$72))"),"") | T78: =IFERROR(__xludf.DUMMYFUNCTION("INDIRECT(""'收支紀錄'!T""&TO_TEXT(ROW()-$C$72))"),"") | U78: =IFERROR(__xludf.DUMMYFUNCTION("IF(T78=""是"",TEXTJOIN("""", TRUE, ""$"", TO_TEXT(C78), S78),"""")"),"") | V78: =IFERROR(__xludf.DUMMYFUNCTION("IF(T78=""是"",TEXTJOIN("""", TRUE, ""$"", TO_TEXT(D78), S78),"""")"),"")
A79: =IFERROR(__xludf.DUMMYFUNCTION("INDIRECT(""'收支紀錄'!A""&TO_TEXT(ROW()-$C$72))"),45487.513733125) -> 45487.514 | B79: =IFERROR(__xludf.DUMMYFUNCTION("IF(ISBLANK(D79), """", IF(ISDATE(D79), D79, IF(D79=""今天"", A79, IF(D79=""昨天 (-1 day)"", A79-1, IF(D79=""前天 (-2 days)"", A79-2, IF(D79=""明天 (+1 day)"", A79+1, DATE(LEFT(D79,4), MID(D79,5,2), RIGHT(D79,2))))))))"),45487.0) -> 45487 | C79: =IFERROR(__xludf.DUMMYFUNCTION("INDIRECT(""'收支紀錄'!C""&TO_TEXT(ROW()-$C$72))"),60.0) -> 60 | D79: =IFERROR(__xludf.DUMMYFUNCTION("INDIRECT(""'收支紀錄'!D""&TO_TEXT(ROW()-$C$72))"),45487.0) -> 45487 | E79: =IFERROR(__xludf.DUMMYFUNCTION("INDIRECT(""'收支紀錄'!E""&TO_TEXT(ROW()-$C$72))"),"") | F79: =IFERROR(__xludf.DUMMYFUNCTION("INDIRECT(""'收支紀錄'!F""&TO_TEXT(ROW()-$C$72))"),"") | G79: =IFERROR(__xludf.DUMMYFUNCTION("INDIRECT(""'收支紀錄'!G""&TO_TEXT(ROW()-$C$72))"),"") | H79: =IFERROR(__xludf.DUMMYFUNCTION("INDIRECT(""'收支紀錄'!H""&TO_TEXT(ROW()-$C$72))"),"日常生活") -> 日常生活 | I79: =IFERROR(__xludf.DUMMYFUNCTION("INDIRECT(""'收支紀錄'!I""&TO_TEXT(ROW()-$C$72))"),"") | J79: =IFERROR(__xludf.DUMMYFUNCTION("INDIRECT(""'收支紀錄'!J""&TO_TEXT(ROW()-$C$72))"),"日常用品") -> 日常用品 | K79: =IFERROR(__xludf.DUMMYFUNCTION("INDIRECT(""'收支紀錄'!K""&TO_TEXT(ROW()-$C$72))"),"") | L79: =IFERROR(__xludf.DUMMYFUNCTION("INDIRECT(""'收支紀錄'!L""&TO_TEXT(ROW()-$C$72))"),"") | M79: =IFERROR(__xludf.DUMMYFUNCTION("INDIRECT(""'收支紀錄'!M""&TO_TEXT(ROW()-$C$72))"),"") | N79: =IFERROR(__xludf.DUMMYFUNCTION("INDIRECT(""'收支紀錄'!N""&TO_TEXT(ROW()-$C$72))"),"") | O79: =IFERROR(__xludf.DUMMYFUNCTION("INDIRECT(""'收支紀錄'!O""&TO_TEXT(ROW()-$C$72))"),"") | P79: =IFERROR(__xludf.DUMMYFUNCTION("INDIRECT(""'收支紀錄'!P""&TO_TEXT(ROW()-$C$72))"),"") | Q79: =IFERROR(__xludf.DUMMYFUNCTION("INDIRECT(""'收支紀錄'!Q""&TO_TEXT(ROW()-$C$72))"),"") | R79: =IFERROR(__xludf.DUMMYFUNCTION("INDIRECT(""'收支紀錄'!R""&TO_TEXT(ROW()-$C$72))"),"") | S79: =IFERROR(__xludf.DUMMYFUNCTION("INDIRECT(""'收支紀錄'!S""&TO_TEXT(ROW()-$C$72))"),"") | T79: =IFERROR(__xludf.DUMMYFUNCTION("INDIRECT(""'收支紀錄'!T""&TO_TEXT(ROW()-$C$72))"),"") | U79: =IFERROR(__xludf.DUMMYFUNCTION("IF(T79=""是"",TEXTJOIN("""", TRUE, ""$"", TO_TEXT(C79), S79),"""")"),"")
A80: =IFERROR(__xludf.DUMMYFUNCTION("INDIRECT(""'收支紀錄'!A""&TO_TEXT(ROW()-$C$72))"),45487.51392228009) -> 45487.514 | B80: =IFERROR(__xludf.DUMMYFUNCTION("IF(ISBLANK(D80), """", IF(ISDATE(D80), D80, IF(D80=""今天"", A80, IF(D80=""昨天 (-1 day)"", A80-1, IF(D80=""前天 (-2 days)"", A80-2, IF(D80=""明天 (+1 day)"", A80+1, DATE(LEFT(D80,4), MID(D80,5,2), RIGHT(D80,2))))))))"),45487.0) -> 45487 | C80: =IFERROR(__xludf.DUMMYFUNCTION("INDIRECT(""'收支紀錄'!C""&TO_TEXT(ROW()-$C$72))"),77.0) -> 77 | D80: =IFERROR(__xludf.DUMMYFUNCTION("INDIRECT(""'收支紀錄'!D""&TO_TEXT(ROW()-$C$72))"),45487.0) -> 45487 | E80: =IFERROR(__xludf.DUMMYFUNCTION("INDIRECT(""'收支紀錄'!E""&TO_TEXT(ROW()-$C$72))"),"") | F80: =IFERROR(__xludf.DUMMYFUNCTION("INDIRECT(""'收支紀錄'!F""&TO_TEXT(ROW()-$C$72))"),"") | G80: =IFERROR(__xludf.DUMMYFUNCTION("INDIRECT(""'收支紀錄'!G""&TO_TEXT(ROW()-$C$72))"),"") | H80: =IFERROR(__xludf.DUMMYFUNCTION("INDIRECT(""'收支紀錄'!H""&TO_TEXT(ROW()-$C$72))"),"行車交通") -> 行車交通 | I80: =IFERROR(__xludf.DUMMYFUNCTION("INDIRECT(""'收支紀錄'!I""&TO_TEXT(ROW()-$C$72))"),"") | J80: =IFERROR(__xludf.DUMMYFUNCTION("INDIRECT(""'收支紀錄'!J""&TO_TEXT(ROW()-$C$72))"),"") | K80: =IFERROR(__xludf.DUMMYFUNCTION("INDIRECT(""'收支紀錄'!K""&TO_TEXT(ROW()-$C$72))"),"") | L80: =IFERROR(__xludf.DUMMYFUNCTION("INDIRECT(""'收支紀錄'!L""&TO_TEXT(ROW()-$C$72))"),"火車費") -> 火車費 | M80: =IFERROR(__xludf.DUMMYFUNCTION("INDIRECT(""'收支紀錄'!M""&TO_TEXT(ROW()-$C$72))"),"") | N80: =IFERROR(__xludf.DUMMYFUNCTION("INDIRECT(""'收支紀錄'!N""&TO_TEXT(ROW()-$C$72))"),"") | O80: =IFERROR(__xludf.DUMMYFUNCTION("INDIRECT(""'收支紀錄'!O""&TO_TEXT(ROW()-$C$72))"),"") | P80: =IFERROR(__xludf.DUMMYFUNCTION("INDIRECT(""'收支紀錄'!P""&TO_TEXT(ROW()-$C$72))"),"") | Q80: =IFERROR(__xludf.DUMMYFUNCTION("INDIRECT(""'收支紀錄'!Q""&TO_TEXT(ROW()-$C$72))"),"") | R80: =IFERROR(__xludf.DUMMYFUNCTION("INDIRECT(""'收支紀錄'!R""&TO_TEXT(ROW()-$C$72))"),"") | S80: =IFERROR(__xludf.DUMMYFUNCTION("INDIRECT(""'收支紀錄'!S""&TO_TEXT(ROW()-$C$72))"),"") | T80: =IFERROR(__xludf.DUMMYFUNCTION("INDIRECT(""'收支紀錄'!T""&TO_TEXT(ROW()-$C$72))"),"") | U80: =IFERROR(__xludf.DUMMYFUNCTION("IF(T80=""是"",TEXTJOIN("""", TRUE, ""$"", TO_TEXT(C80), S80),"""")"),"")
A81: =IFERROR(__xludf.DUMMYFUNCTION("INDIRECT(""'收支紀錄'!A""&TO_TEXT(ROW()-$C$72))"),45487.51412695602) -> 45487.514 | B81: =IFERROR(__xludf.DUMMYFUNCTION("IF(ISBLANK(D81), """", IF(ISDATE(D81), D81, IF(D81=""今天"", A81, IF(D81=""昨天 (-1 day)"", A81-1, IF(D81=""前天 (-2 days)"", A81-2, IF(D81=""明天 (+1 day)"", A81+1, DATE(LEFT(D81,4), MID(D81,5,2), RIGHT(D81,2))))))))"),45487.0) -> 45487 | C81: =IFERROR(__xludf.DUMMYFUNCTION("INDIRECT(""'收支紀錄'!C""&TO_TEXT(ROW()-$C$72))"),380.0) -> 380 | D81: =IFERROR(__xludf.DUMMYFUNCTION("INDIRECT(""'收支紀錄'!D""&TO_TEXT(ROW()-$C$72))"),45487.0) -> 45487 | E81: =IFERROR(__xludf.DUMMYFUNCTION("INDIRECT(""'收支紀錄'!E""&TO_TEXT(ROW()-$C$72))"),"") | F81: =IFERROR(__xludf.DUMMYFUNCTION("INDIRECT(""'收支紀錄'!F""&TO_TEXT(ROW()-$C$72))"),"") | G81: =IFERROR(__xludf.DUMMYFUNCTION("INDIRECT(""'收支紀錄'!G""&TO_TEXT(ROW()-$C$72))"),"") | H81: =IFERROR(__xludf.DUMMYFUNCTION("INDIRECT(""'收支紀錄'!H""&TO_TEXT(ROW()-$C$72))"),"食品酒水") -> 食品酒水 | I81: =IFERROR(__xludf.DUMMYFUNCTION("INDIRECT(""'收支紀錄'!I""&TO_TEXT(ROW()-$C$72))"),"早餐") -> 早餐 | J81: =IFERROR(__xludf.DUMMYFUNCTION("INDIRECT(""'收支紀錄'!J""&TO_TEXT(ROW()-$C$72))"),"") | K81: =IFERROR(__xludf.DUMMYFUNCTION("INDIRECT(""'收支紀錄'!K""&TO_TEXT(ROW()-$C$72))"),"") | L81: =IFERROR(__xludf.DUMMYFUNCTION("INDIRECT(""'收支紀錄'!L""&TO_TEXT(ROW()-$C$72))"),"") | M81: =IFERROR(__xludf.DUMMYFUNCTION("INDIRECT(""'收支紀錄'!M""&TO_TEXT(ROW()-$C$72))"),"") | N81: =IFERROR(__xludf.DUMMYFUNCTION("INDIRECT(""'收支紀錄'!N""&TO_TEXT(ROW()-$C$72))"),"") | O81: =IFERROR(__xludf.DUMMYFUNCTION("INDIRECT(""'收支紀錄'!O""&TO_TEXT(ROW()-$C$72))"),"") | P81: =IFERROR(__xludf.DUMMYFUNCTION("INDIRECT(""'收支紀錄'!P""&TO_TEXT(ROW()-$C$72))"),"") | Q81: =IFERROR(__xludf.DUMMYFUNCTION("INDIRECT(""'收支紀錄'!Q""&TO_TEXT(ROW()-$C$72))"),"") | R81: =IFERROR(__xludf.DUMMYFUNCTION("INDIRECT(""'收支紀錄'!R""&TO_TEXT(ROW()-$C$72))"),"") | S81: =IFERROR(__xludf.DUMMYFUNCTION("INDIRECT(""'收支紀錄'!S""&TO_TEXT(ROW()-$C$72))"),"") | T81: =IFERROR(__xludf.DUMMYFUNCTION("INDIRECT(""'收支紀錄'!T""&TO_TEXT(ROW()-$C$72))"),"") | U81: =IFERROR(__xludf.DUMMYFUNCTION("IF(T81=""是"",TEXTJOIN("""", TRUE, ""$"", TO_TEXT(C81), S81),"""")"),"")
A82: =IFERROR(__xludf.DUMMYFUNCTION("INDIRECT(""'收支紀錄'!A""&TO_TEXT(ROW()-$C$72))"),45487.51453959491) -> 45487.515 | B82: =IFERROR(__xludf.DUMMYFUNCTION("IF(ISBLANK(D82), """", IF(ISDATE(D82), D82, IF(D82=""今天"", A82, IF(D82=""昨天 (-1 day)"", A82-1, IF(D82=""前天 (-2 days)"", A82-2, IF(D82=""明天 (+1 day)"", A82+1, DATE(LEFT(D82,4), MID(D82,5,2), RIGHT(D82,2))))))))"),45487.0) -> 45487 | C82: =IFERROR(__xludf.DUMMYFUNCTION("INDIRECT(""'收支紀錄'!C""&TO_TEXT(ROW()-$C$72))"),510.0) -> 510 | D82: =IFERROR(__xludf.DUMMYFUNCTION("INDIRECT(""'收支紀錄'!D""&TO_TEXT(ROW()-$C$72))"),45487.0) -> 45487 | E82: =IFERROR(__xludf.DUMMYFUNCTION("INDIRECT(""'收支紀錄'!E""&TO_TEXT(ROW()-$C$72))"),"") | F82: =IFERROR(__xludf.DUMMYFUNCTION("INDIRECT(""'收支紀錄'!F""&TO_TEXT(ROW()-$C$72))"),"") | G82: =IFERROR(__xludf.DUMMYFUNCTION("INDIRECT(""'收支紀錄'!G""&TO_TEXT(ROW()-$C$72))"),"") | H82: =IFERROR(__xludf.DUMMYFUNCTION("INDIRECT(""'收支紀錄'!H""&TO_TEXT(ROW()-$C$72))"),"食品酒水") -> 食品酒水 | I82: =IFERROR(__xludf.DUMMYFUNCTION("INDIRECT(""'收支紀錄'!I""&TO_TEXT(ROW()-$C$72))"),"晚餐") -> 晚餐 | J82: =IFERROR(__xludf.DUMMYFUNCTION("INDIRECT(""'收支紀錄'!J""&TO_TEXT(ROW()-$C$72))"),"") | K82: =IFERROR(__xludf.DUMMYFUNCTION("INDIRECT(""'收支紀錄'!K""&TO_TEXT(ROW()-$C$72))"),"") | L82: =IFERROR(__xludf.DUMMYFUNCTION("INDIRECT(""'收支紀錄'!L""&TO_TEXT(ROW()-$C$72))"),"") | M82: =IFERROR(__xludf.DUMMYFUNCTION("INDIRECT(""'收支紀錄'!M""&TO_TEXT(ROW()-$C$72))"),"") | N82: =IFERROR(__xludf.DUMMYFUNCTION("INDIRECT(""'收支紀錄'!N""&TO_TEXT(ROW()-$C$72))"),"") | O82: =IFERROR(__xludf.DUMMYFUNCTION("INDIRECT(""'收支紀錄'!O""&TO_TEXT(ROW()-$C$72))"),"") | P82: =IFERROR(__xludf.DUMMYFUNCTION("INDIRECT(""'收支紀錄'!P""&TO_TEXT(ROW()-$C$72))"),"") | Q82: =IFERROR(__xludf.DUMMYFUNCTION("INDIRECT(""'收支紀錄'!Q""&TO_TEXT(ROW()-$C$72))"),"") | R82: =IFERROR(__xludf.DUMMYFUNCTION("INDIRECT(""'收支紀錄'!R""&TO_TEXT(ROW()-$C$72))"),"") | S82: =IFERROR(__xludf.DUMMYFUNCTION("INDIRECT(""'收支紀錄'!S""&TO_TEXT(ROW()-$C$72))"),"") | T82: =IFERROR(__xludf.DUMMYFUNCTION("INDIRECT(""'收支紀錄'!T""&TO_TEXT(ROW()-$C$72))"),"") | U82: =IFERROR(__xludf.DUMMYFUNCTION("IF(T82=""是"",TEXTJOIN("""", TRUE, ""$"", TO_TEXT(C82), S82),"""")"),"")
A83: =IFERROR(__xludf.DUMMYFUNCTION("INDIRECT(""'收支紀錄'!A""&TO_TEXT(ROW()-$C$72))"),45487.51480895834) -> 45487.515 | B83: =IFERROR(__xludf.DUMMYFUNCTION("IF(ISBLANK(D83), """", IF(ISDATE(D83), D83, IF(D83=""今天"", A83, IF(D83=""昨天 (-1 day)"", A83-1, IF(D83=""前天 (-2 days)"", A83-2, IF(D83=""明天 (+1 day)"", A83+1, DATE(LEFT(D83,4), MID(D83,5,2), RIGHT(D83,2))))))))"),45487.0) -> 45487 | C83: =IFERROR(__xludf.DUMMYFUNCTION("INDIRECT(""'收支紀錄'!C""&TO_TEXT(ROW()-$C$72))"),359.0) -> 359 | D83: =IFERROR(__xludf.DUMMYFUNCTION("INDIRECT(""'收支紀錄'!D""&TO_TEXT(ROW()-$C$72))"),45487.0) -> 45487 | E83: =IFERROR(__xludf.DUMMYFUNCTION("INDIRECT(""'收支紀錄'!E""&TO_TEXT(ROW()-$C$72))"),"") | F83: =IFERROR(__xludf.DUMMYFUNCTION("INDIRECT(""'收支紀錄'!F""&TO_TEXT(ROW()-$C$72))"),"") | G83: =IFERROR(__xludf.DUMMYFUNCTION("INDIRECT(""'收支紀錄'!G""&TO_TEXT(ROW()-$C$72))"),"") | H83: =IFERROR(__xludf.DUMMYFUNCTION("INDIRECT(""'收支紀錄'!H""&TO_TEXT(ROW()-$C$72))"),"日常生活") -> 日常生活 | I83: =IFERROR(__xludf.DUMMYFUNCTION("INDIRECT(""'收支紀錄'!I""&TO_TEXT(ROW()-$C$72))"),"") | J83: =IFERROR(__xludf.DUMMYFUNCTION("INDIRECT(""'收支紀錄'!J""&TO_TEXT(ROW()-$C$72))"),"日常用品") -> 日常用品 | K83: =IFERROR(__xludf.DUMMYFUNCTION("INDIRECT(""'收支紀錄'!K""&TO_TEXT(ROW()-$C$72))"),"") | L83: =IFERROR(__xludf.DUMMYFUNCTION("INDIRECT(""'收支紀錄'!L""&TO_TEXT(ROW()-$C$72))"),"") | M83: =IFERROR(__xludf.DUMMYFUNCTION("INDIRECT(""'收支紀錄'!M""&TO_TEXT(ROW()-$C$72))"),"") | N83: =IFERROR(__xludf.DUMMYFUNCTION("INDIRECT(""'收支紀錄'!N""&TO_TEXT(ROW()-$C$72))"),"") | O83: =IFERROR(__xludf.DUMMYFUNCTION("INDIRECT(""'收支紀錄'!O""&TO_TEXT(ROW()-$C$72))"),"") | P83: =IFERROR(__xludf.DUMMYFUNCTION("INDIRECT(""'收支紀錄'!P""&TO_TEXT(ROW()-$C$72))"),"") | Q83: =IFERROR(__xludf.DUMMYFUNCTION("INDIRECT(""'收支紀錄'!Q""&TO_TEXT(ROW()-$C$72))"),"") | R83: =IFERROR(__xludf.DUMMYFUNCTION("INDIRECT(""'收支紀錄'!R""&TO_TEXT(ROW()-$C$72))"),"") | S83: =IFERROR(__xludf.DUMMYFUNCTION("INDIRECT(""'收支紀錄'!S""&TO_TEXT(ROW()-$C$72))"),"") | T83: =IFERROR(__xludf.DUMMYFUNCTION("INDIRECT(""'收支紀錄'!T""&TO_TEXT(ROW()-$C$72))"),"") | U83: =IFERROR(__xludf.DUMMYFUNCTION("IF(T83=""是"",TEXTJOIN("""", TRUE, ""$"", TO_TEXT(C83), S83),"""")"),"")
A84: =IFERROR(__xludf.DUMMYFUNCTION("INDIRECT(""'收支紀錄'!A""&TO_TEXT(ROW()-$C$72))"),45487.51497402778) -> 45487.515 | B84: =IFERROR(__xludf.DUMMYFUNCTION("IF(ISBLANK(D84), """", IF(ISDATE(D84), D84, IF(D84=""今天"", A84, IF(D84=""昨天 (-1 day)"", A84-1, IF(D84=""前天 (-2 days)"", A84-2, IF(D84=""明天 (+1 day)"", A84+1, DATE(LEFT(D84,4), MID(D84,5,2), RIGHT(D84,2))))))))"),45487.0) -> 45487 | C84: =IFERROR(__xludf.DUMMYFUNCTION("INDIRECT(""'收支紀錄'!C""&TO_TEXT(ROW()-$C$72))"),233.0) -> 233 | D84: =IFERROR(__xludf.DUMMYFUNCTION("INDIRECT(""'收支紀錄'!D""&TO_TEXT(ROW()-$C$72))"),45487.0) -> 45487 | E84: =IFERROR(__xludf.DUMMYFUNCTION("INDIRECT(""'收支紀錄'!E""&TO_TEXT(ROW()-$C$72))"),"") | F84: =IFERROR(__xludf.DUMMYFUNCTION("INDIRECT(""'收支紀錄'!F""&TO_TEXT(ROW()-$C$72))"),"") | G84: =IFERROR(__xludf.DUMMYFUNCTION("INDIRECT(""'收支紀錄'!G""&TO_TEXT(ROW()-$C$72))"),"") | H84: =IFERROR(__xludf.DUMMYFUNCTION("INDIRECT(""'收支紀錄'!H""&TO_TEXT(ROW()-$C$72))"),"日常生活") -> 日常生活 | I84: =IFERROR(__xludf.DUMMYFUNCTION("INDIRECT(""'收支紀錄'!I""&TO_TEXT(ROW()-$C$72))"),"") | J84: =IFERROR(__xludf.DUMMYFUNCTION("INDIRECT(""'收支紀錄'!J""&TO_TEXT(ROW()-$C$72))"),"日常用品") -> 日常用品 | K84: =IFERROR(__xludf.DUMMYFUNCTION("INDIRECT(""'收支紀錄'!K""&TO_TEXT(ROW()-$C$72))"),"") | L84: =IFERROR(__xludf.DUMMYFUNCTION("INDIRECT(""'收支紀錄'!L""&TO_TEXT(ROW()-$C$72))"),"") | M84: =IFERROR(__xludf.DUMMYFUNCTION("INDIRECT(""'收支紀錄'!M""&TO_TEXT(ROW()-$C$72))"),"") | N84: =IFERROR(__xludf.DUMMYFUNCTION("INDIRECT(""'收支紀錄'!N""&TO_TEXT(ROW()-$C$72))"),"") | O84: =IFERROR(__xludf.DUMMYFUNCTION("INDIRECT(""'收支紀錄'!O""&TO_TEXT(ROW()-$C$72))"),"") | P84: =IFERROR(__xludf.DUMMYFUNCTION("INDIRECT(""'收支紀錄'!P""&TO_TEXT(ROW()-$C$72))"),"") | Q84: =IFERROR(__xludf.DUMMYFUNCTION("INDIRECT(""'收支紀錄'!Q""&TO_TEXT(ROW()-$C$72))"),"") | R84: =IFERROR(__xludf.DUMMYFUNCTION("INDIRECT(""'收支紀錄'!R""&TO_TEXT(ROW()-$C$72))"),"") | S84: =IFERROR(__xludf.DUMMYFUNCTION("INDIRECT(""'收支紀錄'!S""&TO_TEXT(ROW()-$C$72))"),"") | T84: =IFERROR(__xludf.DUMMYFUNCTION("INDIRECT(""'收支紀錄'!T""&TO_TEXT(ROW()-$C$72))"),"") | U84: =IFERROR(__xludf.DUMMYFUNCTION("IF(T84=""是"",TEXTJOIN("""", TRUE, ""$"", TO_TEXT(C84), S84),"""")"),"")
A85: =IFERROR(__xludf.DUMMYFUNCTION("INDIRECT(""'收支紀錄'!A""&TO_TEXT(ROW()-$C$72))"),45487.51516045139) -> 45487.515 | B85: =IFERROR(__xludf.DUMMYFUNCTION("IF(ISBLANK(D85), """", IF(ISDATE(D85), D85, IF(D85=""今天"", A85, IF(D85=""昨天 (-1 day)"", A85-1, IF(D85=""前天 (-2 days)"", A85-2, IF(D85=""明天 (+1 day)"", A85+1, DATE(LEFT(D85,4), MID(D85,5,2), RIGHT(D85,2))))))))"),45487.0) -> 45487 | C85: =IFERROR(__xludf.DUMMYFUNCTION("INDIRECT(""'收支紀錄'!C""&TO_TEXT(ROW()-$C$72))"),20.0) -> 20 | D85: =IFERROR(__xludf.DUMMYFUNCTION("INDIRECT(""'收支紀錄'!D""&TO_TEXT(ROW()-$C$72))"),45487.0) -> 45487 | E85: =IFERROR(__xludf.DUMMYFUNCTION("INDIRECT(""'收支紀錄'!E""&TO_TEXT(ROW()-$C$72))"),"") | F85: =IFERROR(__xludf.DUMMYFUNCTION("INDIRECT(""'收支紀錄'!F""&TO_TEXT(ROW()-$C$72))"),"") | G85: =IFERROR(__xludf.DUMMYFUNCTION("INDIRECT(""'收支紀錄'!G""&TO_TEXT(ROW()-$C$72))"),"") | H85: =IFERROR(__xludf.DUMMYFUNCTION("INDIRECT(""'收支紀錄'!H""&TO_TEXT(ROW()-$C$72))"),"行車交通") -> 行車交通 | I85: =IFERROR(__xludf.DUMMYFUNCTION("INDIRECT(""'收支紀錄'!I""&TO_TEXT(ROW()-$C$72))"),"") | J85: =IFERROR(__xludf.DUMMYFUNCTION("INDIRECT(""'收支紀錄'!J""&TO_TEXT(ROW()-$C$72))"),"") | K85: =IFERROR(__xludf.DUMMYFUNCTION("INDIRECT(""'收支紀錄'!K""&TO_TEXT(ROW()-$C$72))"),"") | L85: =IFERROR(__xludf.DUMMYFUNCTION("INDIRECT(""'收支紀錄'!L""&TO_TEXT(ROW()-$C$72))"),"停車") -> 停車 | M85: =IFERROR(__xludf.DUMMYFUNCTION("INDIRECT(""'收支紀錄'!M""&TO_TEXT(ROW()-$C$72))"),"") | N85: =IFERROR(__xludf.DUMMYFUNCTION("INDIRECT(""'收支紀錄'!N""&TO_TEXT(ROW()-$C$72))"),"") | O85: =IFERROR(__xludf.DUMMYFUNCTION("INDIRECT(""'收支紀錄'!O""&TO_TEXT(ROW()-$C$72))"),"") | P85: =IFERROR(__xludf.DUMMYFUNCTION("INDIRECT(""'收支紀錄'!P""&TO_TEXT(ROW()-$C$72))"),"") | Q85: =IFERROR(__xludf.DUMMYFUNCTION("INDIRECT(""'收支紀錄'!Q""&TO_TEXT(ROW()-$C$72))"),"") | R85: =IFERROR(__xludf.DUMMYFUNCTION("INDIRECT(""'收支紀錄'!R""&TO_TEXT(ROW()-$C$72))"),"") | S85: =IFERROR(__xludf.DUMMYFUNCTION("INDIRECT(""'收支紀錄'!S""&TO_TEXT(ROW()-$C$72))"),"") | T85: =IFERROR(__xludf.DUMMYFUNCTION("INDIRECT(""'收支紀錄'!T""&TO_TEXT(ROW()-$C$72))"),"") | U85: =IFERROR(__xludf.DUMMYFUNCTION("IF(T85=""是"",TEXTJOIN("""", TRUE, ""$"", TO_TEXT(C85), S85),"""")"),"")
A86: =IFERROR(__xludf.DUMMYFUNCTION("INDIRECT(""'收支紀錄'!A""&TO_TEXT(ROW()-$C$72))"),45487.51531038195) -> 45487.515 | B86: =IFERROR(__xludf.DUMMYFUNCTION("IF(ISBLANK(D86), """", IF(ISDATE(D86), D86, IF(D86=""今天"", A86, IF(D86=""昨天 (-1 day)"", A86-1, IF(D86=""前天 (-2 days)"", A86-2, IF(D86=""明天 (+1 day)"", A86+1, DATE(LEFT(D86,4), MID(D86,5,2), RIGHT(D86,2))))))))"),45487.0) -> 45487 | C86: =IFERROR(__xludf.DUMMYFUNCTION("INDIRECT(""'收支紀錄'!C""&TO_TEXT(ROW()-$C$72))"),78.0) -> 78 | D86: =IFERROR(__xludf.DUMMYFUNCTION("INDIRECT(""'收支紀錄'!D""&TO_TEXT(ROW()-$C$72))"),45487.0) -> 45487 | E86: =IFERROR(__xludf.DUMMYFUNCTION("INDIRECT(""'收支紀錄'!E""&TO_TEXT(ROW()-$C$72))"),"") | F86: =IFERROR(__xludf.DUMMYFUNCTION("INDIRECT(""'收支紀錄'!F""&TO_TEXT(ROW()-$C$72))"),"") | G86: =IFERROR(__xludf.DUMMYFUNCTION("INDIRECT(""'收支紀錄'!G""&TO_TEXT(ROW()-$C$72))"),"") | H86: =IFERROR(__xludf.DUMMYFUNCTION("INDIRECT(""'收支紀錄'!H""&TO_TEXT(ROW()-$C$72))"),"食品酒水") -> 食品酒水 | I86: =IFERROR(__xludf.DUMMYFUNCTION("INDIRECT(""'收支紀錄'!I""&TO_TEXT(ROW()-$C$72))"),"早餐") -> 早餐 | J86: =IFERROR(__xludf.DUMMYFUNCTION("INDIRECT(""'收支紀錄'!J""&TO_TEXT(ROW()-$C$72))"),"") | K86: =IFERROR(__xludf.DUMMYFUNCTION("INDIRECT(""'收支紀錄'!K""&TO_TEXT(ROW()-$C$72))"),"") | L86: =IFERROR(__xludf.DUMMYFUNCTION("INDIRECT(""'收支紀錄'!L""&TO_TEXT(ROW()-$C$72))"),"") | M86: =IFERROR(__xludf.DUMMYFUNCTION("INDIRECT(""'收支紀錄'!M""&TO_TEXT(ROW()-$C$72))"),"") | N86: =IFERROR(__xludf.DUMMYFUNCTION("INDIRECT(""'收支紀錄'!N""&TO_TEXT(ROW()-$C$72))"),"") | O86: =IFERROR(__xludf.DUMMYFUNCTION("INDIRECT(""'收支紀錄'!O""&TO_TEXT(ROW()-$C$72))"),"") | P86: =IFERROR(__xludf.DUMMYFUNCTION("INDIRECT(""'收支紀錄'!P""&TO_TEXT(ROW()-$C$72))"),"") | Q86: =IFERROR(__xludf.DUMMYFUNCTION("INDIRECT(""'收支紀錄'!Q""&TO_TEXT(ROW()-$C$72))"),"") | R86: =IFERROR(__xludf.DUMMYFUNCTION("INDIRECT(""'收支紀錄'!R""&TO_TEXT(ROW()-$C$72))"),"") | S86: =IFERROR(__xludf.DUMMYFUNCTION("INDIRECT(""'收支紀錄'!S""&TO_TEXT(ROW()-$C$72))"),"") | T86: =IFERROR(__xludf.DUMMYFUNCTION("INDIRECT(""'收支紀錄'!T""&TO_TEXT(ROW()-$C$72))"),"") | U86: =IFERROR(__xludf.DUMMYFUNCTION("IF(T86=""是"",TEXTJOIN("""", TRUE, ""$"", TO_TEXT(C86), S86),"""")"),"")
A87: =IFERROR(__xludf.DUMMYFUNCTION("INDIRECT(""'收支紀錄'!A""&TO_TEXT(ROW()-$C$72))"),45487.51546059028) -> 45487.515 | B87: =IFERROR(__xludf.DUMMYFUNCTION("IF(ISBLANK(D87), """", IF(ISDATE(D87), D87, IF(D87=""今天"", A87, IF(D87=""昨天 (-1 day)"", A87-1, IF(D87=""前天 (-2 days)"", A87-2, IF(D87=""明天 (+1 day)"", A87+1, DATE(LEFT(D87,4), MID(D87,5,2), RIGHT(D87,2))))))))"),45487.0) -> 45487 | C87: =IFERROR(__xludf.DUMMYFUNCTION("INDIRECT(""'收支紀錄'!C""&TO_TEXT(ROW()-$C$72))"),515.0) -> 515 | D87: =IFERROR(__xludf.DUMMYFUNCTION("INDIRECT(""'收支紀錄'!D""&TO_TEXT(ROW()-$C$72))"),45487.0) -> 45487 | E87: =IFERROR(__xludf.DUMMYFUNCTION("INDIRECT(""'收支紀錄'!E""&TO_TEXT(ROW()-$C$72))"),"") | F87: =IFERROR(__xludf.DUMMYFUNCTION("INDIRECT(""'收支紀錄'!F""&TO_TEXT(ROW()-$C$72))"),"") | G87: =IFERROR(__xludf.DUMMYFUNCTION("INDIRECT(""'收支紀錄'!G""&TO_TEXT(ROW()-$C$72))"),"") | H87: =IFERROR(__xludf.DUMMYFUNCTION("INDIRECT(""'收支紀錄'!H""&TO_TEXT(ROW()-$C$72))"),"休閒娛樂") -> 休閒娛樂 | I87: =IFERROR(__xludf.DUMMYFUNCTION("INDIRECT(""'收支紀錄'!I""&TO_TEXT(ROW()-$C$72))"),"") | J87: =IFERROR(__xludf.DUMMYFUNCTION("INDIRECT(""'收支紀錄'!J""&TO_TEXT(ROW()-$C$72))"),"") | K87: =IFERROR(__xludf.DUMMYFUNCTION("INDIRECT(""'收支紀錄'!K""&TO_TEXT(ROW()-$C$72))"),"") | L87: =IFERROR(__xludf.DUMMYFUNCTION("INDIRECT(""'收支紀錄'!L""&TO_TEXT(ROW()-$C$72))"),"") | M87: =IFERROR(__xludf.DUMMYFUNCTION("INDIRECT(""'收支紀錄'!M""&TO_TEXT(ROW()-$C$72))"),"公司福利金") -> 公司福利金 | N87: =IFERROR(__xludf.DUMMYFUNCTION("INDIRECT(""'收支紀錄'!N""&TO_TEXT(ROW()-$C$72))"),"") | O87: =IFERROR(__xludf.DUMMYFUNCTION("INDIRECT(""'收支紀錄'!O""&TO_TEXT(ROW()-$C$72))"),"") | P87: =IFERROR(__xludf.DUMMYFUNCTION("INDIRECT(""'收支紀錄'!P""&TO_TEXT(ROW()-$C$72))"),"") | Q87: =IFERROR(__xludf.DUMMYFUNCTION("INDIRECT(""'收支紀錄'!Q""&TO_TEXT(ROW()-$C$72))"),"") | R87: =IFERROR(__xludf.DUMMYFUNCTION("INDIRECT(""'收支紀錄'!R""&TO_TEXT(ROW()-$C$72))"),"") | S87: =IFERROR(__xludf.DUMMYFUNCTION("INDIRECT(""'收支紀錄'!S""&TO_TEXT(ROW()-$C$72))"),"") | T87: =IFERROR(__xludf.DUMMYFUNCTION("INDIRECT(""'收支紀錄'!T""&TO_TEXT(ROW()-$C$72))"),"") | U87: =IFERROR(__xludf.DUMMYFUNCTION("IF(T87=""是"",TEXTJOIN("""", TRUE, ""$"", TO_TEXT(C87), S87),"""")"),"")
A88: =IFERROR(__xludf.DUMMYFUNCTION("INDIRECT(""'收支紀錄'!A""&TO_TEXT(ROW()-$C$72))"),45487.51565479167) -> 45487.516 | B88: =IFERROR(__xludf.DUMMYFUNCTION("IF(ISBLANK(D88), """", IF(ISDATE(D88), D88, IF(D88=""今天"", A88, IF(D88=""昨天 (-1 day)"", A88-1, IF(D88=""前天 (-2 days)"", A88-2, IF(D88=""明天 (+1 day)"", A88+1, DATE(LEFT(D88,4), MID(D88,5,2), RIGHT(D88,2))))))))"),45487.0) -> 45487 | C88: =IFERROR(__xludf.DUMMYFUNCTION("INDIRECT(""'收支紀錄'!C""&TO_TEXT(ROW()-$C$72))"),1303.0) -> 1303 | D88: =IFERROR(__xludf.DUMMYFUNCTION("INDIRECT(""'收支紀錄'!D""&TO_TEXT(ROW()-$C$72))"),45487.0) -> 45487 | E88: =IFERROR(__xludf.DUMMYFUNCTION("INDIRECT(""'收支紀錄'!E""&TO_TEXT(ROW()-$C$72))"),"") | F88: =IFERROR(__xludf.DUMMYFUNCTION("INDIRECT(""'收支紀錄'!F""&TO_TEXT(ROW()-$C$72))"),"") | G88: =IFERROR(__xludf.DUMMYFUNCTION("INDIRECT(""'收支紀錄'!G""&TO_TEXT(ROW()-$C$72))"),"") | H88: =IFERROR(__xludf.DUMMYFUNCTION("INDIRECT(""'收支紀錄'!H""&TO_TEXT(ROW()-$C$72))"),"食品酒水") -> 食品酒水 | I88: =IFERROR(__xludf.DUMMYFUNCTION("INDIRECT(""'收支紀錄'!I""&TO_TEXT(ROW()-$C$72))"),"前月公司餐費扣款") -> 前月公司餐費扣款 | J88: =IFERROR(__xludf.DUMMYFUNCTION("INDIRECT(""'收支紀錄'!J""&TO_TEXT(ROW()-$C$72))"),"") | K88: =IFERROR(__xludf.DUMMYFUNCTION("INDIRECT(""'收支紀錄'!K""&TO_TEXT(ROW()-$C$72))"),"") | L88: =IFERROR(__xludf.DUMMYFUNCTION("INDIRECT(""'收支紀錄'!L""&TO_TEXT(ROW()-$C$72))"),"") | M88: =IFERROR(__xludf.DUMMYFUNCTION("INDIRECT(""'收支紀錄'!M""&TO_TEXT(ROW()-$C$72))"),"") | N88: =IFERROR(__xludf.DUMMYFUNCTION("INDIRECT(""'收支紀錄'!N""&TO_TEXT(ROW()-$C$72))"),"") | O88: =IFERROR(__xludf.DUMMYFUNCTION("INDIRECT(""'收支紀錄'!O""&TO_TEXT(ROW()-$C$72))"),"") | P88: =IFERROR(__xludf.DUMMYFUNCTION("INDIRECT(""'收支紀錄'!P""&TO_TEXT(ROW()-$C$72))"),"") | Q88: =IFERROR(__xludf.DUMMYFUNCTION("INDIRECT(""'收支紀錄'!Q""&TO_TEXT(ROW()-$C$72))"),"") | R88: =IFERROR(__xludf.DUMMYFUNCTION("INDIRECT(""'收支紀錄'!R""&TO_TEXT(ROW()-$C$72))"),"") | S88: =IFERROR(__xludf.DUMMYFUNCTION("INDIRECT(""'收支紀錄'!S""&TO_TEXT(ROW()-$C$72))"),"") | T88: =IFERROR(__xludf.DUMMYFUNCTION("INDIRECT(""'收支紀錄'!T""&TO_TEXT(ROW()-$C$72))"),"") | U88: =IFERROR(__xludf.DUMMYFUNCTION("IF(T88=""是"",TEXTJOIN("""", TRUE, ""$"", TO_TEXT(C88), S88),"""")"),"") | V88: =IFERROR(__xludf.DUMMYFUNCTION("IF(T88=""是"",TEXTJOIN("""", TRUE, ""$"", TO_TEXT(D88), S88),"""")"),"")
A89: =IFERROR(__xludf.DUMMYFUNCTION("INDIRECT(""'收支紀錄'!A""&TO_TEXT(ROW()-$C$72))"),45487.515843229165) -> 45487.516 | B89: =IFERROR(__xludf.DUMMYFUNCTION("IF(ISBLANK(D89), """", IF(ISDATE(D89), D89, IF(D89=""今天"", A89, IF(D89=""昨天 (-1 day)"", A89-1, IF(D89=""前天 (-2 days)"", A89-2, IF(D89=""明天 (+1 day)"", A89+1, DATE(LEFT(D89,4), MID(D89,5,2), RIGHT(D89,2))))))))"),45487.0) -> 45487 | C89: =IFERROR(__xludf.DUMMYFUNCTION("INDIRECT(""'收支紀錄'!C""&TO_TEXT(ROW()-$C$72))"),180.0) -> 180 | D89: =IFERROR(__xludf.DUMMYFUNCTION("INDIRECT(""'收支紀錄'!D""&TO_TEXT(ROW()-$C$72))"),45487.0) -> 45487 | E89: =IFERROR(__xludf.DUMMYFUNCTION("INDIRECT(""'收支紀錄'!E""&TO_TEXT(ROW()-$C$72))"),"") | F89: =IFERROR(__xludf.DUMMYFUNCTION("INDIRECT(""'收支紀錄'!F""&TO_TEXT(ROW()-$C$72))"),"") | G89: =IFERROR(__xludf.DUMMYFUNCTION("INDIRECT(""'收支紀錄'!G""&TO_TEXT(ROW()-$C$72))"),"") | H89: =IFERROR(__xludf.DUMMYFUNCTION("INDIRECT(""'收支紀錄'!H""&TO_TEXT(ROW()-$C$72))"),"休閒娛樂") -> 休閒娛樂 | I89: =IFERROR(__xludf.DUMMYFUNCTION("INDIRECT(""'收支紀錄'!I""&TO_TEXT(ROW()-$C$72))"),"") | J89: =IFERROR(__xludf.DUMMYFUNCTION("INDIRECT(""'收支紀錄'!J""&TO_TEXT(ROW()-$C$72))"),"") | K89: =IFERROR(__xludf.DUMMYFUNCTION("INDIRECT(""'收支紀錄'!K""&TO_TEXT(ROW()-$C$72))"),"") | L89: =IFERROR(__xludf.DUMMYFUNCTION("INDIRECT(""'收支紀錄'!L""&TO_TEXT(ROW()-$C$72))"),"") | M89: =IFERROR(__xludf.DUMMYFUNCTION("INDIRECT(""'收支紀錄'!M""&TO_TEXT(ROW()-$C$72))"),"運動健身") -> 運動健身 | N89: =IFERROR(__xludf.DUMMYFUNCTION("INDIRECT(""'收支紀錄'!N""&TO_TEXT(ROW()-$C$72))"),"") | O89: =IFERROR(__xludf.DUMMYFUNCTION("INDIRECT(""'收支紀錄'!O""&TO_TEXT(ROW()-$C$72))"),"") | P89: =IFERROR(__xludf.DUMMYFUNCTION("INDIRECT(""'收支紀錄'!P""&TO_TEXT(ROW()-$C$72))"),"") | Q89: =IFERROR(__xludf.DUMMYFUNCTION("INDIRECT(""'收支紀錄'!Q""&TO_TEXT(ROW()-$C$72))"),"") | R89: =IFERROR(__xludf.DUMMYFUNCTION("INDIRECT(""'收支紀錄'!R""&TO_TEXT(ROW()-$C$72))"),"") | S89: =IFERROR(__xludf.DUMMYFUNCTION("INDIRECT(""'收支紀錄'!S""&TO_TEXT(ROW()-$C$72))"),"") | T89: =IFERROR(__xludf.DUMMYFUNCTION("INDIRECT(""'收支紀錄'!T""&TO_TEXT(ROW()-$C$72))"),"") | U89: =IFERROR(__xludf.DUMMYFUNCTION("IF(T89=""是"",TEXTJOIN("""", TRUE, ""$"", TO_TEXT(C89), S89),"""")"),"") | V89: =IFERROR(__xludf.DUMMYFUNCTION("IF(T89=""是"",TEXTJOIN("""", TRUE, ""$"", TO_TEXT(D89), S89),"""")"),"")
A90: =IFERROR(__xludf.DUMMYFUNCTION("INDIRECT(""'收支紀錄'!A""&TO_TEXT(ROW()-$C$72))"),45487.516022094904) -> 45487.516 | B90: =IFERROR(__xludf.DUMMYFUNCTION("IF(ISBLANK(D90), """", IF(ISDATE(D90), D90, IF(D90=""今天"", A90, IF(D90=""昨天 (-1 day)"", A90-1, IF(D90=""前天 (-2 days)"", A90-2, IF(D90=""明天 (+1 day)"", A90+1, DATE(LEFT(D90,4), MID(D90,5,2), RIGHT(D90,2))))))))"),45487.0) -> 45487 | C90: =IFERROR(__xludf.DUMMYFUNCTION("INDIRECT(""'收支紀錄'!C""&TO_TEXT(ROW()-$C$72))"),520.0) -> 520 | D90: =IFERROR(__xludf.DUMMYFUNCTION("INDIRECT(""'收支紀錄'!D""&TO_TEXT(ROW()-$C$72))"),45487.0) -> 45487 | E90: =IFERROR(__xludf.DUMMYFUNCTION("INDIRECT(""'收支紀錄'!E""&TO_TEXT(ROW()-$C$72))"),"") | F90: =IFERROR(__xludf.DUMMYFUNCTION("INDIRECT(""'收支紀錄'!F""&TO_TEXT(ROW()-$C$72))"),"") | G90: =IFERROR(__xludf.DUMMYFUNCTION("INDIRECT(""'收支紀錄'!G""&TO_TEXT(ROW()-$C$72))"),"") | H90: =IFERROR(__xludf.DUMMYFUNCTION("INDIRECT(""'收支紀錄'!H""&TO_TEXT(ROW()-$C$72))"),"食品酒水") -> 食品酒水 | I90: =IFERROR(__xludf.DUMMYFUNCTION("INDIRECT(""'收支紀錄'!I""&TO_TEXT(ROW()-$C$72))"),"晚餐") -> 晚餐 | J90: =IFERROR(__xludf.DUMMYFUNCTION("INDIRECT(""'收支紀錄'!J""&TO_TEXT(ROW()-$C$72))"),"") | K90: =IFERROR(__xludf.DUMMYFUNCTION("INDIRECT(""'收支紀錄'!K""&TO_TEXT(ROW()-$C$72))"),"") | L90: =IFERROR(__xludf.DUMMYFUNCTION("INDIRECT(""'收支紀錄'!L""&TO_TEXT(ROW()-$C$72))"),"") | M90: =IFERROR(__xludf.DUMMYFUNCTION("INDIRECT(""'收支紀錄'!M""&TO_TEXT(ROW()-$C$72))"),"") | N90: =IFERROR(__xludf.DUMMYFUNCTION("INDIRECT(""'收支紀錄'!N""&TO_TEXT(ROW()-$C$72))"),"") | O90: =IFERROR(__xludf.DUMMYFUNCTION("INDIRECT(""'收支紀錄'!O""&TO_TEXT(ROW()-$C$72))"),"") | P90: =IFERROR(__xludf.DUMMYFUNCTION("INDIRECT(""'收支紀錄'!P""&TO_TEXT(ROW()-$C$72))"),"") | Q90: =IFERROR(__xludf.DUMMYFUNCTION("INDIRECT(""'收支紀錄'!Q""&TO_TEXT(ROW()-$C$72))"),"") | R90: =IFERROR(__xludf.DUMMYFUNCTION("INDIRECT(""'收支紀錄'!R""&TO_TEXT(ROW()-$C$72))"),"") | S90: =IFERROR(__xludf.DUMMYFUNCTION("INDIRECT(""'收支紀錄'!S""&TO_TEXT(ROW()-$C$72))"),"") | T90: =IFERROR(__xludf.DUMMYFUNCTION("INDIRECT(""'收支紀錄'!T""&TO_TEXT(ROW()-$C$72))"),"") | U90: =IFERROR(__xludf.DUMMYFUNCTION("IF(T90=""是"",TEXTJOIN("""", TRUE, ""$"", TO_TEXT(C90), S90),"""")"),"")
A91: =IFERROR(__xludf.DUMMYFUNCTION("INDIRECT(""'收支紀錄'!A""&TO_TEXT(ROW()-$C$72))"),45487.51618914352) -> 45487.516 | B91: =IFERROR(__xludf.DUMMYFUNCTION("IF(ISBLANK(D91), """", IF(ISDATE(D91), D91, IF(D91=""今天"", A91, IF(D91=""昨天 (-1 day)"", A91-1, IF(D91=""前天 (-2 days)"", A91-2, IF(D91=""明天 (+1 day)"", A91+1, DATE(LEFT(D91,4), MID(D91,5,2), RIGHT(D91,2))))))))"),45487.0) -> 45487 | C91: =IFERROR(__xludf.DUMMYFUNCTION("INDIRECT(""'收支紀錄'!C""&TO_TEXT(ROW()-$C$72))"),211.0) -> 211 | D91: =IFERROR(__xludf.DUMMYFUNCTION("INDIRECT(""'收支紀錄'!D""&TO_TEXT(ROW()-$C$72))"),45487.0) -> 45487 | E91: =IFERROR(__xludf.DUMMYFUNCTION("INDIRECT(""'收支紀錄'!E""&TO_TEXT(ROW()-$C$72))"),"") | F91: =IFERROR(__xludf.DUMMYFUNCTION("INDIRECT(""'收支紀錄'!F""&TO_TEXT(ROW()-$C$72))"),"") | G91: =IFERROR(__xludf.DUMMYFUNCTION("INDIRECT(""'收支紀錄'!G""&TO_TEXT(ROW()-$C$72))"),"") | H91: =IFERROR(__xludf.DUMMYFUNCTION("INDIRECT(""'收支紀錄'!H""&TO_TEXT(ROW()-$C$72))"),"食品酒水") -> 食品酒水 | I91: =IFERROR(__xludf.DUMMYFUNCTION("INDIRECT(""'收支紀錄'!I""&TO_TEXT(ROW()-$C$72))"),"食材") -> 食材 | J91: =IFERROR(__xludf.DUMMYFUNCTION("INDIRECT(""'收支紀錄'!J""&TO_TEXT(ROW()-$C$72))"),"") | K91: =IFERROR(__xludf.DUMMYFUNCTION("INDIRECT(""'收支紀錄'!K""&TO_TEXT(ROW()-$C$72))"),"") | L91: =IFERROR(__xludf.DUMMYFUNCTION("INDIRECT(""'收支紀錄'!L""&TO_TEXT(ROW()-$C$72))"),"") | M91: =IFERROR(__xludf.DUMMYFUNCTION("INDIRECT(""'收支紀錄'!M""&TO_TEXT(ROW()-$C$72))"),"") | N91: =IFERROR(__xludf.DUMMYFUNCTION("INDIRECT(""'收支紀錄'!N""&TO_TEXT(ROW()-$C$72))"),"") | O91: =IFERROR(__xludf.DUMMYFUNCTION("INDIRECT(""'收支紀錄'!O""&TO_TEXT(ROW()-$C$72))"),"") | P91: =IFERROR(__xludf.DUMMYFUNCTION("INDIRECT(""'收支紀錄'!P""&TO_TEXT(ROW()-$C$72))"),"") | Q91: =IFERROR(__xludf.DUMMYFUNCTION("INDIRECT(""'收支紀錄'!Q""&TO_TEXT(ROW()-$C$72))"),"") | R91: =IFERROR(__xludf.DUMMYFUNCTION("INDIRECT(""'收支紀錄'!R""&TO_TEXT(ROW()-$C$72))"),"") | S91: =IFERROR(__xludf.DUMMYFUNCTION("INDIRECT(""'收支紀錄'!S""&TO_TEXT(ROW()-$C$72))"),"") | T91: =IFERROR(__xludf.DUMMYFUNCTION("INDIRECT(""'收支紀錄'!T""&TO_TEXT(ROW()-$C$72))"),"") | U91: =IFERROR(__xludf.DUMMYFUNCTION("IF(T91=""是"",TEXTJOIN("""", TRUE, ""$"", TO_TEXT(C91), S91),"""")"),"")
A92: =IFERROR(__xludf.DUMMYFUNCTION("INDIRECT(""'收支紀錄'!A""&TO_TEXT(ROW()-$C$72))"),45487.516362442126) -> 45487.516 | B92: =IFERROR(__xludf.DUMMYFUNCTION("IF(ISBLANK(D92), """", IF(ISDATE(D92), D92, IF(D92=""今天"", A92, IF(D92=""昨天 (-1 day)"", A92-1, IF(D92=""前天 (-2 days)"", A92-2, IF(D92=""明天 (+1 day)"", A92+1, DATE(LEFT(D92,4), MID(D92,5,2), RIGHT(D92,2))))))))"),45487.0) -> 45487 | C92: =IFERROR(__xludf.DUMMYFUNCTION("INDIRECT(""'收支紀錄'!C""&TO_TEXT(ROW()-$C$72))"),50.0) -> 50 | D92: =IFERROR(__xludf.DUMMYFUNCTION("INDIRECT(""'收支紀錄'!D""&TO_TEXT(ROW()-$C$72))"),45487.0) -> 45487 | E92: =IFERROR(__xludf.DUMMYFUNCTION("INDIRECT(""'收支紀錄'!E""&TO_TEXT(ROW()-$C$72))"),"") | F92: =IFERROR(__xludf.DUMMYFUNCTION("INDIRECT(""'收支紀錄'!F""&TO_TEXT(ROW()-$C$72))"),"") | G92: =IFERROR(__xludf.DUMMYFUNCTION("INDIRECT(""'收支紀錄'!G""&TO_TEXT(ROW()-$C$72))"),"") | H92: =IFERROR(__xludf.DUMMYFUNCTION("INDIRECT(""'收支紀錄'!H""&TO_TEXT(ROW()-$C$72))"),"食品酒水") -> 食品酒水 | I92: =IFERROR(__xludf.DUMMYFUNCTION("INDIRECT(""'收支紀錄'!I""&TO_TEXT(ROW()-$C$72))"),"宵夜") -> 宵夜 | J92: =IFERROR(__xludf.DUMMYFUNCTION("INDIRECT(""'收支紀錄'!J""&TO_TEXT(ROW()-$C$72))"),"") | K92: =IFERROR(__xludf.DUMMYFUNCTION("INDIRECT(""'收支紀錄'!K""&TO_TEXT(ROW()-$C$72))"),"") | L92: =IFERROR(__xludf.DUMMYFUNCTION("INDIRECT(""'收支紀錄'!L""&TO_TEXT(ROW()-$C$72))"),"") | M92: =IFERROR(__xludf.DUMMYFUNCTION("INDIRECT(""'收支紀錄'!M""&TO_TEXT(ROW()-$C$72))"),"") | N92: =IFERROR(__xludf.DUMMYFUNCTION("INDIRECT(""'收支紀錄'!N""&TO_TEXT(ROW()-$C$72))"),"") | O92: =IFERROR(__xludf.DUMMYFUNCTION("INDIRECT(""'收支紀錄'!O""&TO_TEXT(ROW()-$C$72))"),"") | P92: =IFERROR(__xludf.DUMMYFUNCTION("INDIRECT(""'收支紀錄'!P""&TO_TEXT(ROW()-$C$72))"),"") | Q92: =IFERROR(__xludf.DUMMYFUNCTION("INDIRECT(""'收支紀錄'!Q""&TO_TEXT(ROW()-$C$72))"),"") | R92: =IFERROR(__xludf.DUMMYFUNCTION("INDIRECT(""'收支紀錄'!R""&TO_TEXT(ROW()-$C$72))"),"") | S92: =IFERROR(__xludf.DUMMYFUNCTION("INDIRECT(""'收支紀錄'!S""&TO_TEXT(ROW()-$C$72))"),"") | T92: =IFERROR(__xludf.DUMMYFUNCTION("INDIRECT(""'收支紀錄'!T""&TO_TEXT(ROW()-$C$72))"),"") | U92: =IFERROR(__xludf.DUMMYFUNCTION("IF(T92=""是"",TEXTJOIN("""", TRUE, ""$"", TO_TEXT(C92), S92),"""")"),"")
A93: =IFERROR(__xludf.DUMMYFUNCTION("INDIRECT(""'收支紀錄'!A""&TO_TEXT(ROW()-$C$72))"),45487.51651212963) -> 45487.517 | B93: =IFERROR(__xludf.DUMMYFUNCTION("IF(ISBLANK(D93), """", IF(ISDATE(D93), D93, IF(D93=""今天"", A93, IF(D93=""昨天 (-1 day)"", A93-1, IF(D93=""前天 (-2 days)"", A93-2, IF(D93=""明天 (+1 day)"", A93+1, DATE(LEFT(D93,4), MID(D93,5,2), RIGHT(D93,2))))))))"),45487.0) -> 45487 | C93: =IFERROR(__xludf.DUMMYFUNCTION("INDIRECT(""'收支紀錄'!C""&TO_TEXT(ROW()-$C$72))"),100.0) -> 100 | D93: =IFERROR(__xludf.DUMMYFUNCTION("INDIRECT(""'收支紀錄'!D""&TO_TEXT(ROW()-$C$72))"),45487.0) -> 45487 | E93: =IFERROR(__xludf.DUMMYFUNCTION("INDIRECT(""'收支紀錄'!E""&TO_TEXT(ROW()-$C$72))"),"") | F93: =IFERROR(__xludf.DUMMYFUNCTION("INDIRECT(""'收支紀錄'!F""&TO_TEXT(ROW()-$C$72))"),"") | G93: =IFERROR(__xludf.DUMMYFUNCTION("INDIRECT(""'收支紀錄'!G""&TO_TEXT(ROW()-$C$72))"),"") | H93: =IFERROR(__xludf.DUMMYFUNCTION("INDIRECT(""'收支紀錄'!H""&TO_TEXT(ROW()-$C$72))"),"休閒娛樂") -> 休閒娛樂 | I93: =IFERROR(__xludf.DUMMYFUNCTION("INDIRECT(""'收支紀錄'!I""&TO_TEXT(ROW()-$C$72))"),"") | J93: =IFERROR(__xludf.DUMMYFUNCTION("INDIRECT(""'收支紀錄'!J""&TO_TEXT(ROW()-$C$72))"),"") | K93: =IFERROR(__xludf.DUMMYFUNCTION("INDIRECT(""'收支紀錄'!K""&TO_TEXT(ROW()-$C$72))"),"") | L93: =IFERROR(__xludf.DUMMYFUNCTION("INDIRECT(""'收支紀錄'!L""&TO_TEXT(ROW()-$C$72))"),"") | M93: =IFERROR(__xludf.DUMMYFUNCTION("INDIRECT(""'收支紀錄'!M""&TO_TEXT(ROW()-$C$72))"),"運動健身") -> 運動健身 | N93: =IFERROR(__xludf.DUMMYFUNCTION("INDIRECT(""'收支紀錄'!N""&TO_TEXT(ROW()-$C$72))"),"") | O93: =IFERROR(__xludf.DUMMYFUNCTION("INDIRECT(""'收支紀錄'!O""&TO_TEXT(ROW()-$C$72))"),"") | P93: =IFERROR(__xludf.DUMMYFUNCTION("INDIRECT(""'收支紀錄'!P""&TO_TEXT(ROW()-$C$72))"),"") | Q93: =IFERROR(__xludf.DUMMYFUNCTION("INDIRECT(""'收支紀錄'!Q""&TO_TEXT(ROW()-$C$72))"),"") | R93: =IFERROR(__xludf.DUMMYFUNCTION("INDIRECT(""'收支紀錄'!R""&TO_TEXT(ROW()-$C$72))"),"") | S93: =IFERROR(__xludf.DUMMYFUNCTION("INDIRECT(""'收支紀錄'!S""&TO_TEXT(ROW()-$C$72))"),"") | T93: =IFERROR(__xludf.DUMMYFUNCTION("INDIRECT(""'收支紀錄'!T""&TO_TEXT(ROW()-$C$72))"),"") | U93: =IFERROR(__xludf.DUMMYFUNCTION("IF(T93=""是"",TEXTJOIN("""", TRUE, ""$"", TO_TEXT(C93), S93),"""")"),"")
A94: =IFERROR(__xludf.DUMMYFUNCTION("INDIRECT(""'收支紀錄'!A""&TO_TEXT(ROW()-$C$72))"),45487.51670461806) -> 45487.517 | B94: =IFERROR(__xludf.DUMMYFUNCTION("IF(ISBLANK(D94), """", IF(ISDATE(D94), D94, IF(D94=""今天"", A94, IF(D94=""昨天 (-1 day)"", A94-1, IF(D94=""前天 (-2 days)"", A94-2, IF(D94=""明天 (+1 day)"", A94+1, DATE(LEFT(D94,4), MID(D94,5,2), RIGHT(D94,2))))))))"),45487.0) -> 45487 | C94: =IFERROR(__xludf.DUMMYFUNCTION("INDIRECT(""'收支紀錄'!C""&TO_TEXT(ROW()-$C$72))"),930.0) -> 930 | D94: =IFERROR(__xludf.DUMMYFUNCTION("INDIRECT(""'收支紀錄'!D""&TO_TEXT(ROW()-$C$72))"),45487.0) -> 45487 | E94: =IFERROR(__xludf.DUMMYFUNCTION("INDIRECT(""'收支紀錄'!E""&TO_TEXT(ROW()-$C$72))"),"") | F94: =IFERROR(__xludf.DUMMYFUNCTION("INDIRECT(""'收支紀錄'!F""&TO_TEXT(ROW()-$C$72))"),"") | G94: =IFERROR(__xludf.DUMMYFUNCTION("INDIRECT(""'收支紀錄'!G""&TO_TEXT(ROW()-$C$72))"),"") | H94: =IFERROR(__xludf.DUMMYFUNCTION("INDIRECT(""'收支紀錄'!H""&TO_TEXT(ROW()-$C$72))"),"行車交通") -> 行車交通 | I94: =IFERROR(__xludf.DUMMYFUNCTION("INDIRECT(""'收支紀錄'!I""&TO_TEXT(ROW()-$C$72))"),"") | J94: =IFERROR(__xludf.DUMMYFUNCTION("INDIRECT(""'收支紀錄'!J""&TO_TEXT(ROW()-$C$72))"),"") | K94: =IFERROR(__xludf.DUMMYFUNCTION("INDIRECT(""'收支紀錄'!K""&TO_TEXT(ROW()-$C$72))"),"") | L94: =IFERROR(__xludf.DUMMYFUNCTION("INDIRECT(""'收支紀錄'!L""&TO_TEXT(ROW()-$C$72))"),"高鐵") -> 高鐵 | M94: =IFERROR(__xludf.DUMMYFUNCTION("INDIRECT(""'收支紀錄'!M""&TO_TEXT(ROW()-$C$72))"),"") | N94: =IFERROR(__xludf.DUMMYFUNCTION("INDIRECT(""'收支紀錄'!N""&TO_TEXT(ROW()-$C$72))"),"") | O94: =IFERROR(__xludf.DUMMYFUNCTION("INDIRECT(""'收支紀錄'!O""&TO_TEXT(ROW()-$C$72))"),"") | P94: =IFERROR(__xludf.DUMMYFUNCTION("INDIRECT(""'收支紀錄'!P""&TO_TEXT(ROW()-$C$72))"),"") | Q94: =IFERROR(__xludf.DUMMYFUNCTION("INDIRECT(""'收支紀錄'!Q""&TO_TEXT(ROW()-$C$72))"),"") | R94: =IFERROR(__xludf.DUMMYFUNCTION("INDIRECT(""'收支紀錄'!R""&TO_TEXT(ROW()-$C$72))"),"") | S94: =IFERROR(__xludf.DUMMYFUNCTION("INDIRECT(""'收支紀錄'!S""&TO_TEXT(ROW()-$C$72))"),"") | T94: =IFERROR(__xludf.DUMMYFUNCTION("INDIRECT(""'收支紀錄'!T""&TO_TEXT(ROW()-$C$72))"),"") | U94: =IFERROR(__xludf.DUMMYFUNCTION("IF(T94=""是"",TEXTJOIN("""", TRUE, ""$"", TO_TEXT(C94), S94),"""")"),"")
